Workbook
Name AUD: FX!$C$5
Name CHF: FX!$C$3
Name CNY: FX!$C$11
Name DKK: FX!$C$2
Name DKKUSD: #REF!
Name EUR: FX!$C$4
Name GBP: FX!$C$6
Name HKD: FX!$C$8
Name INR: FX!$C$10
Name JPY: FX!$C$7
Name KRW: FX!$C$9

Sheet Main
D2: =RANDBETWEEN(1,D304) -> 198 | H2: =SUM(H5:H458)-H15-H12-H9-H23-H20-H26-H50-China!F17 -> 6139258.2 | M2: =MIN(M5:M67) -> 45540 | O2: =AVERAGE(O5:O36) -> -0.066630371 | S2: EV/EPS | AB2: EPS | AO2: =AVERAGE(AO5:AO106) -> 0.061854076 | AP2: =AVERAGE(AP5:AP106) -> 0.044232656 | AQ2: =AVERAGE(AQ5:AQ106) -> 0.045486892 | AR2: =AVERAGE(AR5:AR106) -> 0.28833087
B3: R | C3: C | E3: Name | F3: Ticker | G3: Price | H3: MC | I3: NC | J3: EV | K3: Update | L3: SO | M3: Last | N3: NPV | O3: Upside | P3: ROIC | Q3: Terminal | R3: Discount | S3: 2022 | T3: 2023 | U3: 2024 | V3: 2025 | W3: 2026 | X3: 2027 | Y3: 2028 | Z3: 2029 | AA3: 2030 | AB3: 2022 | AC3: 2023 | AD3: 2024 | AE3: 2025 | AF3: 2026 | AG3: 2027 | AH3: 2028 | AI3: 2029 | AJ3: 2030 | AK3: 2031 | AL3: Founded | AM3: Location | AN3: Country | AO3: YTD | AP3: MTD | AQ3: M/M | AR3: Y/Y | AS3: 2025 | AT3: 2024 | AU3: 2023 | AV3: 2022 | AW3: 2021 | AX3: 2020 | BD3: 46199 | BE3: =+BD3-1 -> 46198 | BF3: =+BE3-1 -> 46197 | BG3: =+BF3-1 -> 46196 | BH3: =+BG3-1 -> 46195 | BI3: 46192 | BJ3: =+BH3-4 -> 46191 | BK3: =+BJ3-1 -> 46190 | BL3: =+BK3-1 -> 46189 | BM3: =+BL3-1 -> 46188 | BN3: =+BM3-3 -> 46185 | BO3: =+BN3-1 -> 46184 | BP3: =+BO3-1 -> 46183 | BQ3: =+BP3-1 -> 46182 | BR3: =+BQ3-1 -> 46181 | BS3: =+BR3-3 -> 46178 | BT3: =+BS3-1 -> 46177 | BU3: =+BT3-1 -> 46176 | BV3: =+BU3-1 -> 46175 | BW3: =+BV3-1 -> 46174 | BX3: =+BW3-3 -> 46171 | BY3: =+BX3-1 -> 46170 | BZ3: =+BY3-1 -> 46169 | CA3: =+BZ3-1 -> 46168 | CB3: =+CA3-4 -> 46164 | CC3: =+CB3-1 -> 46163 | CD3: =+CC3-1 -> 46162 | CE3: =+CD3-1 -> 46161 | CF3: =+CE3-1 -> 46160 | CG3: =+CF3-3 -> 46157 | CH3: =+CG3-1 -> 46156 | CI3: =+CH3-1 -> 46155 | CJ3: =+CI3-1 -> 46154 | CK3: =+CJ3-1 -> 46153 | CL3: =+CK3-3 -> 46150 | CM3: =+CL3-1 -> 46149 | CN3: =+CM3-1 -> 46148 | CO3: =+CN3-1 -> 46147 | CP3: =+CO3-1 -> 46146 | CQ3: =+CP3-3 -> 46143 | CR3: =+CQ3-1 -> 46142 | CS3: =+CR3-1 -> 46141 | CT3: =+CS3-1 -> 46140 | CU3: =+CT3-1 -> 46139 | CV3: =+CU3-3 -> 46136 | CW3: =+CV3-1 -> 46135 | CX3: =+CW3-1 -> 46134 | CY3: =+CX3-1 -> 46133 | CZ3: =+CY3-1 -> 46132 | DA3: =+CZ3-3 -> 46129 | DB3: =+DA3-1 -> 46128 | DC3: =+DB3-1 -> 46127 | DD3: =+DC3-1 -> 46126 | DE3: =+DD3-1 -> 46125 | DF3: =+DE3-3 -> 46122 | DG3: =+DF3-1 -> 46121 | DH3: =+DG3-1 -> 46120 | DI3: =+DH3-1 -> 46119 | DJ3: =+DI3-1 -> 46118 | DK3: =+DJ3-4 -> 46114 | DL3: =+DK3-1 -> 46113 | DM3: =+DL3-1 -> 46112 | DN3: =+DM3-1 -> 46111 | DO3: =+DN3-3 -> 46108 | DP3: =+DO3-1 -> 46107 | DQ3: =+DP3-1 -> 46106 | DR3: =+DQ3-1 -> 46105 | DS3: =+DR3-1 -> 46104 | DT3: =+DS3-3 -> 46101 | DU3: =+DT3-1 -> 46100 | DV3: =+DU3-1 -> 46099 | DW3: =+DV3-1 -> 46098 | DX3: =+DW3-1 -> 46097 | DY3: =+DX3-3 -> 46094 | DZ3: =+DY3-1 -> 46093 | EA3: =+DZ3-1 -> 46092 | EB3: =+EA3-1 -> 46091 | EC3: =+EB3-1 -> 46090 | ED3: =+EC3-3 -> 46087 | EE3: =+ED3-1 -> 46086 | EF3: =+EE3-1 -> 46085 | EG3: =+EF3-1 -> 46084 | EH3: =+EG3-1 -> 46083 | EI3: =+EH3-3 -> 46080 | EJ3: =+EI3-1 -> 46079 | EK3: =+EJ3-1 -> 46078 | EL3: =+EK3-1 -> 46077 | EM3: =+EL3-1 -> 46076 | EN3: =+EM3-3 -> 46073 | EO3: =+EN3-1 -> 46072 | EP3: =+EO3-1 -> 46071 | EQ3: =+EP3-1 -> 46070 | ER3: =+EQ3-4 -> 46066 | ES3: =+ER3-1 -> 46065 | ET3: =+ES3-1 -> 46064 | EU3: =+ET3-1 -> 46063 | EV3: =+EU3-1 -> 46062 | EW3: =+EV3-3 -> 46059 | EX3: =+EW3-1 -> 46058 | EY3: =+EX3-1 -> 46057 | EZ3: =+EY3-1 -> 46056 | FA3: =+EZ3-1 -> 46055 | FB3: =+FA3-3 -> 46052 | FC3: =+FB3-1 -> 46051 | FD3: =+FC3-1 -> 46050 | FE3: =+FD3-1 -> 46049 | FF3: =+FE3-1 -> 46048 | FG3: =+FF3-3 -> 46045 | FH3: =+FG3-1 -> 46044 | FI3: =+FH3-1 -> 46043 | FJ3: =+FI3-1 -> 46042 | FK3: =+FJ3-4 -> 46038 | FL3: =+FK3-1 -> 46037 | FM3: =+FL3-1 -> 46036 | FN3: =+FM3-1 -> 46035 | FO3: =+FN3-1 -> 46034 | FP3: =+FO3-3 -> 46031 | FQ3: =+FP3-1 -> 46030 | FR3: =+FQ3-1 -> 46029 | FS3: =+FR3-1 -> 46028 | FT3: =+FS3-1 -> 46027 | FU3: =+FT3-3 -> 46024 | FV3: =FU3-2 -> 46022 | FW3: =+FV3-1 -> 46021 | FX3: =+FW3-1 -> 46020 | FY3: =+FX3-3 -> 46017 | FZ3: =+FY3-2 -> 46015 | GA3: =+FZ3-1 -> 46014 | GB3: =+GA3-1 -> 46013 | GC3: =+GB3-3 -> 46010 | GD3: =+GC3-1 -> 46009 | GE3: =+GD3-1 -> 46008 | GF3: =+GE3-1 -> 46007 | GG3: =+GF3-1 -> 46006 | GH3: =+GG3-3 -> 46003 | GI3: =+GH3-1 -> 46002 | GJ3: =+GI3-1 -> 46001 | GK3: =+GJ3-1 -> 46000 | GL3: =+GK3-1 -> 45999 | GM3: =+GL3-3 -> 45996 | GN3: =+GM3-1 -> 45995 | GO3: =+GN3-1 -> 45994 | GP3: =+GO3-1 -> 45993 | GQ3: =+GP3-1 -> 45992 | GR3: =+GQ3-3 -> 45989 | GS3: =+GR3-2 -> 45987 | GT3: =+GS3-1 -> 45986 | GU3: =+GT3-1 -> 45985 | GV3: =+GU3-3 -> 45982 | GW3: =+GV3-1 -> 45981 | GX3: =+GW3-1 -> 45980 | GY3: =+GX3-1 -> 45979 | GZ3: =+GY3-1 -> 45978 | HA3: =+GZ3-3 -> 45975 | HB3: =+HA3-1 -> 45974 | HC3: =+HB3-1 -> 45973 | HD3: =+HC3-1 -> 45972 | HE3: =+HD3-1 -> 45971 | HF3: =HE3-3 -> 45968 | HG3: =+HF3-1 -> 45967 | HH3: =+HG3-1 -> 45966 | HI3: =+HH3-1 -> 45965 | HJ3: =+HI3-1 -> 45964 | HK3: =+HJ3-3 -> 45961 | HL3: =+HK3-1 -> 45960 | HM3: =+HL3-1 -> 45959 | HN3: =+HM3-1 -> 45958 | HO3: =+HN3-1 -> 45957 | HP3: =+HO3-3 -> 45954 | HQ3: =+HP3-1 -> 45953 | HR3: =+HQ3-1 -> 45952 | HS3: =+HR3-1 -> 45951 | HT3: =+HS3-1 -> 45950 | HU3: =+HT3-3 -> 45947 | HV3: =+HU3-1 -> 45946 | HW3: =+HV3-1 -> 45945 | HX3: =+HW3-1 -> 45944 | HY3: =+HX3-1 -> 45943 | HZ3: =+HY3-3 -> 45940 | IA3: =+HZ3-1 -> 45939 | IB3: =+IA3-1 -> 45938 | IC3: =+IB3-1 -> 45937 | ID3: =+IC3-1 -> 45936 | IE3: =+ID3-3 -> 45933 | IF3: =+IE3-1 -> 45932 | IG3: =+IF3-1 -> 45931 | IH3: =+IG3-1 -> 45930 | II3: =+IH3-1 -> 45929 | IJ3: =+II3-3 -> 45926 | IK3: =+IJ3-1 -> 45925 | IL3: =+IK3-1 -> 45924 | IM3: =+IL3-1 -> 45923 | IN3: =+IM3-1 -> 45922 | IO3: =+IN3-3 -> 45919 | IP3: =+IO3-1 -> 45918 | IQ3: =+IP3-1 -> 45917 | IR3: =+IQ3-1 -> 45916 | IS3: =+IR3-1 -> 45915 | IT3: =+IS3-3 -> 45912 | IU3: =+IT3-1 -> 45911 | IV3: =+IU3-1 -> 45910 | IW3: =+IV3-1 -> 45909 | IX3: =+IW3-1 -> 45908 | IY3: =+IX3-3 -> 45905 | IZ3: =+IY3-1 -> 45904 | JA3: =+IZ3-1 -> 45903 | JB3: =+JA3-1 -> 45902 | JC3: =+JB3-4 -> 45898 | JD3: =+JC3-1 -> 45897 | JE3: =+JD3-1 -> 45896 | JF3: =+JE3-1 -> 45895 | JG3: =+JF3-1 -> 45894 | JH3: =+JG3-3 -> 45891 | JI3: =+JH3-1 -> 45890 | JJ3: =+JI3-1 -> 45889 | JK3: =+JJ3-1 -> 45888 | JL3: =+JK3-1 -> 45887 | JM3: =+JL3-3 -> 45884 | JN3: =+JM3-1 -> 45883 | JO3: =+JN3-1 -> 45882 | JP3: =+JO3-1 -> 45881 | JQ3: =+JP3-1 -> 45880 | JR3: =+JQ3-3 -> 45877 | JS3: =+JR3-1 -> 45876 | JT3: =+JS3-1 -> 45875 | JU3: =+JT3-1 -> 45874 | JV3: =+JU3-1 -> 45873 | JW3: =+JV3-3 -> 45870 | JX3: =+JW3-1 -> 45869 | JY3: =+JX3-1 -> 45868 | JZ3: =+JY3-1 -> 45867 | KA3: =+JZ3-1 -> 45866 | KB3: =+KA3-3 -> 45863 | KC3: =+KB3-1 -> 45862 | KD3: =+KC3-1 -> 45861 | KE3: =+KD3-1 -> 45860 | KF3: =+KE3-1 -> 45859 | KG3: =+KF3-3 -> 45856 | KH3: =+KG3-1 -> 45855 | KI3: =+KH3-1 -> 45854 | KJ3: =+KI3-1 -> 45853 | KK3: =+KJ3-1 -> 45852 | KL3: =+KK3-3 -> 45849 | KM3: =+KL3-1 -> 45848 | KN3: =+KM3-1 -> 45847 | KO3: =+KN3-1 -> 45846 | KP3: =+KO3-1 -> 45845 | KQ3: =+KP3-4 -> 45841 | KR3: =+KQ3-1 -> 45840 | KS3: =+KR3-1 -> 45839 | KT3: =+KS3-1 -> 45838
S4: =TRIMMEAN(S5:S345,10%) -> 42.279125 | T4: =TRIMMEAN(T5:T345,10%) -> 35.327268 | U4: =TRIMMEAN(U5:U345,10%) -> 29.58952 | V4: =TRIMMEAN(V5:V345,10%) -> 24.145118 | W4: =TRIMMEAN(W5:W345,10%) -> 18.035849 | X4: =TRIMMEAN(X5:X345,10%) -> 16.263831 | Y4: =TRIMMEAN(Y5:Y345,10%) -> 14.91945 | Z4: =TRIMMEAN(Z5:Z345,10%) -> 14.27409 | AA4: =TRIMMEAN(AA5:AA345,10%) -> 13.223686 | AB4: - | AC4: - | AD4: - | AE4: - | AF4: - | AG4: - | AH4: - | AI4: - | AJ4: - | AK4: - | AL4: =AVERAGE(AL5:AL271) -> 1965.2188
A5: x | D5: 1 | E5: Eli Lilly | F5: LLY | G5: 1185.85 | H5: =+G5*L5 -> 1060149.9 | I5: =+[1]Main!$J$5-[1]Main!$J$6 -> -42102 | J5: =H5-I5 -> 1102251.9 | K5: Q226 | L5: =+[1]Main!$J$3 -> 894 | M5: 46243 | N5: =[1]Model!$GL$102 -> 1227.0562 | O5: =+N5/G5-1 -> 0.03474822 | P5: =[1]Model!$GL$98 -> 0.02 | Q5: =[1]Model!$GL$99 -> 0 | R5: =[1]Model!$GL$100 -> 0.07 | S5: =($J5/$L5)/AB5 -> 162.87239 | T5: =($J5/$L5)/AC5 -> 134.74797 | U5: =($J5/$L5)/AD5 -> 81.275146 | V5: =($J5/$L5)/AE5 -> 47.148909 | W5: =($J5/$L5)/AF5 -> 34.267481 | X5: =($J5/$L5)/AG5 -> 26.687099 | Y5: =($J5/$L5)/AH5 -> 23.06724 | Z5: =($J5/$L5)/AI5 -> 20.767121 | AA5: =($J5/$L5)/AJ5 -> 19.000523 | AB5: 7.57 | AC5: 9.15 | AD5: 15.17 | AE5: 26.15 | AF5: 35.98 | AG5: 46.2 | AH5: 53.45 | AI5: 59.37 | AJ5: 64.89 | AK5: 70.98 | AL5: 1876 | AM5: Indiana | AN5: United States | AO5: =BD5/FV5-1 -> 0.12416719 | AP5: =BD5/BX5-1 -> 0.093321267 | AQ5: =BD5/CA5-1 -> 0.13466198 | AR5: =BD5/KT5-1 -> 0.54980565 | BD5: 1208.12 | BE5: 1127.69 | BF5: 1117.26 | BG5: 1107.08 | BH5: 1102.08 | BJ5: 1098.57 | BK5: 1112 | BL5: 1122.5 | BM5: 1129.35 | BN5: 1133 | BO5: 1160.95 | BP5: 1136.37 | BQ5: 1144.68 | BR5: 1149.15 | BS5: 1131.42 | BT5: 1125.27 | BU5: 1078.78 | BV5: 1064.15 | BW5: 1082.2 | BX5: 1105 | BY5: 1126.8 | BZ5: 1082.92 | CA5: 1064.74 | CB5: 1065 | CC5: 1041.65 | CD5: 1018.87 | CE5: 1021.41 | CF5: 988.09 | CG5: 1004.92 | CH5: 1006.7 | CI5: 1015.75 | CJ5: 989.87 | CK5: 966.99 | CL5: 948.45 | CM5: 974.96 | CN5: 987.05 | CO5: 988.87 | CP5: 967.93 | CQ5: 963.33 | CR5: 934.6 | CS5: 851.21 | CT5: 874 | CU5: 868.27 | CV5: 883.96 | CW5: 917.65 | CX5: 921.48 | CY5: 903.02 | CZ5: 919.9 | DA5: 927.03 | DB5: 903.99 | DC5: 905.03 | DD5: 922.5 | DE5: 929.55 | DF5: 939.47 | DG5: 955.19 | DH5: 953.3 | DI5: 931.09 | DJ5: 927.06 | DK5: 935.58 | DL5: 954.52 | DM5: 919.77 | DN5: 886.63 | DO5: 878.24 | DP5: 897 | DQ5: 916.31 | DR5: 903.02 | DS5: 910.55 | DT5: 906.7 | DU5: 917.5 | DV5: 918.05 | DW5: 930.35 | DX5: 989.12 | DY5: 985.08 | DZ5: 977.25 | EA5: 999.84 | EB5: 1001.35 | EC5: 1008.39 | ED5: 990.33 | EE5: 983.26 | EF5: 1003.57 | EG5: 1007.73 | EH5: 1017.97 | EI5: 1051.99 | EJ5: 1022.02 | EK5: 1028.83 | EL5: 1042.15 | EM5: 1058.56 | EN5: 1009.52 | EO5: 1023.22 | EP5: 1020.56 | EQ5: 1036.05 | ER5: 1040 | ES5: 1038.27 | ET5: 1015.21 | EU5: 1025 | EV5: 1044.67 | EW5: 1058.18 | EX5: 1020.84 | EY5: 1107.12 | EZ5: 1003.46 | FA5: 1044.13 | FB5: 1037.15 | FC5: 1024.14 | FD5: 1023.8 | FE5: 1039.51 | FF5: 1062.75 | FG5: 1064.29 | FH5: 1087.38 | FI5: 1078.52 | FJ5: 1041.29 | FK5: 1038.4 | FL5: 1032.97 | FM5: 1073.29 | FN5: 1077.19 | FO5: 1081 | FP5: 1063.56 | FQ5: 1085.19 | FR5: 1108.09 | FS5: 1064.04 | FT5: 1041.51 | FU5: 1080.36 | FV5: 1074.68 | FW5: 1079.75 | FX5: 1078.73 | FY5: 1077.75 | FZ5: 1076.98 | GA5: 1071.64 | GB5: 1076.48 | GC5: 1071.44 | GD5: 1056.88 | GE5: 1041.79 | GF5: 1054.29 | GG5: 1062.19 | GH5: 1027.51 | GI5: 1009.38 | GJ5: 993.64 | GK5: 982.22 | GL5: 997.59 | GM5: 1010.31 | GN5: 1014.49 | GO5: 1033.56 | GP5: 1046.12 | GQ5: 1057.89 | GR5: 1075.47 | GS5: 1104.34 | GT5: 1109.94 | GU5: 1070.16 | GV5: 1059.7 | GW5: 1043.29 | GX5: 1049.6 | GY5: 1030.05 | GZ5: 1021.7 | HA5: 1025.28 | HB5: 1022.87 | HC5: 1017.78 | HD5: 988.62 | HE5: 966.64 | HF5: 924.37 | HG5: 937.44 | HH5: 925.81 | HI5: 906.86 | HJ5: 896.53 | HK5: 862.86 | HL5: 844.5 | HM5: 813.53 | HN5: 820.1 | HO5: 826.41 | HP5: 825.45 | HQ5: 821.04 | HR5: 812.43 | HS5: 799.57 | HT5: 808.96 | HU5: 802.83 | HV5: 819.38 | HW5: 826.57 | HX5: 812.35 | HY5: 819.4 | HZ5: 833.49 | IA5: 855.35 | IB5: 845.72 | IC5: 843.63 | ID5: 845.05 | IE5: 839.87 | IF5: 819.85 | IG5: 825.42 | IH5: 763 | II5: 726.51 | IJ5: 724.54 | IK5: 714.59 | IL5: 741.85 | IM5: 746.98 | IN5: 754.95 | IO5: 751.99 | IP5: 762.93 | IQ5: 760.13 | IR5: 764.71 | IS5: 748.19 | IT5: 755.39 | IU5: 756.28 | IV5: 754.62 | IW5: 750.61 | IX5: 738.64 | IY5: 727.21 | IZ5: 742.91 | JA5: 737.83 | JB5: 735.19 | JC5: 732.58 | JD5: 731.96 | JE5: 734.17 | JF5: 736.03 | JG5: 695.33 | JH5: 711.68 | JI5: 709.82 | JJ5: 705.44 | JK5: 703.21 | JL5: 698.05 | JM5: 701.23 | JN5: 684.43 | JO5: 660.49 | JP5: 639.43 | JQ5: 635.22 | JR5: 625.65 | JS5: 640.86 | JT5: 746.37 | JU5: 765.95 | JV5: 769 | JW5: 762.33 | JX5: 740.07 | JY5: 760.08 | JZ5: 762.95 | KA5: 808.11 | KB5: 812.69 | KC5: 805.43 | KD5: 798.89 | KE5: 776.44 | KF5: 762.18 | KG5: 771.71 | KH5: 761.5 | KI5: 789.8 | KJ5: 771.75 | KK5: 799.34 | KL5: 793.01 | KM5: 790.65 | KN5: 786.92 | KO5: 777.66 | KP5: 772.87 | KQ5: 780.67 | KR5: 779.28 | KS5: 775.9 | KT5: 779.53
A6: x | D6: 2 | E6: J&J | F6: JNJ | G6: 259.72 | H6: =+G6*L6 -> 625405.76 | I6: =+[2]Main!$L$5-[2]Main!$L$6 -> -28278 | J6: =H6-I6 -> 653683.76 | K6: Q226 | L6: =+[2]Main!$L$3 -> 2408 | M6: 46243 | N6: =[2]Model!$FV$85 -> 175.06971 | O6: =N6/G6-1 -> -0.32592903 | P6: =+[2]Model!$FV$78 -> 0.02 | Q6: =[2]Model!$FR$79 -> 0 | R6: =[2]Model!$FR$80 -> 0 | S6: =($J6/$L6)/AB6 -> 35.531853 | T6: =($J6/$L6)/AC6 -> 32.049983 | U6: =($J6/$L6)/AD6 -> 32.394195 | V6: =($J6/$L6)/AE6 -> 29.410981 | W6: =($J6/$L6)/AF6 -> 23.503321 | X6: =($J6/$L6)/AG6 -> 21.442603 | Y6: =($J6/$L6)/AH6 -> 19.22545 | Z6: =($J6/$L6)/AI6 -> 16.871557 | AA6: =($J6/$L6)/AJ6 -> 15.098073 | AB6: 7.64 | AC6: 8.47 | AD6: 8.38 | AE6: 9.23 | AF6: 11.55 | AG6: 12.66 | AH6: 14.12 | AI6: 16.09 | AJ6: 17.98 | AK6: 20.57 | AL6: 1886 | AM6: New Jersey | AN6: United States | AO6: =BD6/FV6-1 -> 0.23053878 | AP6: =BD6/BX6-1 -> 0.13016465 | AQ6: =BD6/CA6-1 -> 0.10635155 | AR6: =BD6/KT6-1 -> 0.66716858 | BD6: 254.66 | BE6: 244.88 | BF6: 241 | BG6: 239.08 | BH6: 231.29 | BJ6: 228.39 | BK6: 234.2 | BL6: 235.18 | BM6: 235.66 | BN6: 240.87 | BO6: 238.33 | BP6: 238.49 | BQ6: 237 | BR6: 232.16 | BS6: 232.77 | BT6: 228.17 | BU6: 223.24 | BV6: 222.89 | BW6: 223.51 | BX6: 225.33 | BY6: 230.8 | BZ6: 231.29 | CA6: 230.18 | CB6: 234.34 | CC6: 231.73 | CD6: 229.32 | CE6: 230 | CF6: 228.92 | CG6: 226.71 | CH6: 230.8 | CI6: 230.42 | CJ6: 224.26 | CK6: 221.43 | CL6: 221.32 | CM6: 222.51 | CN6: 224.62 | CO6: 225.55 | CP6: 224.2 | CQ6: 227.19 | CR6: 229.85 | CS6: 227.35 | CT6: 227.79 | CU6: 225.34 | CV6: 227.5 | CW6: 230.65 | CX6: 226.1 | CY6: 226.16 | CZ6: 230.69 | DA6: 234.18 | DB6: 234.54 | DC6: 238.67 | DD6: 240.1 | DE6: 237.96 | DF6: 238.46 | DG6: 241.31 | DH6: 241.3 | DI6: 238.41 | DJ6: 240.97 | DK6: 243.04 | DL6: 244.12 | DM6: 244.44 | DN6: 242.49 | DO6: 240.45 | DP6: 239.24 | DQ6: 239.93 | DR6: 235.27 | DS6: 235.42 | DT6: 235.37 | DU6: 237.6 | DV6: 237.28 | DW6: 238.11 | DX6: 243.19 | DY6: 241.52 | DZ6: 242.04 | EA6: 242.99 | EB6: 243.71 | EC6: 242.59 | ED6: 240.4 | EE6: 239.63 | EF6: 245.3 | EG6: 246.75 | EH6: 248.56 | EI6: 248.43 | EJ6: 243.47 | EK6: 245.17 | EL6: 246.28 | EM6: 245.84 | EN6: 242.49 | EO6: 246.91 | EP6: 244.99 | EQ6: 243.33 | ER6: 243.45 | ES6: 244.55 | ET6: 240.86 | EU6: 238.35 | EV6: 238.64 | EW6: 239.99 | EX6: 237.79 | EY6: 234.47 | EZ6: 233.1 | FA6: 230.75 | FB6: 227.25 | FC6: 227.29 | FD6: 227.72 | FE6: 224.44 | FF6: 221.49 | FG6: 220.14 | FH6: 218.49 | FI6: 218.01 | FJ6: 218.21 | FK6: 218.66 | FL6: 219.57 | FM6: 218.55 | FN6: 213.65 | FO6: 209.72 | FP6: 204.39 | FQ6: 205.75 | FR6: 207.49 | FS6: 204.79 | FT6: 204.31 | FU6: 207.35 | FV6: 206.95 | FW6: 206.91 | FX6: 207.56 | FY6: 207.63 | FZ6: 207.78 | GA6: 205.78 | GB6: 207.32 | GC6: 206.37 | GD6: 208.31 | GE6: 210.33 | GF6: 209.3 | GG6: 214.17 | GH6: 211.58 | GI6: 210.01 | GJ6: 206.54 | GK6: 199.96 | GL6: 201.62 | GM6: 201.93 | GN6: 202.48 | GO6: 205.33 | GP6: 205.42 | GQ6: 205.34 | GR6: 206.92 | GS6: 207.56 | GT6: 206.67 | GU6: 206.05 | GV6: 203.9 | GW6: 203.07 | GX6: 202.51 | GY6: 200 | GZ6: 199.58 | HA6: 195.93 | HB6: 195.25 | HC6: 194.39 | HD6: 193.83 | HE6: 188.41 | HF6: 186.57 | HG6: 186.97 | HH6: 186 | HI6: 186.86 | HJ6: 186.26 | HK6: 188.87 | HL6: 189.05 | HM6: 186.6 | HN6: 186.93 | HO6: 190.3 | HP6: 190.4 | HQ6: 192.47 | HR6: 192.94 | HS6: 191.88 | HT6: 193.72 | HU6: 193.22 | HV6: 192.12 | HW6: 191.17 | HX6: 190.85 | HY6: 190.9 | HZ6: 190.72 | IA6: 191.08 | IB6: 189.69 | IC6: 188.89 | ID6: 188.16 | IE6: 188.64 | IF6: 185.98 | IG6: 186.05 | IH6: 185.42 | II6: 181.62 | IJ6: 179.71 | IK6: 177.73 | IL6: 176.69 | IM6: 176.58 | IN6: 174.21 | IO6: 176.19 | IP6: 174.16 | IQ6: 177.2 | IR6: 176.46 | IS6: 177.4 | IT6: 178.06 | IU6: 178.5 | IV6: 175.79 | IW6: 176.96 | IX6: 178.13 | IY6: 178.43 | IZ6: 178.76 | JA6: 178 | JB6: 178.06 | JC6: 177.17 | JD6: 175.45 | JE6: 176.79 | JF6: 176.49 | JG6: 178.41 | JH6: 179.29 | JI6: 178.93 | JJ6: 178.84 | JK6: 177.8 | JL6: 176.25 | JM6: 176.64 | JN6: 174.72 | JO6: 174.42 | JP6: 172.78 | JQ6: 173.82 | JR6: 173.33 | JS6: 171.53 | JT6: 170.59 | JU6: 170.74 | JV6: 171.04 | JW6: 167.33 | JX6: 164.74 | JY6: 167.26 | JZ6: 168.11 | KA6: 166.22 | KB6: 168.3 | KC6: 169.56 | KD6: 169.1 | KE6: 167.93 | KF6: 164.36 | KG6: 163.7 | KH6: 162.98 | KI6: 164.78 | KJ6: 155.17 | KK6: 156.82 | KL6: 156.9 | KM6: 157.69 | KN6: 156.28 | KO6: 155.79 | KP6: 155.27 | KQ6: 156.01 | KR6: 155.56 | KS6: 155.92 | KT6: 152.75
A7: x | D7: 3 | E7: AbbVie | F7: ABBV | G7: 246.04 | H7: =+G7*L7 -> 435736.84 | I7: =+[3]Main!$K$5-[3]Main!$K$6 -> -63987 | J7: =H7-I7 -> 499723.84 | K7: Q226 | L7: =+[3]Main!$K$3 -> 1771 | M7: 46243 | N7: =[3]Model!$DX$79 -> 224.94848 | O7: =+N7/G7-1 -> -0.085723936 | P7: =[3]Model!$DX$77 -> 0 | Q7: =[3]Model!$DX$76 -> -0.01 | R7: =[3]Model!$DX$75 -> 0.06 | S7: =($J7/$L7)/AB7 -> 26.695405 | T7: =($J7/$L7)/AC7 -> 36.315371 | U7: =($J7/$L7)/AD7 -> 36.597981 | V7: =($J7/$L7)/AE7 -> 32.321928 | W7: =($J7/$L7)/AF7 -> 20.069021 | X7: =($J7/$L7)/AG7 -> 17.353655 | Y7: =($J7/$L7)/AH7 -> 15.887975 | Z7: =($J7/$L7)/AI7 -> 14.89026 | AA7: =($J7/$L7)/AJ7 -> 14.455453 | AB7: 10.57 | AC7: 7.77 | AD7: 7.71 | AE7: 8.73 | AF7: 14.06 | AG7: 16.26 | AH7: 17.76 | AI7: 18.95 | AJ7: 19.52 | AK7: 20.98 | AL7: 1888 | AM7: Illinois | AN7: United States | AO7: =BD7/FV7-1 -> 0.10880126 | AP7: =BD7/BX7-1 -> 0.16365056 | AQ7: =BD7/CA7-1 -> 0.18876689 | AR7: =BD7/KT7-1 -> 0.36488525 | BD7: 253.35 | BE7: 243.14 | BF7: 234.89 | BG7: 234.76 | BH7: 230.01 | BJ7: 216.49 | BK7: 221.23 | BL7: 222.47 | BM7: 221.59 | BN7: 227.73 | BO7: 224.77 | BP7: 224.95 | BQ7: 225.42 | BR7: 223.07 | BS7: 227.23 | BT7: 224.94 | BU7: 217.13 | BV7: 215.4 | BW7: 212.93 | BX7: 217.72 | BY7: 218.63 | BZ7: 215.4 | CA7: 213.12 | CB7: 215.7 | CC7: 214.5 | CD7: 212.3 | CE7: 213.76 | CF7: 209.41 | CG7: 210.39 | CH7: 210.77 | CI7: 208.5 | CJ7: 207.86 | CK7: 202.78 | CL7: 201.55 | CM7: 202.71 | CN7: 205.03 | CO7: 206.11 | CP7: 208.16 | CQ7: 206.6 | CR7: 211.32 | CS7: 203.89 | CT7: 197.69 | CU7: 197.38 | CV7: 198.71 | CW7: 200.95 | CX7: 200.5 | CY7: 205.12 | CZ7: 203.71 | DA7: 208.38 | DB7: 208.99 | DC7: 208.42 | DD7: 210.26 | DE7: 206.47 | DF7: 207.94 | DG7: 212.4 | DH7: 211.59 | DI7: 206.37 | DJ7: 206.69 | DK7: 208.84 | DL7: 214.98 | DM7: 217.49 | DN7: 213.12 | DO7: 209.4 | DP7: 211.12 | DQ7: 207.18 | DR7: 205.2 | DS7: 204.93 | DT7: 205.07 | DU7: 206.23 | DV7: 208.34 | DW7: 219.76 | DX7: 221.45 | DY7: 219.68 | DZ7: 225.37 | EA7: 227.68 | EB7: 227.01 | EC7: 227.45 | ED7: 230.11 | EE7: 232.35 | EF7: 236.19 | EG7: 233.86 | EH7: 234.26 | EI7: 232.08 | EJ7: 224.69 | EK7: 226.92 | EL7: 228.44 | EM7: 229.48 | EN7: 224.81 | EO7: 224.35 | EP7: 228.72 | EQ7: 232.86 | ER7: 231.5 | ES7: 227.5 | ET7: 220.89 | EU7: 222.44 | EV7: 223.26 | EW7: 223.43 | EX7: 219.02 | EY7: 217.11 | EZ7: 225.66 | FA7: 225.64 | FB7: 223.01 | FC7: 220.43 | FD7: 218.67 | FE7: 223.93 | FF7: 220.77 | FG7: 219.26 | FH7: 218.11 | FI7: 216.15 | FJ7: 214.04 | FK7: 214.35 | FL7: 216.75 | FM7: 221.89 | FN7: 220.75 | FO7: 220.04 | FP7: 220.08 | FQ7: 224.13 | FR7: 233.42 | FS7: 223.93 | FT7: 220.18 | FU7: 229.31 | FV7: 228.49 | FW7: 229.74 | FX7: 230.84 | FY7: 229.98 | FZ7: 229.89 | GA7: 228.79 | GB7: 227.91 | GC7: 226.82 | GD7: 222.82 | GE7: 224.31 | GF7: 223.67 | GG7: 227.45 | GH7: 223.32 | GI7: 223.98 | GJ7: 225.18 | GK7: 222.99 | GL7: 223.12 | GM7: 226.08 | GN7: 228.71 | GO7: 230.24 | GP7: 224.37 | GQ7: 225.11 | GR7: 227.7 | GS7: 227.66 | GT7: 231.8 | GU7: 229.51 | GV7: 236.28 | GW7: 229.45 | GX7: 232.91 | GY7: 233.87 | GZ7: 234 | HA7: 232.36 | HB7: 232.29 | HC7: 233.23 | HD7: 225.17 | HE7: 218.71 | HF7: 219.16 | HG7: 219.04 | HH7: 216.77 | HI7: 215.89 | HJ7: 211.96 | HK7: 218.04 | HL7: 228.2 | HM7: 225.14 | HN7: 227.54 | HO7: 228.03 | HP7: 227.99 | HQ7: 228.25 | HR7: 228.68 | HS7: 231.39 | HT7: 232.06 | HU7: 229.57 | HV7: 226.87 | HW7: 226.22 | HX7: 229.13 | HY7: 230.3 | HZ7: 230.5 | IA7: 230.69 | IB7: 231.24 | IC7: 232.83 | ID7: 230.19 | IE7: 233.91 | IF7: 236.56 | IG7: 244.38 | IH7: 231.54 | II7: 223.16 | IJ7: 220.61 | IK7: 218.54 | IL7: 219.99 | IM7: 222.61 | IN7: 222.59 | IO7: 222.47 | IP7: 221.99 | IQ7: 220.81 | IR7: 216.26 | IS7: 217.61 | IT7: 218.34 | IU7: 220.22 | IV7: 211.64 | IW7: 210.42 | IX7: 209.79 | IY7: 212.56 | IZ7: 213 | JA7: 211.86 | JB7: 211.92 | JC7: 210.4 | JD7: 207.92 | JE7: 208.06 | JF7: 208.36 | JG7: 207.55 | JH7: 210.6 | JI7: 209.5 | JJ7: 209.15 | JK7: 206.19 | JL7: 206.57 | JM7: 206.69 | JN7: 204.68 | JO7: 201.47 | JP7: 198.64 | JQ7: 198.64 | JR7: 198.05 | JS7: 198.86 | JT7: 196.3 | JU7: 198.55 | JV7: 197.19 | JW7: 195.22 | JX7: 189.02 | JY7: 189.31 | JZ7: 191.22 | KA7: 188.52 | KB7: 190.28 | KC7: 190.83 | KD7: 190.55 | KE7: 187.11 | KF7: 184.85 | KG7: 189.26 | KH7: 191.4 | KI7: 190.58 | KJ7: 186.39 | KK7: 191.52 | KL7: 192.45 | KM7: 195 | KN7: 190.62 | KO7: 189.77 | KP7: 187.63 | KQ7: 189.28 | KR7: 190.75 | KS7: 189.99 | KT7: 185.62
A8: x | D8: 4 | E8: Merck | F8: MRK | G8: 128.58 | H8: =+G8*L8 -> 317570.02 | I8: =+[4]Main!$J$5-[4]Main!$J$6 -> -45543 | J8: =H8-I8 -> 363113.02 | K8: Q226 | L8: =+[4]Main!$J$3 -> 2469.8244 | M8: 46243 | N8: =[4]Model!$EQ$115 -> 82.709451 | O8: =N8/G8-1 -> -0.35674715 | P8: =[4]Model!$EQ$111 -> 0.01 | Q8: =[4]Model!$EQ$112 -> -0.01 | R8: =[4]Model!$EQ$113 -> 0.07 | S8: =($J8/$L8)/AB8 -> 21.557151 | T8: =($J8/$L8)/AC8 -> 21.748487 | U8: =($J8/$L8)/AD8 -> 21.002825 | V8: =($J8/$L8)/AE8 -> 18.286041 | W8: =($J8/$L8)/AF8 -> 15.125491 | X8: =($J8/$L8)/AG8 -> 15.410878 | Y8: =($J8/$L8)/AH8 -> 14.068878 | Z8: =($J8/$L8)/AI8 -> 14.556413 | AA8: =($J8/$L8)/AJ8 -> 14.643404 | AB8: 6.82 | AC8: 6.76 | AD8: 7 | AE8: 8.04 | AF8: 9.72 | AG8: 9.54 | AH8: 10.45 | AI8: 10.1 | AJ8: 10.04 | AK8: 9.79 | AL8: 1919 | AM8: New Jersey | AN8: United States | AO8: =BD8/FV8-1 -> 0.22230667 | AP8: =BD8/BX8-1 -> 0.083726415 | AQ8: =BD8/CA8-1 -> 0.07467424 | AR8: =BD8/KT8-1 -> 0.62531582 | BD8: 128.66 | BE8: 125.45 | BF8: 120.6 | BG8: 119.6 | BH8: 115.48 | BJ8: 113.87 | BK8: 115.44 | BL8: 115.17 | BM8: 114.9 | BN8: 119.05 | BO8: 120.76 | BP8: 119.09 | BQ8: 119.6 | BR8: 119.52 | BS8: 120.79 | BT8: 120.26 | BU8: 114.7 | BV8: 115.65 | BW8: 115.17 | BX8: 118.72 | BY8: 119.89 | BZ8: 120.24 | CA8: 119.72 | CB8: 122.41 | CC8: 115.88 | CD8: 113 | CE8: 114.24 | CF8: 112.56 | CG8: 111.38 | CH8: 113.41 | CI8: 113.45 | CJ8: 112.37 | CK8: 111.28 | CL8: 111.38 | CM8: 112.3 | CN8: 113.56 | CO8: 113.15 | CP8: 113.11 | CQ8: 112.16 | CR8: 109.18 | CS8: 110.95 | CT8: 110.03 | CU8: 110.23 | CV8: 111.9 | CW8: 114.62 | CX8: 112.89 | CY8: 112.56 | CZ8: 117.1 | DA8: 119.07 | DB8: 115.46 | DC8: 117.9 | DD8: 119.96 | DE8: 120.15 | DF8: 121.42 | DG8: 122.68 | DH8: 123.18 | DI8: 119.28 | DJ8: 120.85 | DK8: 120.87 | DL8: 120.84 | DM8: 120.29 | DN8: 118.1 | DO8: 119.63 | DP8: 118.93 | DQ8: 119.37 | DR8: 116.37 | DS8: 115.68 | DT8: 114.18 | DU8: 114.2 | DV8: 114.5 | DW8: 115.87 | DX8: 115.43 | DY8: 115.61 | DZ8: 115.91 | EA8: 116.21 | EB8: 117.09 | EC8: 117.11 | ED8: 115.79 | EE8: 116.07 | EF8: 120.28 | EG8: 119.83 | EH8: 121.41 | EI8: 123.82 | EJ8: 119.3 | EK8: 122.46 | EL8: 123.93 | EM8: 123.82 | EN8: 122.26 | EO8: 121.86 | EP8: 121.66 | EQ8: 121.57 | ER8: 121.41 | ES8: 119.24 | ET8: 119.31 | EU8: 117.15 | EV8: 117.65 | EW8: 121.93 | EX8: 119.75 | EY8: 118.33 | EZ8: 115.84 | FA8: 113.37 | FB8: 110.27 | FC8: 108.34 | FD8: 106.9 | FE8: 107.92 | FF8: 107.4 | FG8: 108.18 | FH8: 109.18 | FI8: 111.11 | FJ8: 109.45 | FK8: 108.83 | FL8: 110.97 | FM8: 111.01 | FN8: 108.26 | FO8: 109.19 | FP8: 110.53 | FQ8: 110.99 | FR8: 108.6 | FS8: 108.87 | FT8: 107.44 | FU8: 106.45 | FV8: 105.26 | FW8: 106.06 | FX8: 106.62 | FY8: 106.78 | FZ8: 106.45 | GA8: 105.04 | GB8: 104.72 | GC8: 101.09 | GD8: 100.69 | GE8: 99.18 | GF8: 98.27 | GG8: 100.26 | GH8: 100.3 | GI8: 99.01 | GJ8: 97.62 | GK8: 96.89 | GL8: 98.93 | GM8: 99.72 | GN8: 100.89 | GO8: 102.27 | GP8: 101.03 | GQ8: 101.83 | GR8: 104.83 | GS8: 104.63 | GT8: 105.66 | GU8: 100.4 | GV8: 97.76 | GW8: 94.97 | GX8: 95.05 | GY8: 96.43 | GZ8: 92.86 | HA8: 92.92 | HB8: 92.93 | HC8: 91.45 | HD8: 90.95 | HE8: 86.75 | HF8: 86.28 | HG8: 85.78 | HH8: 84.39 | HI8: 83.86 | HJ8: 82.49 | HK8: 85.98 | HL8: 86.28 | HM8: 86.58 | HN8: 87.03 | HO8: 88 | HP8: 87.49 | HQ8: 87.18 | HR8: 87.61 | HS8: 87.62 | HT8: 86.32 | HU8: 84.79 | HV8: 83.92 | HW8: 84.11 | HX8: 84.7 | HY8: 85.7 | HZ8: 85.99 | IA8: 87.5 | IB8: 86.4 | IC8: 87.61 | ID8: 88.8 | IE8: 89.19 | IF8: 89.51 | IG8: 90.13 | IH8: 83.93 | II8: 78.58 | IJ8: 78.56 | IK8: 77.6 | IL8: 79.67 | IM8: 79.96 | IN8: 80.4 | IO8: 81.51 | IP8: 81.53 | IQ8: 81.14 | IR8: 81.09 | IS8: 81.02 | IT8: 82.81 | IU8: 85.15 | IV8: 84.03 | IW8: 84.61 | IX8: 84.09 | IY8: 84.71 | IZ8: 84.05 | JA8: 84.18 | JB8: 85.48 | JC8: 84.12 | JD8: 83.21 | JE8: 84.07 | JF8: 84.99 | JG8: 85.31 | JH8: 87.37 | JI8: 86.08 | JJ8: 84.66 | JK8: 84.93 | JL8: 84.22 | JM8: 84.21 | JN8: 82.76 | JO8: 82.71 | JP8: 80.3 | JQ8: 80.03 | JR8: 80.69 | JS8: 80.37 | JT8: 79.44 | JU8: 80.79 | JV8: 79.86 | JW8: 79.29 | JX8: 78.12 | JY8: 81.75 | JZ8: 82.63 | KA8: 84.06 | KB8: 84.71 | KC8: 84.11 | KD8: 83.98 | KE8: 81.61 | KF8: 79.31 | KG8: 79.96 | KH8: 81.52 | KI8: 82.43 | KJ8: 81.52 | KK8: 83.67 | KL8: 83.36 | KM8: 84.02 | KN8: 83.71 | KO8: 81.37 | KP8: 80.9 | KQ8: 80.93 | KR8: 82.39 | KS8: 81.81 | KT8: 79.16
A9: x | D9: 5 | E9: Novartis | F9: NVS | G9: 157.44 | H9: =+G9*L9 -> 301340.16 | I9: =+[5]Main!$K$6-[5]Main!$K$7 -> -39400 | J9: =H9-I9 -> 340740.16 | K9: Q126 | L9: =+[5]Main!$K$4 -> 1914 | M9: 46227 | S9: =($J9/$L9)/AB9 -> 43.848562 | T9: =($J9/$L9)/AC9 -> 33.275731 | U9: =($J9/$L9)/AD9 -> 26.650473 | V9: =($J9/$L9)/AE9 -> 23.18036 | W9: =($J9/$L9)/AF9 -> 20.1614 | X9: =($J9/$L9)/AG9 -> 18.147315 | Y9: =($J9/$L9)/AH9 -> 16.392741 | Z9: =($J9/$L9)/AI9 -> 15.202832 | AA9: =($J9/$L9)/AJ9 -> 14.438375 | AB9: 4.06 | AC9: 5.35 | AD9: 6.68 | AE9: 7.68 | AF9: 8.83 | AG9: 9.81 | AH9: 10.86 | AI9: 11.71 | AJ9: 12.33 | AK9: 11.89 | AM9: Basel | AN9: Switzerland
A10: x | D10: =+D9 -> 5 | E10: Novartis | F10: NOVN VX | G10: 126.6 | H10: =+G10*L10/CHF -> 296225.43 | I10: =+[5]Main!$K$6-[5]Main!$K$7 -> -39400 | J10: =H10-I10 -> 335625.43 | K10: Q126 | L10: =+[5]Main!$K$4 -> 1914 | M10: 46227 | N10: - | O10: - | P10: - | Q10: - | R10: - | S10: - | T10: - | U10: - | V10: - | W10: - | X10: - | Y10: - | Z10: - | AA10: - | AB10: - | AC10: - | AD10: - | AE10: - | AF10: - | AG10: - | AH10: - | AI10: - | AJ10: - | AK10: - | AM10: Basel | AN10: Switzerland
A11: x | D11: =+D10+1 -> 6 | E11: Roche | F11: ROP SW | G11: 353.6 | H11: =+L11*G11 -> 281465.6 | I11: =+[6]Main!$J$5-[6]Main!$J$6 -> -16160 | J11: =H11-I11 -> 297625.6 | K11: Q425 | L11: =+[6]Main!$J$3 -> 796 | M11: 46227 | S11: - | T11: - | U11: =($J11/$L11)/AD11 -> 16.435231 | V11: =($J11/$L11)/AE11 -> 19.545296 | W11: =($J11/$L11)/AF11 -> 18.310554 | X11: =($J11/$L11)/AG11 -> 17.127875 | Y11: =($J11/$L11)/AH11 -> 15.86345 | Z11: =($J11/$L11)/AI11 -> 14.896474 | AA11: =($J11/$L11)/AJ11 -> 14.061734 | AB11: 19.55 | AC11: 19.27 | AD11: 22.75 | AE11: 19.13 | AF11: 20.42 | AG11: 21.83 | AH11: 23.57 | AI11: 25.1 | AJ11: 26.59 | AK11: 28.32 | AL11: 1896 | AM11: Basel | AN11: Switzerland | AP11: =BD11/BW11-1 -> 0.058601134 | AQ11: =BD11/BZ11-1 -> 0.015412511 | BD11: 336 | BE11: 335.3 | BF11: 332 | BG11: 325.2 | BH11: 318.6 | BI11: 319.8 | BJ11: 319 | BK11: 327.8 | BL11: 324 | BM11: 326.1 | BN11: 330 | BO11: 325.3 | BP11: 323.9 | BQ11: 318.8 | BR11: 322.7 | BS11: 327.1 | BT11: 324.6 | BU11: 311.6 | BV11: 309.7 | BW11: 317.4 | BX11: 329.3 | BY11: 328.9 | BZ11: 330.9 | CA11: 331.2 | CB11: 334.5 | CC11: 330.4 | CD11: 328.1 | CE11: 329.5 | CF11: 321.7 | CG11: 322.8 | CI11: 320 | CJ11: 321.5 | CK11: 319.4 | CL11: 315.3 | CM11: 318.3 | CN11: 321.9 | CO11: 318.5 | CP11: 316.5 | CR11: 318.4 | CS11: 317.3 | CT11: 321.1 | CU11: 321.2 | CV11: 322 | CW11: 324.9 | CX11: 313.1 | CY11: 317.2 | CZ11: 320.9 | DA11: 320 | DB11: 313.5 | DC11: 317 | DD11: 318.1 | DE11: 317.2 | DF11: 315.6 | DG11: 316.7 | DH11: 314.1 | DI11: 311.3 | DK11: 318 | DL11: 318.3 | DM11: 314.7 | DN11: 314.1 | DO11: 312.5 | DP11: 312.8 | DQ11: 312 | DR11: 305.8 | DS11: 303.9 | DT11: 300.9 | DU11: 305.7 | DV11: 314.8 | DW11: 323.9
A12: x | D12: =+D11+1 -> 7 | E12: AstraZeneca | F12: AZN | G12: 169.64 | H12: =+G12*L12 -> 264808.04 | I12: =+[7]Main!$K$5-[7]Main!$K$6 -> -25944 | J12: =H12-I12 -> 290752.04 | K12: Q126 | L12: =+[7]Main!$K$3 -> 1561 | M12: 46227 | S12: =($J12/$L12)/AB12 -> 175.71709 | T12: =($J12/$L12)/AC12 -> 97.010477 | U12: =($J12/$L12)/AD12 -> 82.052914 | V12: =($J12/$L12)/AE12 -> 41.29936 | W12: =($J12/$L12)/AF12 -> 18.136331 | X12: =($J12/$L12)/AG12 -> 16.253064 | Y12: =($J12/$L12)/AH12 -> 14.643091 | Z12: =($J12/$L12)/AI12 -> 12.91679 | AA12: =($J12/$L12)/AJ12 -> 11.455112 | AB12: 1.06 | AC12: 1.92 | AD12: 2.27 | AE12: 4.51 | AF12: 10.27 | AG12: 11.46 | AH12: 12.72 | AI12: 14.42 | AJ12: 16.26 | AK12: 17.23 | AM12: London | AN12: United Kingdom | AO12: =BD12/FV12-1 -> 0.073561254 | AP12: =BD12/BX12-1 -> 0.014757365 | AQ12: =BD12/CA12-1 -> 0.0065174422 | AR12: =BD12/KS12-1 -> 0.3485792 | BD12: 188.41 | BE12: 185.68 | BF12: 183.02 | BG12: 181.02 | BH12: 176.43 | BJ12: 174.93 | BK12: 177.89 | BL12: 178.71 | BM12: 177.27 | BN12: 178.75 | BO12: 182.28 | BP12: 178.96 | BQ12: 183.43 | BR12: 181.55 | BS12: 185.95 | BT12: 181.8 | BU12: 176.28 | BV12: 177.45 | BW12: 179.71 | BX12: 185.67 | BY12: 185.33 | BZ12: 185.65 | CA12: 187.19 | CB12: 187.03 | CC12: 189.75 | CD12: 187.46 | CE12: 184.64 | CF12: 183.92 | CG12: 181.58 | CH12: 184.96 | CI12: 187.72 | CJ12: 184.54 | CK12: 181.86 | CL12: 182.85 | CM12: 182.52 | CN12: 184.92 | CO12: 181.24 | CP12: 183.46 | CQ12: 184.74 | CR12: 187.37 | CS12: 185.2 | CT12: 186.68 | CU12: 187.51 | CV12: 189.75 | CW12: 192.3 | CX12: 194.81 | CY12: 195.78 | CZ12: 200.69 | DA12: 204.8 | DB12: 200.47 | DC12: 201.21 | DD12: 204.38 | DE12: 202.24 | DF12: 204.03 | DG12: 204.99 | DH12: 204.27 | DI12: 200.81 | DJ12: 202.83 | DK12: 203.49 | DL12: 200.73 | DM12: 197.22 | DN12: 193.88 | DO12: 188.42 | DP12: 183.4 | DQ12: 187.14 | DR12: 185.78 | DS12: 184.07 | DT12: 183.6 | DU12: 188.93 | DV12: 188.42 | DW12: 191.29 | DX12: 192.01 | DY12: 189.9 | DZ12: 192.5 | EA12: 193.31 | EB12: 194.99 | EC12: 194.95 | ED12: 194.22 | EE12: 197.52 | EF12: 201.53 | EG12: 201.76 | EH12: 203.73 | EI12: 208.45 | EJ12: 203.98 | EK12: 205.79 | EL12: 206.61 | EM12: 204.94 | EN12: 204.2 | EO12: 208.62 | EP12: 208.67 | EQ12: 209.48 | ER12: 205.55 | ES12: 204.52 | ET12: 204.76 | EU12: 193.4 | EV12: 188.01 | EW12: 193.03 | EX12: 187.16 | EY12: 187.45 | EZ12: 184.32 | FA12: 188.41 | FB12: 187.1 | FC12: 183.17 | FD12: 187.8 | FE12: 188.065 | FF12: 179.05 | FG12: 177.5 | FH12: 179.5 | FI12: 175 | FJ12: 183.2 | FK12: 191.125 | FL12: 188.835 | FM12: 190.23 | FN12: 188.66 | FO12: 185.4799 | FP12: 190.985 | FQ12: 188.5 | FR12: 190.775 | FS12: 190.49 | FT12: 179.057 | FU12: 182.675 | FV12: 175.5 | FW12: 180.85 | FX12: 187.06 | FY12: 181.275 | FZ12: 186.4 | GA12: 183 | GB12: 180.75 | GC12: 181.23 | GD12: 180.5399 | GE12: 184.75 | GG12: 183.86 | GJ12: 181.92 | GK12: 179.0999 | GL12: 180.94 | GM12: 179.4875 | GO12: 183.275 | GP12: 179.0999 | GQ12: 180.35 | GR12: 183.74 | GS12: 188.5 | GT12: 187.72 | GU12: 182.7 | GV12: 182.58 | GW12: 177.85 | GX12: 179.82 | GY12: 175.2049 | GZ12: 175.245 | HA12: 174.8249 | HB12: 177.5 | HC12: 175.66 | HD12: 175.2 | HE12: 174.9 | HF12: 166.17 | HG12: 169 | HI12: 165.26 | HJ12: 161.9 | HM12: 163.675 | HN12: 165.58 | HO12: 163.99 | HP12: 163.75 | HQ12: 168.24 | HS12: 168.28 | HT12: 166.9799 | HU12: 170.88 | HV12: 169.12 | HW12: 168.065 | HX12: 169.1 | HZ12: 169.3353 | IA12: 169.85 | IB12: 172.1 | IC12: 170 | ID12: 172.3 | IE12: 170.51 | IF12: 164.675 | IG12: 162.555 | IH12: 149.5 | II12: 146.0999 | IJ12: 146.16 | IK12: 149.75 | IL12: 149.0399 | IM12: 150.74 | IN12: 156.82 | IO12: 154.38 | IP12: 153.385 | IQ12: 156.025 | IR12: 153.0028 | IS12: 154.58 | IT12: 159.56 | IU12: 162 | IV12: 160.1399 | IW12: 160.5399 | IY12: 164.5 | IZ12: 162 | JA12: 162.2599 | JB12: 160.66 | JC12: 161.13 | JD12: 158.1999 | JE12: 160.65 | JF12: 160.3 | JG12: 162.98 | JH12: 157.09 | JJ12: 157.8 | JL12: 160.46 | JM12: 155.5 | JN12: 155.75 | JO12: 154.3 | JP12: 148.28 | JQ12: 146.12 | JR12: 141.772 | JS12: 147.235 | JT12: 148.68 | JU12: 150.29 | JV12: 150.32 | JW12: 147.5 | JX12: 147.39 | JY12: 155.67 | JZ12: 150.48 | KA12: 144.1 | KC12: 146.92 | KD12: 147.3 | KE12: 141.9 | KF12: 139.7 | KI12: 142.02 | KJ12: 140.4 | KK12: 143.15 | KL12: 140.2599 | KN12: 141.4 | KO12: 140.15 | KP12: 142.63 | KQ12: 140.685 | KR12: 143.88 | KS12: 139.71
A13: x | D13: =+D12 -> 7 | E13: AstraZeneca | F13: AZN LN | G13: 12632 | H13: =+G13*L13/100*GBP -> 262769.42 | I13: =+[7]Main!$K$5-[7]Main!$K$6 -> -25944 | J13: =H13-I13 -> 288713.42 | K13: Q126 | L13: =+[7]Main!$K$3 -> 1561 | M13: =+M12 -> 46227 | N13: - | O13: - | P13: - | Q13: - | R13: - | S13: - | T13: - | U13: - | V13: - | W13: - | X13: - | Y13: - | Z13: - | AA13: - | AB13: - | AC13: - | AD13: - | AE13: - | AF13: - | AG13: - | AH13: - | AI13: - | AJ13: - | AK13: - | AM13: London | AN13: United Kingdom
A14: x | D14: =+D13+1 -> 8 | E14: Amgen | F14: AMGN | G14: 394 | H14: =+G14*L14 -> 214336 | I14: =[8]Main!$J$5-[8]Main!$J$6 -> -45300 | J14: =H14-I14 -> 259636 | K14: Q126 | L14: =[8]Main!$J$3 -> 544 | M14: 46204 | N14: =+[8]Model!$EU$60 -> 384.37785 | O14: =N14/G14-1 -> -0.024421702 | P14: =+[8]Model!$EU$56 -> 0.01 | Q14: =+[8]Model!$EU$57 -> -0.02 | R14: =+[8]Model!$EU$58 -> 0.08 | S14: =($J14/$L14)/AB14 -> 35.804356 | T14: =($J14/$L14)/AC14 -> 37.729017 | U14: =($J14/$L14)/AD14 -> 55.112247 | V14: =($J14/$L14)/AE14 -> 34.262172 | W14: =($J14/$L14)/AF14 -> 20.85068 | X14: =($J14/$L14)/AG14 -> 19.820268 | Y14: =($J14/$L14)/AH14 -> 18.879433 | Z14: =($J14/$L14)/AI14 -> 17.768878 | AA14: =($J14/$L14)/AJ14 -> 16.746388 | AB14: 13.33 | AC14: 12.65 | AD14: 8.66 | AE14: 13.93 | AF14: 22.89 | AG14: 24.08 | AH14: 25.28 | AI14: 26.86 | AJ14: 28.5 | AK14: 29.64 | AL14: 1980 | AM14: California | AN14: United States | AO14: =BD14/FV14-1 -> 0.09477254 | AP14: =BD14/BX14-1 -> 0.063956768 | AQ14: =BD14/CA14-1 -> 0.066648806 | AR14: =BD14/KT14-1 -> 0.28337094 | BD14: 358.33 | BE14: 352.82 | BF14: 351.43 | BG14: 347.01 | BH14: 344.72 | BJ14: 337.6 | BK14: 341.66 | BL14: 347.84 | BM14: 350.53 | BN14: 355.2 | BO14: 354.06 | BP14: 337.73 | BQ14: 344.565 | BR14: 345.73 | BS14: 349.58 | BT14: 345.6 | BU14: 338.22 | BV14: 328.26 | BW14: 329.13 | BX14: 336.79 | BY14: 336.48 | BZ14: 336.06 | CA14: 335.94 | CB14: 339.3 | CC14: 337.42 | CD14: 331.57 | CE14: 330.75 | CF14: 324.39 | CG14: 326.31 | CH14: 336.23 | CI14: 336.45 | CJ14: 336.29 | CK14: 329.59 | CL14: 331.7 | CM14: 329.09 | CN14: 331.11 | CO14: 329.59 | CP14: 323.85 | CQ14: 329.82 | CR14: 346.25 | CS14: 338.02 | CT14: 339.57 | CU14: 340.18 | CV14: 344.55 | CW14: 348.62 | CX14: 345.92 | CY14: 344.86 | CZ14: 350.16 | DA14: 355.3 | DB14: 349.39 | DC14: 348.22 | DD14: 350.95 | DE14: 349.82 | DF14: 351.02 | DG14: 355.6 | DH14: 349.81 | DI14: 340 | DJ14: 342.57 | DK14: 347.94 | DL14: 353.28 | DM14: 351.85 | DN14: 349 | DO14: 348.77 | DP14: 353.16 | DQ14: 353.93 | DR14: 348.43 | DS14: 349.77 | DT14: 347.8 | DU14: 349.92 | DV14: 351.48 | DW14: 361.13 | DX14: 366.25 | DY14: 366.21 | DZ14: 367.79 | EA14: 377.64 | EB14: 375.43 | EC14: 376.97 | ED14: 369.53 | EE14: 367.6 | EF14: 379.27 | EG14: 377 | EH14: 385.7 | EI14: 388.16 | EJ14: 379.33 | EK14: 384.33 | EL14: 382.87 | EM14: 379.42 | EN14: 374.75 | EO14: 375.5 | EP14: 379.73 | EQ14: 373.36 | ER14: 369.19 | ES14: 366.2 | ET14: 366.58 | EU14: 364.65 | EV14: 375.82 | EW14: 384.32 | EX14: 367.8 | EY14: 366.2 | EZ14: 338.59 | FA14: 344.68 | FB14: 341.88 | FC14: 342.94 | FD14: 342.22 | FE14: 351.32 | FF14: 349.69 | FG14: 344.75 | FH14: 347.07 | FI14: 343.6 | FJ14: 331 | FK14: 330.41 | FL14: 330.03 | FM14: 328.97 | FN14: 324.3 | FO14: 325.54 | FP14: 326.1 | FQ14: 330.11 | FR14: 341.64 | FS14: 330.17 | FT14: 320.72 | FU14: 327.64 | FV14: 327.31 | FW14: 328.69 | FX14: 329.63 | FY14: 332.93 | FZ14: 333.96 | GA14: 331.49 | GB14: 331.39 | GC14: 327.38 | GD14: 324.42 | GE14: 326.01 | GF14: 326.74 | GG14: 325.31 | GH14: 317.74 | GI14: 317.38 | GJ14: 315.38 | GK14: 313.85 | GL14: 321.23 | GM14: 329.89 | GN14: 340.16 | GO14: 345.42 | GP14: 338.36 | GQ14: 337.49 | GR14: 345.46 | GS14: 344.57 | GT14: 341.11 | GU14: 334.3 | GV14: 337.54 | GW14: 336.07 | GX14: 342.4 | GY14: 343.99 | GZ14: 341.71 | HA14: 336.74 | HB14: 336 | HC14: 336.28 | HD14: 338.45 | HE14: 323.66 | HF14: 320.2 | HG14: 315.59 | HH14: 319.86 | HI14: 296.7 | HJ14: 296.3 | HK14: 298.43 | HL14: 292 | HM14: 291.77 | HN14: 292.09 | HO14: 291.16 | HP14: 291.76 | HQ14: 292.89 | HR14: 295.98 | HS14: 301.14 | HT14: 303.33 | HU14: 298.81 | HV14: 295.81 | HW14: 297.32 | HX14: 293.85 | HY14: 292.405 | HZ14: 290.13 | IA14: 295.43 | IB14: 294.62 | IC14: 295.54 | ID14: 294.12 | IE14: 297.89 | IF14: 297.4 | IG14: 298.5 | IH14: 282.2 | II14: 273.97 | IJ14: 272.98 | IK14: 271.18 | IL14: 279.22 | IM14: 286.81 | IN14: 286 | IO14: 285.41 | IP14: 275.83 | IQ14: 274.71 | IR14: 273.085 | IS14: 274.4 | IT14: 276.39 | IU14: 282.73 | IV14: 278.51 | IW14: 279.97 | IX14: 280.19 | IY14: 283.64 | IZ14: 280.1 | JA14: 283.85 | JB14: 286.92 | JC14: 287.71 | JD14: 285.61 | JE14: 287.97 | JF14: 289.58 | JG14: 288.47 | JH14: 293.72 | JI14: 295.76 | JJ14: 296.45 | JK14: 295.55 | JL14: 292.62 | JM14: 296.47 | JN14: 290.29 | JO14: 289.33 | JP14: 284.98 | JQ14: 285.09 | JR14: 288.23 | JS14: 284.7 | JT14: 284.67 | JU14: 300.08 | JV14: 301.94 | JW14: 296.88 | JX14: 295.1 | JY14: 301.37 | JZ14: 303.56 | KA14: 301.29 | KB14: 306.58 | KC14: 308.55 | KD14: 309.22 | KE14: 305.69 | KF14: 295.87 | KG14: 294.76 | KH14: 298.25 | KI14: 299.02 | KJ14: 292.51 | KK14: 297.03 | KL14: 295.27 | KM14: 300.37 | KN14: 296.52 | KO14: 297 | KP14: 292.95 | KQ14: 298.24 | KR14: 296.85 | KS14: 290.52 | KT14: 279.21
A15: x | D15: =+D14+1 -> 9 | E15: Novo Nordisk | F15: NVO | G15: 46.92 | H15: =+L15*G15 -> 208733 | I15: =([9]Main!$J$5-[9]Main!$J$6)/DKK -> -17878.526 | J15: =H15-I15 -> 226611.53 | K15: Q126 | L15: =+[9]Main!$J$3 -> 4448.7 | M15: 46227 | N15: - | O15: - | P15: - | Q15: - | R15: - | S15: =($J15/$L15)/AB15 -> 29.107897 | T15: =($J15/$L15)/AC15 -> 18.456094 | U15: =($J15/$L15)/AD15 -> 14.348963 | V15: =($J15/$L15)/AE15 -> 14.110477 | W15: =($J15/$L15)/AF15 -> 14.93807 | X15: =($J15/$L15)/AG15 -> 15.482924 | Y15: =($J15/$L15)/AH15 -> 14.512484 | Z15: =($J15/$L15)/AI15 -> 13.128562 | AA15: =($J15/$L15)/AJ15 -> 12.244909 | AB15: 1.75 | AC15: 2.76 | AD15: 3.55 | AE15: 3.61 | AF15: 3.41 | AG15: 3.29 | AH15: 3.51 | AI15: 3.88 | AJ15: 4.16 | AK15: 4.41 | AL15: 1923 | AM15: Copenhagen | AN15: Denmark | AO15: =BD15/FV15-1 -> -0.055227987 | AP15: =BD15/BX15-1 -> 0.054629223 | AQ15: =BD15/CA15-1 -> 0.08780267 | AR15: =BD15/KT15-1 -> -0.30353521 | BD15: 48.07 | BE15: 47.64 | BF15: 47.41 | BG15: 47.42 | BH15: 45.88 | BJ15: 43.19 | BK15: 43.52 | BL15: 43.55 | BM15: 43.92 | BN15: 43.88 | BO15: 43.96 | BP15: 42.81 | BQ15: 42.19 | BR15: 41.02 | BS15: 42.96 | BT15: 43.75 | BU15: 42 | BV15: 42.92 | BW15: 44.07 | BX15: 45.58 | BY15: 45.51 | BZ15: 44.55 | CA15: 44.19 | CB15: 44.96 | CC15: 44.39 | CD15: 45.07 | CE15: 44.28 | CF15: 44.28 | CG15: 44.74 | CH15: 45.8 | CI15: 47.08 | CJ15: 47 | CK15: 46.4 | CL15: 46.07 | CM15: 45.8 | CN15: 45.76 | CO15: 44.87 | CP15: 44.39 | CQ15: 43.88 | CR15: 42.22 | CS15: 40.29 | CT15: 41.17 | CU15: 41.2 | CV15: 41.17 | CW15: 38.52 | CX15: 39.15 | CY15: 39.42 | CZ15: 40.46 | DA15: 40.52 | DB15: 40.93 | DC15: 40.81 | DD15: 39.32 | DE15: 37.98 | DF15: 37.52 | DG15: 37.44 | DH15: 37.61 | DI15: 36.91 | DJ15: 36.67 | DK15: 36.98 | DL15: 36.48 | DM15: 36.75 | DN15: 35.29 | DO15: 36.04 | DP15: 36.4 | DQ15: 36.33 | DR15: 36.89 | DS15: 36.82 | DT15: 36.53 | DU15: 37.08 | DV15: 37.45 | DW15: 38.43 | DX15: 38.58 | DY15: 37.96 | DZ15: 38.02 | EA15: 38.83 | EB15: 38.72 | EC15: 39.78 | ED15: 38.58 | EE15: 39.07 | EF15: 38.5 | EG15: 36.66 | EH15: 37.76 | EI15: 37.45 | EJ15: 37.62 | EK15: 38.16 | EL15: 38.59 | EM15: 39.63 | EN15: 47.42 | EO15: 48.45 | EP15: 49.23 | EQ15: 49.37 | ER15: 49.57 | ES15: 48.93 | ET15: 48.74 | EU15: 49.12 | EV15: 49.37 | EW15: 47.64 | EX15: 43.34 | EY15: 47.19 | EZ15: 50.3 | FA15: 58.93 | FB15: 59.43 | FC15: 59.33 | FD15: 60.33 | FE15: 62.89 | FF15: 63.98 | FG15: 62.26 | FH15: 62.23 | FI15: 59.32 | FJ15: 60.68 | FK15: 62.33 | FL15: 57.12 | FM15: 58.91 | FN15: 59.64 | FO15: 59.86 | FP15: 58.81 | FQ15: 57.34 | FR15: 56.57 | FS15: 56.26 | FT15: 55.11 | FU15: 52.39 | FV15: 50.88 | FW15: 51.22 | FX15: 51.47 | FY15: 52.4 | FZ15: 52.56 | GA15: 51.61 | GB15: 48.1 | GC15: 48.09 | GD15: 47.61 | GE15: 47.77 | GF15: 48.96 | GG15: 50.37 | GH15: 50.18 | GI15: 50.29 | GJ15: 49.05 | GK15: 46.36 | GL15: 46.77 | GM15: 47.86 | GN15: 47.99 | GO15: 47.57 | GP15: 47.43 | GQ15: 48.43 | GR15: 49.35 | GS15: 48.71 | GT15: 47.06 | GU15: 44.97 | GV15: 47.63 | GW15: 47.6 | GX15: 49 | GY15: 47.55 | GZ15: 48.46 | HA15: 48.26 | HB15: 49.16 | HC15: 50.26 | HD15: 49.15 | HE15: 45.94 | HF15: 45.68 | HG15: 46.51 | HH15: 48.46 | HI15: 48.25 | HJ15: 49.11 | HK15: 49.46 | HL15: 50.04 | HM15: 51.37 | HN15: 52.05 | HO15: 52.89 | HP15: 52.96 | HQ15: 53.23 | HR15: 53.38 | HS15: 54.78 | HT15: 55.74 | HU15: 54.37 | HV15: 56.09 | HW15: 56.72 | HX15: 56.66 | HY15: 57.5 | HZ15: 56.93 | IA15: 58.68 | IB15: 59.61 | IC15: 59.02 | ID15: 59.65 | IE15: 59.63 | IF15: 58.74 | IG15: 59.17 | IH15: 55.49 | II15: 55.5 | IJ15: 55.61 | IK15: 56.04 | IL15: 58.74 | IM15: 59.54 | IN15: 60.71 | IO15: 61.4 | IP15: 61.85 | IQ15: 58.2 | IR15: 57.2 | IS15: 55.62 | IT15: 54.87 | IU15: 54.3 | IV15: 54.37 | IW15: 54.3 | IX15: 54.28 | IY15: 55.23 | IZ15: 56.14 | JA15: 56.74 | JB15: 56.38 | JC15: 56.46 | JD15: 56.11 | JE15: 56.44 | JF15: 55.34 | JG15: 56.34 | JH15: 56.98 | JI15: 55.45 | JJ15: 54.3 | JK15: 54.78 | JL15: 53.75 | JM15: 52.41 | JN15: 50.95 | JO15: 50.9 | JP15: 49.78 | JQ15: 49.87 | JR15: 51.08 | JS15: 48.76 | JT15: 45.38 | JU15: 47.22 | JV15: 48.81 | JW15: 48.19 | JX15: 47.07 | JY15: 50.03 | JZ15: 53.94 | KA15: 69 | KB15: 71.7 | KC15: 70.73 | KD15: 70.03 | KE15: 66.78 | KF15: 64.92 | KG15: 64.31 | KH15: 65.29 | KI15: 67.04 | KJ15: 67.22 | KK15: 68.94 | KL15: 68.93 | KM15: 71.01 | KN15: 69.69 | KO15: 69.64 | KP15: 69.32 | KQ15: 69.17 | KR15: 69.82 | KS15: 69.82 | KT15: 69.02
A16: x | D16: =+D15 -> 9 | E16: Novo Nordisk | F16: NOVOB | G16: 306.5 | H16: =+G16*L16/DKK -> 210300.68 | I16: =([9]Main!$J$5-[9]Main!$J$6)/DKK -> -17878.526 | J16: =H16-I16 -> 228179.21 | K16: Q126 | L16: =+[9]Main!$J$3 -> 4448.7 | M16: =+M15 -> 46227 | N16: =+[9]Model!$DQ$64 -> 325.56685 | O16: =N16/G16-1 -> 0.062208323 | P16: =[9]Model!$DQ$60*-1 -> 0.01 | Q16: =+[9]Model!$DQ$61 -> -0.01 | R16: =+[9]Model!$DQ$62 -> 0.08 | S16: - | T16: - | U16: - | V16: - | W16: - | X16: - | Y16: - | Z16: - | AA16: - | AB16: - | AC16: - | AD16: - | AE16: - | AF16: - | AG16: - | AH16: - | AI16: - | AJ16: - | AK16: - | AL16: 1923 | AM16: Copenhagen | AN16: Denmark
A17: x | D17: =+D16+1 -> 10 | E17: Pfizer | F17: PFE | G17: 25.04 | H17: =+L17*G17 -> 142714.08 | I17: =+[10]Main!$K$5-[10]Main!$K$6 -> -49754 | J17: =H17-I17 -> 192468.08 | K17: Q126 | L17: =+[10]Main!$K$3 -> 5699.4442 | M17: 46227 | S17: =($J17/$L17)/AB17 -> 5.4467134 | T17: =($J17/$L17)/AC17 -> 27.680019 | U17: =($J17/$L17)/AD17 -> 14.682445 | V17: =($J17/$L17)/AE17 -> 9.6761098 | W17: =($J17/$L17)/AF17 -> 11.370243 | X17: =($J17/$L17)/AG17 -> 11.684991 | Y17: =($J17/$L17)/AH17 -> 13.671912 | Z17: =($J17/$L17)/AI17 -> 14.129549 | AA17: =($J17/$L17)/AJ17 -> 13.671912 | AB17: 6.2 | AC17: 1.22 | AD17: 2.3 | AE17: 3.49 | AF17: 2.97 | AG17: 2.89 | AH17: 2.47 | AI17: 2.39 | AJ17: 2.47 | AK17: 2.54 | AM17: New York | AN17: United States | AO17: =BD17/FV17-1 -> -0.024497992 | AP17: =BD17/BX17-1 -> -0.072192513 | AQ17: =BD17/CA17-1 -> -0.060348162 | AR17: =BD17/KT17-1 -> 0.0020627063 | BD17: 24.29 | BE17: 23.67 | BF17: 24.04 | BG17: 24.72 | BH17: 25.08 | BJ17: 25.21 | BK17: 25.92 | BL17: 26.04 | BM17: 26 | BN17: 26.21 | BO17: 26.17 | BP17: 25.6 | BQ17: 25.7 | BR17: 25.62 | BS17: 26.04 | BT17: 25.69 | BU17: 25.34 | BV17: 25.55 | BW17: 25.63 | BX17: 26.18 | BY17: 26.14 | BZ17: 26.21 | CA17: 25.85 | CB17: 25.9 | CC17: 25.95 | CD17: 25.79 | CE17: 25.66 | CF17: 25.33 | CG17: 25.33 | CH17: 25.75 | CI17: 25.96 | CJ17: 25.87 | CK17: 25.81 | CL17: 25.68 | CM17: 26.48 | CN17: 26.53 | CO17: 26.45 | CP17: 26.3 | CQ17: 26.33 | CR17: 26.7 | CS17: 26.26 | CT17: 26.48 | CU17: 26.79 | CV17: 27 | CW17: 26.67 | CX17: 26.8 | CY17: 27.31 | CZ17: 27.52 | DA17: 27.56 | DB17: 27.22 | DC17: 27.19 | DD17: 27.11 | DE17: 27.34 | DF17: 26.92 | DG17: 27.22 | DH17: 27.47 | DI17: 27.1 | DJ17: 27.83 | DK17: 28.32 | DL17: 28.55 | DM17: 28.08 | DN17: 27.77 | DO17: 27.04 | DP17: 27.57 | DQ17: 27.28 | DR17: 26.96 | DS17: 26.77 | DT17: 26.97 | DU17: 27.41 | DV17: 27.32 | DW17: 27.45 | DX17: 26.61 | DY17: 26.58 | DZ17: 26.86 | EA17: 27.3 | EB17: 27.16 | EC17: 26.81 | ED17: 27.05 | EE17: 26.61 | EF17: 26.62 | EG17: 26.58 | EH17: 27.26 | EI17: 27.65 | EJ17: 27.1 | EK17: 27.09 | EL17: 27.14 | EM17: 27.06 | EN17: 26.65 | EO17: 26.86 | EP17: 27.37 | EQ17: 27.37 | ER17: 27.58 | ES17: 27.47 | ET17: 27.73 | EU17: 27.61 | EV17: 27.05 | EW17: 27.22 | EX17: 26.49 | EY17: 26.78 | EZ17: 25.77 | FA17: 26.66 | FB17: 26.44 | FC17: 26.1 | FD17: 25.86 | FE17: 26.5 | FF17: 25.88 | FG17: 25.65 | FH17: 26.1 | FI17: 25.89 | FJ17: 25.52 | FK17: 25.65 | FL17: 25.89 | FM17: 25.58 | FN17: 25.15 | FO17: 25.27 | FP17: 25.48 | FQ17: 25.29 | FR17: 25.28 | FS17: 25.43 | FT17: 25.17 | FU17: 25.18 | FV17: 24.9 | FW17: 24.99 | FX17: 25 | FY17: 25.09 | FZ17: 25.03 | GA17: 24.88 | GB17: 25.21 | GC17: 25.19 | GD17: 25.04 | GE17: 25.04 | GF17: 25.53 | GG17: 26.43 | GH17: 25.85 | GI17: 25.8 | GJ17: 25.78 | GK17: 25.33 | GL17: 25.77 | GM17: 26.03 | GN17: 25.7 | GO17: 25.57 | GP17: 25.15 | GQ17: 25.27 | GR17: 25.74 | GS17: 25.71 | GT17: 25.72 | GU17: 25.22 | GV17: 25.04 | GW17: 24.4 | GX17: 24.88 | GY17: 25.45 | GZ17: 25.08 | HA17: 25.06 | HB17: 25.79 | HC17: 25.87 | HD17: 25.51 | HE17: 24.39 | HF17: 24.43 | HG17: 24.85 | HH17: 24.61 | HI17: 24.3 | HJ17: 24.66 | HK17: 24.65 | HL17: 24.29 | HM17: 24.29 | HN17: 24.5 | HO17: 24.77 | HP17: 24.76 | HQ17: 24.67 | HR17: 24.72 | HS17: 24.85 | HT17: 24.69 | HU17: 24.51 | HV17: 24.23 | HW17: 24.39 | HX17: 24.52 | HY17: 24.73 | HZ17: 24.78 | IA17: 25.24 | IB17: 25.68 | IC17: 26.27 | ID17: 26.43 | IE17: 27.37 | IF17: 27.08 | IG17: 27.21 | IH17: 25.48 | II17: 23.85 | IJ17: 23.76 | IK17: 23.6 | IL17: 24.09 | IM17: 24.13 | IN17: 24.04 | IO17: 24.03 | IP17: 24.15 | IQ17: 24.05 | IR17: 23.9 | IS17: 23.97 | IT17: 23.87 | IU17: 24.86 | IV17: 24.57 | IW17: 24.71 | IX17: 24.55 | IY17: 24.88 | IZ17: 24.54 | JA17: 24.79 | JB17: 24.98 | JC17: 24.76 | JD17: 24.6 | JE17: 25.07 | JF17: 24.92 | JG17: 25.14 | JH17: 25.88 | JI17: 25.74 | JJ17: 25.38 | JK17: 25.32 | JL17: 25.07 | JM17: 25.14 | JN17: 25.11 | JO17: 25.16 | JP17: 24.65 | JQ17: 24.58 | JR17: 24.58 | JS17: 24.23 | JT17: 23.93 | JU17: 24.75 | JV17: 23.53 | JW17: 23.49 | JX17: 23.29 | JY17: 23.81 | JZ17: 24.3 | KA17: 24.31 | KB17: 24.79 | KC17: 25.35 | KD17: 25.36 | KE17: 25.14 | KF17: 24.26 | KG17: 24.47 | KH17: 24.58 | KI17: 24.61 | KJ17: 24.61 | KK17: 25.35 | KL17: 25.65 | KM17: 25.78 | KN17: 25.56 | KO17: 25.62 | KP17: 25.24 | KQ17: 25.38 | KR17: 25.32 | KS17: 25.04 | KT17: 24.24
A18: x | D18: =+D17+1 -> 11 | E18: Gilead | F18: GILD | G18: 130.02 | H18: =+G18*L18 -> 163045.08 | I18: =+[11]Main!$J$5-[11]Main!$J$6 -> -13548 | J18: =H18-I18 -> 176593.08 | K18: Q126 | L18: =+[11]Main!$J$3 -> 1254 | M18: 45768 | S18: =($J18/$L18)/AB18 -> 21.434373 | T18: =($J18/$L18)/AC18 -> 23.431585 | U18: =($J18/$L18)/AD18 -> 23.123781 | V18: =($J18/$L18)/AE18 -> 19.185808 | W18: =($J18/$L18)/AF18 -> 16.528618 | X18: =($J18/$L18)/AG18 -> 14.267865 | Y18: =($J18/$L18)/AH18 -> 13.310381 | Z18: =($J18/$L18)/AI18 -> 11.974815 | AA18: =($J18/$L18)/AJ18 -> 11.079766 | AB18: 6.57 | AC18: 6.01 | AD18: 6.09 | AE18: 7.34 | AF18: 8.52 | AG18: 9.87 | AH18: 10.58 | AI18: 11.76 | AJ18: 12.71 | AK18: 13.56 | AM18: California | AN18: United States | AO18: =BD18/FV18-1 -> 0.041877139 | AP18: =BD18/BX18-1 -> -0.048724243 | AQ18: =BD18/CA18-1 -> -0.043744859 | AR18: =BD18/KT18-1 -> 0.15342293 | BD18: 127.88 | BE18: 123.84 | BF18: 125.16 | BG18: 125.05 | BH18: 124.87 | BJ18: 123.76 | BK18: 125.45 | BL18: 127.23 | BM18: 124.3 | BN18: 125.59 | BO18: 125.87 | BP18: 121.48 | BQ18: 125.5 | BR18: 128.1 | BS18: 129.16 | BT18: 129.18 | BU18: 128.99 | BV18: 127.57 | BW18: 131.1 | BX18: 134.43 | BY18: 136.22 | BZ18: 133.69 | CA18: 133.73 | CB18: 134.36 | CC18: 130.5 | CD18: 130.69 | CE18: 130.5 | CF18: 129.67 | CG18: 129.58 | CH18: 132.06 | CI18: 133.05 | CJ18: 134.94 | CK18: 133.52 | CL18: 131.33 | CM18: 134.06 | CN18: 136.3 | CO18: 133.48 | CP18: 132.69 | CQ18: 131.65 | CR18: 130.84 | CS18: 128.84 | CT18: 129.26 | CU18: 127.75 | CV18: 130.4 | CW18: 133.64 | CX18: 132.9 | CY18: 133.29 | CZ18: 135.87 | DA18: 137.64 | DB18: 138.55 | DC18: 139.77 | DD18: 140.45 | DE18: 139.03 | DF18: 138.99 | DG18: 142.09 | DH18: 141.54 | DI18: 138.8 | DJ18: 140.13 | DK18: 139.71 | DL18: 140.3 | DM18: 139.37 | DN18: 136.34 | DO18: 134.25 | DP18: 136.88 | DQ18: 138.26 | DR18: 138.11 | DS18: 137.34 | DT18: 137.21 | DU18: 141.11 | DV18: 141.29 | DW18: 144.4 | DX18: 145.21 | DY18: 144.99 | DZ18: 145.21 | EA18: 146 | EB18: 148.56 | EC18: 146.63 | ED18: 143.93 | EE18: 145.14 | EF18: 148.22 | EG18: 147.83 | EH18: 150.03 | EI18: 148.95 | EJ18: 143.77 | EK18: 147.12 | EL18: 147.64 | EM18: 149.83 | EN18: 151.4 | EO18: 151.12 | EP18: 152.74 | EQ18: 155.27 | ER18: 154.98 | ES18: 151.81 | ET18: 155.8 | EU18: 147.23 | EV18: 151.68 | EW18: 152.5 | EX18: 149.37 | EY18: 146.23 | EZ18: 143.28 | FA18: 142.89 | FB18: 141.95 | FC18: 139.55 | FD18: 139.72 | FE18: 140.97 | FF18: 137.78 | FG18: 135.93 | FH18: 131.14 | FI18: 129.11 | FJ18: 124.14 | FK18: 124.91 | FL18: 121.26 | FM18: 124.07 | FN18: 121.76 | FO18: 122.6 | FP18: 121.1 | FQ18: 120.67 | FR18: 124.35 | FS18: 121.36 | FT18: 118.3 | FU18: 121.6 | FV18: 122.74 | FW18: 123.18 | FX18: 124.91 | FY18: 124.7 | FZ18: 125.67 | GA18: 125.19 | GB18: 124.16 | GC18: 124.29 | GD18: 121.47 | GE18: 121.36 | GF18: 118.78 | GG18: 119.78 | GH18: 120.4 | GI18: 123.21 | GJ18: 121.34 | GK18: 119.36 | GL18: 121.19 | GM18: 121.22 | GN18: 122.62 | GO18: 125 | GP18: 123.91 | GQ18: 124.33 | GR18: 125.84 | GS18: 127.51 | GT18: 127.12 | GU18: 125.27 | GV18: 126.64 | GW18: 124.99 | GX18: 128.07 | GY18: 127.18 | GZ18: 124.09 | HA18: 125.02 | HB18: 125.2 | HC18: 123.4 | HD18: 122.56 | HE18: 118.15 | HF18: 118.84 | HG18: 123.4 | HH18: 122.58 | HI18: 123 | HJ18: 122.05 | HK18: 119.79 | HL18: 118.44 | HM18: 118.5 | HN18: 117.88 | HO18: 120.47 | HP18: 120.94 | HQ18: 120.74 | HR18: 121.46 | HS18: 124.08 | HT18: 123.11 | HU18: 122.81 | HV18: 117.85 | HW18: 118.3 | HX18: 118.48 | HY18: 118.21 | HZ18: 117.18 | IA18: 116.74 | IB18: 118.25 | IC18: 116.78 | ID18: 113.58 | IE18: 112.69 | IF18: 110.56 | IG18: 111.15 | IH18: 111 | II18: 112.62 | IJ18: 112.1 | IK18: 110.99 | IL18: 113.67 | IM18: 114.4 | IN18: 112.49 | IO18: 114.09 | IP18: 113.62 | IQ18: 112.26 | IR18: 110.86 | IS18: 112.54 | IT18: 114.55 | IU18: 117.86 | IV18: 115.25 | IW18: 115.76 | IX18: 115.88 | IY18: 115.05 | IZ18: 112.77 | JA18: 112.99 | JB18: 112.71 | JC18: 112.97 | JD18: 112.56 | JE18: 113.92 | JF18: 114.75 | JG18: 114.15 | JH18: 114.77 | JI18: 116.14 | JJ18: 118.73 | JK18: 117.98 | JL18: 117.99 | JM18: 118.37 | JN18: 119.02 | JO18: 120.14 | JP18: 120.02 | JQ18: 120.47 | JR18: 119.41 | JS18: 110.28 | JT18: 110.28 | JU18: 112.46 | JV18: 114.51 | JW18: 113.18 | JX18: 112.29 | JY18: 114.76 | JZ18: 114.23 | KA18: 113.03 | KB18: 116.2 | KC18: 113.2 | KD18: 113.56 | KE18: 110.17 | KF18: 108.28 | KG18: 108.22 | KH18: 108.8 | KI18: 109.85 | KJ18: 109.06 | KK18: 112.09 | KL18: 109.64 | KM18: 114.54 | KN18: 113.24 | KO18: 111.06 | KP18: 111.78 | KQ18: 111.75 | KR18: 111.51 | KS18: 111.73 | KT18: 110.87
A19: x | B19: -1 | C19: 5 | D19: =+D18+1 -> 12 | E19: Bristol-Myers | F19: BMY | G19: 65.4 | H19: =+G19*L19 -> 133551.46 | I19: =+[12]Main!$K$5-[12]Main!$K$6 -> -33608 | J19: =H19-I19 -> 167159.46 | K19: Q126 | L19: =+[12]Main!$K$3 -> 2042.0712 | M19: 46217 | S19: =($J19/$L19)/AB19 -> 20.16202 | T19: =($J19/$L19)/AC19 -> 17.951272 | U19: =($J19/$L19)/AD19 -> 12.612912 | V19: =($J19/$L19)/AE19 -> 12.383933 | W19: =($J19/$L19)/AF19 -> 11.829162 | X19: =($J19/$L19)/AG19 -> 12.421517 | Y19: =($J19/$L19)/AH19 -> 14.437002 | Z19: =($J19/$L19)/AI19 -> 16.082082 | AA19: =($J19/$L19)/AJ19 -> 16.082082 | AB19: 4.06 | AC19: 4.56 | AD19: 6.49 | AE19: 6.61 | AF19: 6.92 | AG19: 6.59 | AH19: 5.67 | AI19: 5.09 | AJ19: 5.09 | AK19: 5.28 | AL19: 1887 | AM19: New Jersey | AN19: United States | AO19: =BD19/FV19-1 -> 0.066370041 | AP19: =BD19/BX19-1 -> 0.005946135 | AQ19: =BD19/CA19-1 -> -0.0087885576 | AR19: =BD19/KT19-1 -> 0.24260099 | BD19: 57.52 | BE19: 55.39 | BF19: 55 | BG19: 55.53 | BH19: 54.7 | BJ19: 54 | BK19: 55.28 | BL19: 55.92 | BM19: 56.24 | BN19: 57.13 | BO19: 56.9 | BP19: 55.6 | BQ19: 56.48 | BR19: 55.57 | BS19: 57.27 | BT19: 56.6 | BU19: 54.72 | BV19: 54.46 | BW19: 54.95 | BX19: 57.18 | BY19: 56.91 | BZ19: 57.52 | CA19: 58.03 | CB19: 59.46 | CC19: 59.55 | CD19: 58.54 | CE19: 58.31 | CF19: 57.31 | CG19: 57 | CH19: 56.77 | CI19: 56.39 | CJ19: 56.45 | CK19: 55.67 | CL19: 56.16 | CM19: 56.25 | CN19: 56.59 | CO19: 56.95 | CP19: 57.38 | CQ19: 58.22 | CR19: 60.59 | CS19: 57.59 | CT19: 58.26 | CU19: 57.78 | CV19: 58.71 | CW19: 59.02 | CX19: 58.8 | CY19: 59.39 | CZ19: 59.13 | DA19: 60.17 | DB19: 58.96 | DC19: 57.89 | DD19: 58.08 | DE19: 58.06 | DF19: 58.62 | DG19: 59.47 | DH19: 59.2 | DI19: 57.67 | DJ19: 59.33 | DK19: 59.6 | DL19: 61.73 | DM19: 60.65 | DN19: 59.73 | DO19: 58.54 | DP19: 59.43 | DQ19: 58.94 | DR19: 57.39 | DS19: 57 | DT19: 57.48 | DU19: 58.11 | DV19: 59.37 | DW19: 59.71 | DX19: 59.71 | DY19: 59.08 | DZ19: 58.95 | EA19: 59.98 | EB19: 60.13 | EC19: 60.63 | ED19: 60.29 | EE19: 60.74 | EF19: 62.33 | EG19: 61.22 | EH19: 62.34 | EI19: 62.37 | EJ19: 61.1 | EK19: 61.3 | EL19: 61.6 | EM19: 61.25 | EN19: 60.66 | EO19: 60.3 | EP19: 59.73 | EQ19: 60.35 | ER19: 60.74 | ES19: 59.86 | ET19: 59.93 | EU19: 60.86 | EV19: 60.77 | EW19: 61.99 | EX19: 59.52 | EY19: 57.62 | EZ19: 55.99 | FA19: 55.89 | FB19: 55.05 | FC19: 54.28 | FD19: 54.62 | FE19: 55.56 | FF19: 54.6 | FG19: 54.65 | FH19: 54.94 | FI19: 54.5 | FJ19: 54.22 | FK19: 55.26 | FL19: 56.62 | FM19: 57.02 | FN19: 55.92 | FO19: 55.77 | FP19: 55.86 | FQ19: 55.9 | FR19: 56.72 | FS19: 54.42 | FT19: 53.06 | FU19: 53.46 | FV19: 53.94 | FW19: 54.21 | FX19: 54.11 | FY19: 54.64 | FZ19: 54.71 | GA19: 54.28 | GB19: 54.66 | GC19: 54.19 | GD19: 53.33 | GE19: 53.55 | GF19: 54.23 | GG19: 54.29 | GH19: 52.41 | GI19: 51.2 | GJ19: 51.21 | GK19: 50.65 | GL19: 51.67 | GM19: 52.15 | GN19: 51.95 | GO19: 50.96 | GP19: 48.25 | GQ19: 49.18 | GR19: 49.2 | GS19: 49.25 | GT19: 49.05 | GU19: 47.76 | GV19: 46.25 | GW19: 45.94 | GX19: 45.79 | GY19: 47.06 | GZ19: 46.81 | HA19: 46.65 | HB19: 48.63 | HC19: 49.08 | HD19: 48.72 | HE19: 47.26 | HF19: 46.69 | HG19: 46.63 | HH19: 46.47 | HI19: 45.59 | HJ19: 46.02 | HK19: 46.07 | HL19: 45.62 | HM19: 42.6 | HN19: 42.82 | HO19: 43.39 | HP19: 43.83 | HQ19: 43.83 | HR19: 44.39 | HS19: 44.54 | HT19: 43.59 | HU19: 43.63 | HV19: 43.39 | HW19: 43.61 | HX19: 43.8 | HY19: 43.54 | HZ19: 43.96 | IA19: 44.68 | IB19: 44.54 | IC19: 44.66 | ID19: 45.14 | IE19: 45.45 | IF19: 45.73 | IG19: 47.43 | IH19: 45.1 | II19: 44.15 | IJ19: 44.12 | IK19: 43.41 | IL19: 44.16 | IM19: 44.91 | IN19: 44.98 | IO19: 45.02 | IP19: 45.6 | IQ19: 46.15 | IR19: 46.34 | IS19: 46.35 | IT19: 46.2 | IU19: 47.54 | IV19: 47.15 | IW19: 47.23 | IX19: 46.72 | IY19: 47.14 | IZ19: 46.69 | JA19: 47.5 | JB19: 47.41 | JC19: 47.18 | JD19: 46.88 | JE19: 47.63 | JF19: 47.21 | JG19: 47.14 | JH19: 47.92 | JI19: 48.43 | JJ19: 48.26 | JK19: 48.34 | JL19: 48.19 | JM19: 48.44 | JN19: 47.81 | JO19: 47.85 | JP19: 46.55 | JQ19: 45.93 | JR19: 45.95 | JS19: 45.36 | JT19: 44.82 | JU19: 45.85 | JV19: 45.4 | JW19: 44.23 | JX19: 43.31 | JY19: 45.98 | JZ19: 46.86 | KA19: 47.51 | KB19: 48.43 | KC19: 48.94 | KD19: 48.98 | KE19: 48.02 | KF19: 46.69 | KG19: 47.36 | KH19: 48.06 | KI19: 47.17 | KJ19: 46.43 | KK19: 47.34 | KL19: 46.86 | KM19: 48.52 | KN19: 47.66 | KO19: 47.04 | KP19: 46.49 | KQ19: 46.92 | KR19: 47.63 | KS19: 47.51 | KT19: 46.29
A20: x | D20: =+D19+1 -> 13 | E20: GSK | F20: GSK US | G20: 51.81 | H20: =+G20*L20/2 -> 104215.82 | I20: =([13]Main!$J$6-[13]Main!$J$7)*GBP -> -20805.884 | J20: =H20-I20 -> 125021.7 | K20: Q126 | L20: =+[13]Main!$J$4 -> 4023 | M20: 46227 | S20: =($J20/$L20)/AB20 -> 10.024753 | T20: =($J20/$L20)/AC20 -> 8.9817149 | U20: =($J20/$L20)/AD20 -> 8.8286175 | V20: =($J20/$L20)/AE20 -> 7.6543679 | W20: - | X20: - | Y20: - | Z20: - | AA20: - | AB20: 3.1 | AC20: 3.46 | AD20: 3.52 | AE20: 4.06 | AF20: 4.79 | AG20: 5.17 | AH20: 5.44 | AI20: 5.8 | AJ20: 5.86 | AK20: 6.17 | AM20: London | AN20: United Kingdom
A21: x | D21: =+D20 -> 13 | E21: GSK | F21: GSK LN | G21: 1931.5 | H21: =+G21*L21/100*GBP -> 103548.68 | I21: =([13]Main!$J$6-[13]Main!$J$7)*GBP -> -20805.884 | J21: =H21-I21 -> 124354.56 | K21: Q126 | L21: =+L20 -> 4023 | M21: 46227 | N21: - | O21: - | P21: - | Q21: - | R21: - | S21: =($J21/$L21)/AB21 -> 0.24728722 | T21: =($J21/$L21)/AC21 -> 0.22238059 | U21: =($J21/$L21)/AD21 -> 0.22399205 | V21: =($J21/$L21)/AE21 -> 0.20072015 | W21: =($J21/$L21*100)/AF21 -> 17.365676 | X21: =($J21/$L21*100)/AG21 -> 16.099428 | Y21: =($J21/$L21*100)/AH21 -> 15.302427 | Z21: =($J21/$L21*100)/AI21 -> 14.310603 | AA21: =($J21/$L21*100)/AJ21 -> 14.179313 | AB21: 125 | AC21: 139 | AD21: 138 | AE21: 154 | AF21: 178 | AG21: 192 | AH21: 202 | AI21: 216 | AJ21: 218 | AK21: 230 | AM21: London | AN21: United Kingdom
A22: x | D22: =+D21+1 -> 14 | E22: Sanofi | F22: SNY | G22: 43.08 | H22: =+G22*L22*2 -> 107786.16 | I22: =([14]Main!$K$5-[14]Main!$K$6)*EUR -> -14319 | J22: =H22-I22 -> 122105.16 | K22: =+K23 -> Q126 | L22: =+L23 -> 1251 | M22: =+M23 -> 46224 | N22: - | O22: - | P22: - | Q22: - | R22: - | S22: - | T22: - | U22: - | V22: - | W22: =($J22/$L22)/AF22 -> 19.639043 | X22: =($J22/$L22)/AG22 -> 18.556282 | Y22: =($J22/$L22)/AH22 -> 17.034213 | Z22: =($J22/$L22)/AI22 -> 16.027265 | AA22: =($J22/$L22)/AJ22 -> 15.016314 | AB22: 3.73 | AC22: 2.83 | AD22: 2.77 | AE22: 3.28 | AF22: 4.97 | AG22: 5.26 | AH22: 5.73 | AI22: 6.09 | AJ22: 6.5 | AK22: 6.74 | AM22: Paris | AN22: France
A23: x | D23: =+D22 -> 14 | E23: Sanofi | F23: SAN | G23: 74.47 | H23: =+G23*L23*EUR -> 103409.79 | I23: =([14]Main!$K$5-[14]Main!$K$6)*EUR -> -14319 | J23: =H23-I23 -> 117728.79 | K23: Q126 | L23: =+[15]Main!$K$3 -> 1251 | M23: 46224 | S23: - | T23: - | U23: - | V23: =($J23/$L23)/AE23 -> 20.547542 | W23: - | X23: - | Y23: - | Z23: - | AA23: - | AB23: - | AC23: - | AD23: - | AE23: 4.58 | AF23: 5.03 | AG23: - | AH23: - | AI23: - | AJ23: - | AK23: - | AM23: Paris | AN23: France
A24: x | D24: =+D23+1 -> 15 | E24: Vertex | F24: VRTX | G24: 477.1 | H24: =+G24*[16]Main!$M$3 -> 121090.37 | I24: =+[16]Main!$M$5-[16]Main!$M$6 -> 13000 | J24: =H24-I24 -> 108090.37 | K24: Q126 | L24: =+[16]Main!$M$3 -> 253.805 | M24: 46206 | N24: =+[16]Model!$BO$34 -> 586.57187 | O24: =N24/G24-1 -> 0.22945267 | P24: =+[16]Model!$BO$32 -> 0.03 | Q24: =+[16]Model!$BO$30 -> -0.05 | R24: =[16]Model!$BO$30 -> -0.05 | S24: =($J24/$L24)/AB24 -> 30.616792 | T24: =($J24/$L24)/AC24 -> 29.090135 | U24: =($J24/$L24)/AD24 -> 37.162267 | V24: =($J24/$L24)/AE24 -> 27.057152 | W24: =($J24/$L24)/AF24 -> 22.4976 | X24: =($J24/$L24)/AG24 -> 20.145675 | Y24: =($J24/$L24)/AH24 -> 17.389938 | Z24: =($J24/$L24)/AI24 -> 14.958889 | AA24: =($J24/$L24)/AJ24 -> 12.885918 | AB24: 13.91 | AC24: 14.64 | AD24: 11.46 | AE24: 15.74 | AF24: 18.93 | AG24: 21.14 | AH24: 24.49 | AI24: 28.47 | AJ24: 33.05 | AK24: 37.36 | AM24: Boston | AN24: United States | AO24: =BD24/FV24-1 -> 0.083774484 | AP24: =BD24/BX24-1 -> 0.097868347 | AQ24: =BD24/CA24-1 -> 0.12710756 | AR24: =BD24/KT24-1 -> 0.10363881 | BD24: 491.34 | BE24: 480.18 | BF24: 475.2 | BG24: 468.42 | BH24: 466.79 | BJ24: 451.63 | BK24: 458.99 | BL24: 453.17 | BM24: 450.46 | BN24: 444.925 | BO24: 445.04 | BP24: 435.71 | BQ24: 445.77 | BR24: 442.96 | BS24: 446.83 | BT24: 441.74 | BU24: 428.34 | BV24: 425.09 | BW24: 438.4 | BX24: 447.54 | BY24: 447.97 | BZ24: 437.22 | CA24: 435.93 | CB24: 434.52 | CC24: 433.54 | CD24: 430.44 | CE24: 434.31 | CF24: 436.58 | CG24: 436.95 | CH24: 450.41 | CI24: 453.06 | CJ24: 448.29 | CK24: 435.17 | CL24: 429.82 | CM24: 425 | CN24: 427.65 | CO24: 424.36 | CP24: 429.85 | CQ24: 423.92 | CR24: 427.38 | CS24: 423.24 | CT24: 430.14 | CU24: 426.01 | CV24: 430.29 | CW24: 435.1 | CX24: 437.67 | CY24: 436.59 | CZ24: 439.18 | DA24: 441.2 | DB24: 435.65 | DC24: 441.7 | DD24: 444.28 | DE24: 440.05 | DF24: 436.27 | DG24: 446.78 | DH24: 443.92 | DI24: 431.86 | DJ24: 434.3 | DK24: 438.71 | DL24: 447.26 | DM24: 446.54 | DN24: 443.16 | DO24: 433.07 | DP24: 453.74 | DQ24: 454.97 | DR24: 448.62 | DS24: 451.235 | DT24: 454 | DU24: 458.05 | DV24: 451.59 | DW24: 462.49 | DX24: 466.1 | DY24: 469.34 | DZ24: 478.13 | EA24: 492.38 | EB24: 499.17 | EC24: 460.87 | ED24: 456.69 | EE24: 460.82 | EF24: 477.89 | EG24: 474.27 | EH24: 486.03 | EI24: 496.83 | EJ24: 480.13 | EK24: 483.05 | EL24: 487.43 | EM24: 481.01 | EN24: 476.9 | EO24: 469.27 | EP24: 470.31 | EQ24: 477.32 | ER24: 491.47 | ES24: 465.02 | ET24: 461.24 | EU24: 463.48 | EV24: 470.87 | EW24: 477.92 | EX24: 458.81 | EY24: 470.52 | EZ24: 465.61 | FA24: 472.01 | FB24: 469.9 | FC24: 475.68 | FD24: 477.91 | FE24: 474.17 | FF24: 476.84 | FG24: 468.41 | FH24: 467.35 | FI24: 461.14 | FJ24: 442.08 | FK24: 441.36 | FL24: 438.92 | FM24: 449.53 | FN24: 454.67 | FO24: 460.59 | FP24: 463.86 | FQ24: 469.68 | FR24: 484.15 | FS24: 468.38 | FT24: 448.8 | FU24: 452.13 | FV24: 453.36 | FW24: 453.74 | FX24: 459.78 | FY24: 462.9 | FZ24: 462.99 | GA24: 459.21 | GB24: 460.31 | GC24: 456.2 | GD24: 447.38 | GE24: 449.52 | GF24: 454.96 | GG24: 455.71 | GH24: 452.04 | GI24: 445.93 | GJ24: 444.64 | GK24: 437.01 | GL24: 442.04 | GM24: 455.48 | GN24: 457.36 | GO24: 463.13 | GP24: 433.15 | GQ24: 425.6 | GR24: 433.61 | GS24: 432.17 | GT24: 429.82 | GU24: 424 | GV24: 426.76 | GW24: 422.32 | GX24: 421.03 | GY24: 435.52 | GZ24: 434.02 | HA24: 437.15 | HB24: 434.52 | HC24: 434.19 | HD24: 429.22 | HE24: 421.2 | HF24: 409.47 | HG24: 416.25 | HH24: 417 | HI24: 421.67 | HJ24: 426 | HK24: 425.57 | HL24: 419.89 | HM24: 417.21 | HN24: 422.39 | HO24: 420.17 | HP24: 421.39 | HQ24: 422.63 | HR24: 426.44 | HS24: 426.27 | HT24: 419.1 | HU24: 416.81 | HV24: 408.61 | HW24: 407.9 | HX24: 412.22 | HY24: 407.37 | HZ24: 407.79 | IA24: 414.86 | IB24: 421.15 | IC24: 410.28 | ID24: 402.9 | IE24: 403.3 | IF24: 408.85 | IG24: 404.21 | IH24: 391.64 | II24: 395.31 | IJ24: 385.735 | IK24: 381.87 | IL24: 376.62 | IM24: 379.72 | IN24: 383.13 | IO24: 383.12 | IP24: 387.11 | IQ24: 387.15 | IR24: 391.36 | IS24: 393.21 | IT24: 394.53 | IU24: 397.37 | IV24: 388.55 | IW24: 396.48 | IX24: 395.25 | IY24: 396.12 | IZ24: 396.93 | JA24: 396.62 | JB24: 401 | JC24: 391.02 | JD24: 392.05 | JE24: 389.08 | JF24: 387.18 | JG24: 388.94 | JH24: 395.12 | JI24: 397.46 | JJ24: 394.36 | JK24: 390.76 | JL24: 389.88 | JM24: 392.79 | JN24: 390.3 | JO24: 395.92 | JP24: 387.77 | JQ24: 374.46 | JR24: 366.54 | JS24: 375.63 | JT24: 385.65 | JU24: 374.98 | JV24: 472.27 | JW24: 462.13 | JX24: 456.87 | JY24: 469.16 | JZ24: 468.41 | KA24: 460.83 | KB24: 469.65 | KC24: 472.27 | KD24: 476.95 | KE24: 470.13 | KF24: 458.49 | KG24: 459.81 | KH24: 463.27 | KI24: 469.55 | KJ24: 464.2 | KK24: 472.35 | KL24: 468.85 | KM24: 479.53 | KN24: 478.965 | KO24: 466.36 | KP24: 459.41 | KQ24: 459.62 | KR24: 457.03 | KS24: 452.16 | KT24: 445.2
A25: x | D25: =+D24+1 -> 16 | E25: Bayer | F25: BAYN | G25: 48.3 | H25: =+G25*L25*EUR -> 52670.483 | I25: =([17]Main!$J$5-[17]Main!$J$6) -> -32518 | J25: =+H25-I25 -> 85188.483 | K25: Q126 | L25: =+[17]Main!$J$3 -> 982.42 | M25: 46229 | V25: =($J25/$L25)/AE25 -> 68.819759 | W25: =($J25/$L25)/AF25 -> 16.870213 | X25: =($J25/$L25)/AG25 -> 15.969226 | Y25: =($J25/$L25)/AH25 -> 14.309059 | Z25: =($J25/$L25)/AI25 -> 15.028232 | AA25: =($J25/$L25)/AJ25 -> 14.797423 | AB25: 4.73 | AC25: 2.61 | AD25: -1.4 | AE25: 1.26 | AF25: 5.14 | AG25: 5.43 | AH25: 6.06 | AI25: 5.77 | AJ25: 5.86 | AK25: 5.28 | AM25: Leverkusen | AN25: Germany
A26: x | D26: =+D25+1 -> 17 | E26: Takeda | F26: TAK | G26: 17.14 | H26: =+G26*2*L26 -> 53993.14 | I26: =([18]Main!$K$6-[18]Main!$K$7)/JPY -> -23222.185 | J26: =+H26-I26 -> 77215.324 | K26: Q126 | L26: =+[18]Main!$K$4 -> 1575.0624 | M26: 46229 | W26: =($J26/$L26)/AF26 -> 21.691885 | X26: =($J26/$L26)/AG26 -> 16.395873 | Y26: =($J26/$L26)/AH26 -> 13.966855 | Z26: =($J26/$L26)/AI26 -> 12.317503 | AA26: =($J26/$L26)/AJ26 -> 11.507901 | AB26: - | AC26: - | AD26: - | AE26: - | AF26: 2.26 | AG26: 2.99 | AH26: 3.51 | AI26: 3.98 | AJ26: 4.26 | AK26: 4.4 | AM26: Tokyo | AN26: Japan
A27: x | D27: =+D26 -> 17 | E27: Takeda | F27: 4502 JP | G27: 5513 | H27: =+G27*L27/JPY -> 52995.539 | I27: =([18]Main!$K$6-[18]Main!$K$7)/JPY -> -23222.185 | J27: =+H27-I27 -> 76217.724 | K27: Q126 | L27: =+[18]Main!$K$4 -> 1575.0624 | M27: =+M26 -> 46229 | W27: - | X27: - | Y27: - | Z27: - | AA27: - | AB27: - | AC27: - | AD27: - | AE27: - | AF27: - | AG27: - | AH27: - | AI27: - | AJ27: - | AK27: - | AM27: Tokyo | AN27: Japan
A28: x | D28: =+D27+1 -> 18 | E28: Merck KgAa | F28: MRK DE | G28: 143.15 | H28: =+G28*L28 -> 62270.25 | I28: =([19]Main!$J$5-[19]Main!$J$6)*EUR -> -9232.98 | J28: =H28-I28 -> 71503.23 | K28: Q126 | L28: 435 | M28: 46229 | W28: =($J28/$L28)/AF28 -> 17.412632 | X28: =($J28/$L28)/AG28 -> 16.210576 | Y28: =($J28/$L28)/AH28 -> 14.80858 | Z28: =($J28/$L28)/AI28 -> 13.495504 | AA28: =($J28/$L28)/AJ28 -> 12.45267 | AC28: 7.78 | AD28: 7.99 | AE28: 7.93 | AF28: 9.44 | AG28: 10.14 | AH28: 11.1 | AI28: 12.18 | AJ28: 13.2 | AK28: 15.21 | AN28: Germany
A29: x | D29: =+D28+1 -> 19 | E29: Chugai | F29: 4519 JP | G29: 6932 | H29: =+G29*L29/JPY -> 71035.873 | I29: =([20]Main!$J$5-[20]Main!$J$6)/JPY -> 5874.7208 | J29: =+H29-I29 -> 65161.152 | K29: Q126 | L29: =+[20]Main!$J$3 -> 1679.0577 | M29: 46229 | W29: =($J29/$L29*JPY)/AF29 -> 20.563736 | X29: =($J29/$L29*JPY)/AG29 -> 17.782645 | Y29: =($J29/$L29*JPY)/AH29 -> 15.794919 | Z29: =($J29/$L29*JPY)/AI29 -> 13.647661 | AA29: =($J29/$L29*JPY)/AJ29 -> 12.440511 | AB29: 227.84 | AC29: 200.24 | AD29: 242.32 | AE29: 274.77 | AF29: 309.22 | AG29: 357.58 | AH29: 402.58 | AI29: 465.92 | AJ29: 511.13 | AK29: 559.74 | AL29: 1925 | AM29: Tokyo | AN29: Japan
A30: x | D30: =+D29+1 -> 20 | E30: Regeneron | F30: REGN | G30: 763.2 | H30: =+G30*L30 -> 80899.2 | I30: =+[21]Main!$J$5-[21]Main!$J$6 -> 16553.5 | J30: =H30-I30 -> 64345.7 | K30: Q126 | L30: =+[21]Main!$J$3 -> 106 | M30: 46229 | W30: =($J30/$L30)/AF30 -> 11.312615 | X30: =($J30/$L30)/AG30 -> 10.351891 | Y30: =($J30/$L30)/AH30 -> 9.0968815 | Z30: =($J30/$L30)/AI30 -> 7.8886927 | AA30: =($J30/$L30)/AJ30 -> 7.6270248 | AB30: 41.83 | AC30: 38.53 | AD30: 39.16 | AE30: 36.4 | AF30: 53.66 | AG30: 58.64 | AH30: 66.73 | AI30: 76.95 | AJ30: 79.59 | AK30: 82.73 | AL30: 1988 | AM30: New York | AN30: United States | AO30: =BD30/FV30-1 -> -0.18004327 | AP30: =BD30/BX30-1 -> 0.029473958 | AQ30: =BD30/CA30-1 -> -0.0027102833 | AR30: =BD30/KT30-1 -> 0.20552381 | BD30: 632.9 | BE30: 620.14 | BF30: 623.43 | BG30: 618.03 | BH30: 612.5 | BJ30: 609.94 | BK30: 607.93 | BL30: 614.73 | BM30: 614.98 | BN30: 612.14 | BO30: 611.48 | BP30: 601.65 | BQ30: 616.18 | BR30: 611.34 | BS30: 635.45 | BT30: 628.73 | BU30: 618.95 | BV30: 602.92 | BW30: 600.66 | BX30: 614.78 | BY30: 621.52 | BZ30: 627.74 | CA30: 634.62 | CB30: 638.88 | CC30: 642.59 | CD30: 649.76 | CE30: 630.3 | CF30: 629.68 | CG30: 698.25 | CH30: 712.87 | CI30: 719.88 | CJ30: 723.41 | CK30: 712.77 | CL30: 714.89 | CM30: 709.1 | CN30: 721.05 | CO30: 702.27 | CP30: 709.21 | CQ30: 701.42 | CR30: 707.06 | CS30: 686.36 | CT30: 731.77 | CU30: 744.44 | CV30: 751.57 | CW30: 766.02 | CX30: 746.58 | CY30: 747.36 | CZ30: 749.41 | DA30: 750.57 | DB30: 746 | DC30: 753.93 | DD30: 755.51 | DE30: 746.46 | DF30: 748.87 | DG30: 767.85 | DH30: 775.53 | DI30: 760.27 | DJ30: 763.04 | DK30: 761.85 | DL30: 777.25 | DM30: 772.64 | DN30: 749.29 | DO30: 737.71 | DP30: 756.73 | DQ30: 749.47 | DR30: 741.69 | DS30: 736.53 | DT30: 732.87 | DU30: 737.45 | DV30: 744.12 | DW30: 759.05 | DX30: 756.91 | DY30: 745.77 | DZ30: 746.61 | EA30: 774.66 | EB30: 772.03 | EC30: 781.6 | ED30: 759.86 | EE30: 764.93 | EF30: 787.5 | EG30: 766.66 | EH30: 790.81 | EI30: 781.67 | EJ30: 770.79 | EK30: 784.28 | EL30: 772.19 | EM30: 787.04 | EN30: 779.67 | EO30: 782.38 | EP30: 792.16 | EQ30: 793.53 | ER30: 803.17 | ES30: 783.65 | ET30: 778.97 | EU30: 754.91 | EV30: 780.28 | EW30: 785.51 | EX30: 766.63 | EY30: 775.06 | EZ30: 759.18 | FA30: 755.02 | FB30: 741.45 | FC30: 749.44 | FD30: 751.13 | FE30: 771.25 | FF30: 762.65 | FG30: 753.55 | FH30: 755.51 | FI30: 749.33 | FJ30: 733.78 | FK30: 733.04 | FL30: 741.92 | FM30: 754.14 | FN30: 758.91 | FO30: 768 | FP30: 796.55 | FQ30: 801.01 | FR30: 812.27 | FS30: 776.54 | FT30: 763.23 | FU30: 776.31 | FV30: 771.87 | FW30: 773.94 | FX30: 780.5 | FY30: 784.97 | FZ30: 783.71 | GA30: 785.17 | GB30: 779.36 | GC30: 767.96 | GD30: 748.71 | GE30: 749.79 | GF30: 746.36 | GG30: 752.62 | GH30: 741.29 | GI30: 746.8 | GJ30: 726.21 | GK30: 692.58 | GL30: 703.26 | GM30: 718.36 | GN30: 722.8 | GO30: 723.67 | GP30: 742 | GQ30: 750.11 | GR30: 780.19 | GS30: 784.61 | GT30: 787.32 | GU30: 761.45 | GV30: 755.9 | GW30: 737 | GX30: 702.75 | GY30: 725.34 | GZ30: 704.31 | HA30: 693.5 | HB30: 694.99 | HC30: 681.72 | HD30: 674.55 | HE30: 654.74 | HF30: 657.53 | HG30: 646.87 | HH30: 644.19 | HI30: 628 | HJ30: 642.25 | HK30: 651.8 | HL30: 654.04 | HM30: 652.91 | HN30: 654.48 | HO30: 585.31 | HP30: 577.95 | HQ30: 575.69 | HR30: 584.74 | HS30: 579.34 | HT30: 576.77 | HU30: 578.05 | HV30: 569.17 | HW30: 576.42 | HX30: 572.6 | HY30: 557.73 | HZ30: 564.63 | IA30: 569.9 | IB30: 563.86 | IC30: 583.24 | ID30: 585.48 | IE30: 600 | IF30: 600 | IG30: 599.94 | IH30: 562.27 | II30: 560.75 | IJ30: 563.9 | IK30: 555.51 | IL30: 576.98 | IM30: 567.89 | IN30: 595.68 | IO30: 591.99 | IP30: 598.71 | IQ30: 585.5 | IR30: 575.06 | IS30: 572.59 | IT30: 560 | IU30: 568.2 | IV30: 555.83 | IW30: 556.53 | IX30: 558.44 | IY30: 573.38 | IZ30: 567.22 | JA30: 563.8 | JB30: 577.9 | JC30: 580.7 | JD30: 579.61 | JE30: 586.96 | JF30: 587.65 | JG30: 572.38 | JH30: 589.48 | JI30: 598.16 | JJ30: 591.01 | JK30: 571.78 | JL30: 573.91 | JM30: 580.41 | JN30: 565.97 | JO30: 561.55 | JP30: 556.555 | JQ30: 545.94 | JR30: 563 | JS30: 559.8 | JT30: 555.13 | JU30: 569.9 | JV30: 571.54 | JW30: 558.87 | JX30: 545.46 | JY30: 554.58 | JZ30: 558.145 | KA30: 558.63 | KB30: 563.1 | KC30: 564.64 | KD30: 572.39 | KE30: 560.93 | KF30: 545.53 | KG30: 542.52 | KH30: 550 | KI30: 547.93 | KJ30: 547.96 | KK30: 570.59 | KL30: 567.74 | KM30: 559.76 | KN30: 552.58 | KO30: 547.75 | KP30: 538.11 | KQ30: 547.36 | KR30: 547.74 | KS30: 534.91 | KT30: 525
A31: x | D31: =+D30+1 -> 21 | E31: Sun Pharmaceuticals | F31: SUNP | G31: 1990.5 | H31: =+G31*L31/INR -> 57846.269 | I31: =([22]Main!$J$5-[22]Main!$J$6)/INR -> 3484.4906 | J31: =H31-I31 -> 54361.778 | K31: Q126 | L31: =+[22]Main!$J$3 -> 2399 | M31: 46230 | AL31: 1983 | AN31: India
A32: x | D32: =+D31+1 -> 22 | E32: Teva | F32: TEVA | G32: 34.59 | H32: =+G32*L32 -> 41196.69 | I32: =+[23]Main!$M$5-[23]Main!$M$6 -> -12938 | J32: =+H32-I32 -> 54134.69 | K32: Q226 | L32: =+[23]Main!$M$3 -> 1191 | M32: 46232 | AN32: Israel
A33: x | D33: =+D32+1 -> 23 | E33: Galderma | F33: GALD SW | G33: 175.75 | H33: =+G33*L33/CHF -> 50201.617 | I33: =([24]Main!$J$5-[24]Main!$J$6) -> -1876 | J33: =+H33-I33 -> 52077.617 | K33: Q226 | L33: =+[24]Main!$J$3 -> 233.65532 | M33: 46232 | AN33: Switzerland
A34: x | D34: =+D33+1 -> 24 | E34: Argenx | F34: ARGX | G34: 853.82 | H34: =+G34*L34 -> 54994.109 | I34: =+[25]Main!$K$5-[25]Main!$K$6 -> 5187 | J34: =H34-I34 -> 49807.109 | K34: Q226 | L34: =+[25]Main!$K$3 -> 64.409488 | M34: 46232 | AL34: 2008 | AN34: Belgium | AO34: =BD34/FV34-1 -> 0.054973542 | AP34: =BD34/BX34-1 -> 0.06123279 | AQ34: =BD34/CA34-1 -> 0.097411031 | AR34: =BD34/KT34-1 -> 0.60948442 | BD34: 887.18 | BE34: 888.65 | BF34: 852.5 | BG34: 853.4 | BH34: 903.75 | BJ34: 877.72 | BK34: 892.26 | BL34: 878.49 | BM34: 884.2 | BN34: 893.52 | BO34: 898.94 | BP34: 862.18 | BQ34: 884 | BR34: 882.41 | BS34: 891.32 | BT34: 842.27 | BU34: 813.14 | BV34: 802.17 | BW34: 836.09 | BX34: 835.99 | BY34: 838.49 | BZ34: 820.63 | CA34: 808.43 | CB34: 806.46 | CC34: 816.22 | CD34: 804.25 | CE34: 797.77 | CF34: 776.26 | CG34: 799.32 | CH34: 822.13 | CI34: 802.7 | CJ34: 812.81 | CK34: 813.28 | CL34: 782.17 | CM34: 787.31 | CN34: 807.55 | CO34: 794.7 | CP34: 811.09 | CQ34: 783.5 | CR34: 781.72 | CS34: 776.02 | CT34: 775.03 | CU34: 783.74 | CV34: 780.25 | CW34: 787.95 | CX34: 793.22 | CY34: 805.38 | CZ34: 834.45 | DA34: 849.04 | DB34: 828.35 | DC34: 840.87 | DD34: 828.35 | DE34: 809.27 | DF34: 799.65 | DG34: 800.5 | DH34: 785.07 | DI34: 765.43 | DJ34: 748.25 | DK34: 746.42 | DL34: 743.12 | DM34: 730.25 | DN34: 704.31 | DO34: 691.4 | DP34: 692.83 | DQ34: 697.05 | DR34: 677.5 | DS34: 681.85 | DT34: 663.93 | DU34: 684.5 | DV34: 684.77 | DW34: 706.03 | DX34: 703.3 | DY34: 700.45 | DZ34: 708.85 | EA34: 728.09 | EB34: 742.79 | EC34: 740.4 | ED34: 717.8 | EE34: 728.11 | EF34: 749.56 | EG34: 748.72 | EH34: 756.76 | EI34: 766.92 | EJ34: 771.53 | EK34: 816.95 | EL34: 840.28 | EM34: 826.25 | EN34: 844.41 | EO34: 847.26 | EP34: 845.35 | EQ34: 843.55 | ER34: 821.96 | ES34: 833.54 | ET34: 834.55 | EU34: 833.16 | EV34: 828.24 | EW34: 811.45 | EX34: 820.31 | EY34: 850.87 | EZ34: 851.72 | FA34: 835.68 | FB34: 840.5 | FC34: 847.72 | FD34: 846.755 | FE34: 864.42 | FF34: 833.16 | FG34: 814.74 | FH34: 827.02 | FI34: 816.37 | FJ34: 809.64 | FK34: 800.01 | FL34: 813.24 | FM34: 799.33 | FN34: 810.51 | FO34: 796 | FP34: 788.49 | FQ34: 795.57 | FR34: 822.94 | FS34: 803.74 | FT34: 800.88 | FU34: 839.99 | FV34: 840.95 | FW34: 837.9 | FX34: 837.45 | FY34: 844.92 | FZ34: 849.95 | GA34: 845.95 | GB34: 852.04 | GC34: 854.99 | GD34: 847.05 | GE34: 862.05 | GF34: 851.42 | GG34: 850.95 | GH34: 877.94 | GI34: 889.49 | GJ34: 890.11 | GK34: 889.41 | GL34: 900.76 | GM34: 901.17 | GN34: 915.97 | GO34: 921.8 | GP34: 915.36 | GQ34: 894.9 | GR34: 911.98 | GS34: 917.63 | GT34: 917.93 | GU34: 906.74 | GV34: 918.92 | GW34: 918.5 | GX34: 914.59 | GY34: 918.53 | GZ34: 929.61 | HA34: 907.98 | HB34: 891.73 | HC34: 889.89 | HD34: 889.64 | HE34: 869.83 | HF34: 854.65 | HG34: 851.015 | HH34: 832.35 | HI34: 831.48 | HJ34: 826.28 | HK34: 818.5 | HL34: 820.36 | HM34: 821.97 | HN34: 836.39 | HO34: 829.83 | HP34: 817.32 | HQ34: 812.18 | HR34: 814.17 | HS34: 834.75 | HT34: 849.46 | HU34: 843.66 | HV34: 837.28 | HW34: 815.61 | HX34: 812.95 | HY34: 799.56 | HZ34: 796.92 | IA34: 804.9 | IB34: 798.94 | IC34: 797.35 | ID34: 787.94 | IE34: 800 | IF34: 791.59 | IG34: 767.33 | IH34: 737.56 | II34: 719.04 | IJ34: 711.62 | IK34: 711.09 | IL34: 729.76 | IM34: 734.39 | IN34: 740.03 | IO34: 736.76 | IP34: 731.77 | IQ34: 734.35 | IR34: 752.32 | IS34: 756.83 | IT34: 756.38 | IU34: 763.52 | IV34: 762.89 | IW34: 767 | IX34: 768 | IY34: 750.78 | IZ34: 733.66 | JA34: 722.01 | JB34: 706.41 | JC34: 712.2 | JD34: 704.07 | JE34: 707.96 | JF34: 708.09 | JG34: 677.32 | JH34: 660 | JI34: 663.73 | JJ34: 660.97 | JK34: 656.89 | JL34: 661.32 | JM34: 653.83 | JN34: 652.43 | JO34: 646.6 | JP34: 637.56 | JQ34: 638.9 | JR34: 661.83 | JS34: 672.35 | JT34: 673.15 | JU34: 674.9 | JV34: 690.32 | JW34: 673.8 | JX34: 670.33 | JY34: 598.89 | JZ34: 598.79 | KA34: 595.19 | KB34: 591.99 | KC34: 591.74 | KD34: 575.42 | KE34: 571.23 | KF34: 566.14 | KG34: 564.59 | KH34: 572.71 | KI34: 577.92 | KJ34: 555.96 | KK34: 561.28 | KL34: 560.24 | KM34: 563.31 | KN34: 555.19 | KO34: 538.64 | KP34: 546.04 | KQ34: 543.48 | KR34: 545.11 | KS34: 542.47 | KT34: 551.22
A35: x | D35: =+D34+1 -> 25 | E35: CSL | F35: CSL AU | G35: 123.06 | H35: =+G35*L35*AUD -> 39870.855 | I35: =[26]Main!$J$5-[26]Main!$J$6 -> -9118 | J35: =H35-I35 -> 48988.855 | K35: Q425 | L35: =+[26]Main!$J$3 -> 483.575 | M35: 46232 | S35: =($J35/$L35)/AB35 -> 15.120239 | T35: =($J35/$L35)/AC35 -> 11.218782 | U35: =($J35/$L35)/AD35 -> 10.928328 | V35: =($J35/$L35)/AE35 -> 9.521203 | AB35: 6.7 | AC35: 9.03 | AD35: 9.27 | AE35: 10.64 | AF35: 12.17 | AG35: 13.65 | AN35: Australia
A36: x | D36: =+D35+1 -> 26 | E36: Samsung Biologics | F36: 207940 KS | G36: 1485000 | H36: =+G36*L36/KRW -> 47970.734 | I36: =([27]Main!$M$5-[27]Main!$M$6)/KRW*1000 -> 489.18353 | J36: =+H36-I36 -> 47481.551 | K36: Q126 | L36: =+[27]Main!$M$3 -> 46.290951 | M36: 46230 | AN36: South Korea
A37: x | D37: =+D36+1 -> 27 | E37: UCB | F37: UCB | G37: 222.9 | H37: =+G37*L37*EUR -> 47009.61 | I37: =([28]Main!$J$5-[28]Main!$J$6)*EUR -> 7.77 | J37: =H37-I37 -> 47001.84 | K37: Q425 | L37: =+[28]Main!$J$3 -> 190 | M37: 46232 | W37: =($J37/$L37)/AF37 -> 21.418018 | X37: =($J37/$L37)/AG37 -> 17.965004 | Y37: =($J37/$L37)/AH37 -> 14.911278 | Z37: =($J37/$L37)/AI37 -> 12.33806 | AA37: =($J37/$L37)/AJ37 -> 10.888121 | AB37: 2.54 | AC37: 2.04 | AD37: 3.63 | AE37: 8.45 | AF37: 11.55 | AG37: 13.77 | AH37: 16.59 | AI37: 20.05 | AJ37: 22.72 | AK37: 25.1 | AN37: Belgium
A38: x | D38: =+D37+1 -> 28 | E38: Royalty Pharma | F38: RPRX | G38: 55.88 | H38: =+G38*L38 -> 32177.504 | I38: =+[29]Main!$L$5-[29]Main!$L$6 -> -7546.661 | J38: =+H38-I38 -> 39724.165 | K38: Q126 | L38: =+[29]Main!$L$3 -> 575.8322 | M38: 46235 | W38: =($J38/$L38)/AF38 -> 12.99165 | X38: =($J38/$L38)/AG38 -> 14.107497 | Y38: =($J38/$L38)/AH38 -> 12.565694 | Z38: =($J38/$L38)/AI38 -> 13.421335 | AA38: =($J38/$L38)/AJ38 -> 11.752242 | AB38: 1.6 | AC38: 1.53 | AD38: 1.19 | AE38: 1.97 | AF38: 5.31 | AG38: 4.89 | AH38: 5.49 | AI38: 5.14 | AJ38: 5.87 | AK38: - | AL38: 1996 | AN38: United States | AO38: =BD38/FV38-1 -> 0.45522774 | AP38: =BD38/BX38-1 -> 0.0084289813 | AQ38: =BD38/CA38-1 -> 0.044002971 | AR38: =BD38/KT38-1 -> 0.56064391 | BD38: 56.23 | BE38: 54.69 | BF38: 54.28 | BG38: 55.35 | BH38: 53.57 | BJ38: 52.96 | BK38: 53.7 | BL38: 54.21 | BM38: 54.27 | BN38: 54.87 | BO38: 55.29 | BP38: 54.52 | BQ38: 55.63 | BR38: 54.86 | BS38: 55.87 | BT38: 55.02 | BU38: 54.97 | BV38: 54.01 | BW38: 55.18 | BX38: 55.76 | BY38: 54.48 | BZ38: 53.97 | CA38: 53.86 | CB38: 54.5 | CC38: 53.55 | CD38: 53.06 | CE38: 52.41 | CF38: 52.07 | CG38: 52.85 | CH38: 53.4 | CI38: 53.25 | CJ38: 51.7 | CK38: 51.65 | CL38: 50.79 | CM38: 50.2 | CN38: 50.72 | CO38: 50.44 | CP38: 50.2 | CQ38: 49.47 | CR38: 50.09 | CS38: 49.49 | CT38: 49.54 | CU38: 49.65 | CV38: 49.38 | CW38: 49.64 | CX38: 49.72 | CY38: 49.48 | CZ38: 49.3 | DA38: 50 | DB38: 48.48 | DC38: 48.7 | DD38: 48.82 | DE38: 48.43 | DF38: 47.9 | DG38: 48.3 | DH38: 47.9 | DI38: 46.87 | DJ38: 47.32 | DK38: 48.57 | DL38: 48.49 | DM38: 47.97 | DN38: 46.37 | DO38: 46.35 | DP38: 46.94 | DQ38: 47.03 | DR38: 45.57 | DS38: 45.61 | DT38: 45.36 | DU38: 45.53 | DV38: 45.79 | DW38: 46.11 | DX38: 46.1 | DY38: 45.65 | DZ38: 45.87 | EA38: 46.69 | EB38: 45.97 | EC38: 45.84 | ED38: 45.41 | EE38: 45.68 | EF38: 47.43 | EG38: 47.48 | EH38: 47.47 | EI38: 46.21 | EJ38: 45.36 | EK38: 45.15 | EL38: 45.4 | EM38: 45.47 | EN38: 45.12 | EO38: 45.11 | EP38: 45.34 | EQ38: 45.41 | ER38: 45.19 | ES38: 44.8 | ET38: 44.25 | EU38: 44.21 | EV38: 44.05 | EW38: 44.65 | EX38: 44.1 | EY38: 43.68 | EZ38: 42.97 | FA38: 42.36 | FB38: 41.68 | FC38: 40.86 | FD38: 40.41 | FE38: 40.74 | FF38: 40.47 | FG38: 40.4 | FH38: 40.11 | FI38: 39.72 | FJ38: 39.09 | FK38: 39.55 | FL38: 39.72 | FM38: 40.21 | FN38: 40.36 | FO38: 40.26 | FP38: 40.17 | FQ38: 40.26 | FR38: 41.39 | FS38: 40.65 | FT38: 39.65 | FU38: 38.86 | FV38: 38.64 | FW38: 38.99 | FX38: 39.08 | FY38: 39.22 | FZ38: 39.25 | GA38: 39.39 | GB38: 38.86 | GC38: 38.6 | GD38: 38.43 | GE38: 38.31 | GF38: 38.38 | GG38: 38.53 | GH38: 38.39 | GI38: 38.81 | GJ38: 38.26 | GK38: 38.09 | GL38: 38.67 | GM38: 39.73 | GN38: 39.15 | GO38: 39.6 | GP38: 39.53 | GQ38: 39.9 | GR38: 40.02 | GS38: 39.84 | GT38: 39.54 | GU38: 39.75 | GV38: 38.92 | GW38: 38.39 | GX38: 38.65 | GY38: 39.46 | GZ38: 39.16 | HA38: 39.16 | HB38: 39.73 | HC38: 39.59 | HD38: 38.96 | HE38: 38.54 | HF38: 38.56 | HG38: 40.78 | HH38: 40.42 | HI38: 37.84 | HJ38: 37.3 | HK38: 37.54 | HL38: 36.94 | HM38: 36.67 | HN38: 36.41 | HO38: 37.26 | HP38: 37.26 | HQ38: 36.85 | HR38: 36.84 | HS38: 37.48 | HT38: 36.63 | HU38: 37.01 | HV38: 36.34 | HW38: 36.18 | HX38: 36 | HY38: 35.44 | HZ38: 36.01 | IA38: 36.14 | IB38: 36.02 | IC38: 36.1 | ID38: 36.13 | IE38: 36.07 | IF38: 36.49 | IG38: 36.32 | IH38: 35.28 | II38: 35.25 | IJ38: 35.04 | IK38: 34.9 | IL38: 35.77 | IM38: 36.24 | IN38: 35.86 | IO38: 36.24 | IP38: 35.73 | IQ38: 35.64 | IR38: 35.42 | IS38: 35.15 | IT38: 36.36 | IU38: 36.7 | IV38: 36.18 | IW38: 36.5 | IX38: 35.8 | IY38: 36.07 | IZ38: 36.9 | JA38: 36.66 | JB38: 36.17 | JC38: 35.98 | JD38: 35.62 | JE38: 36.06 | JF38: 35.98 | JG38: 35.99 | JH38: 36.32 | JI38: 36.31 | JJ38: 36.88 | JK38: 36 | JL38: 35.92 | JM38: 36.35 | JN38: 36.5 | JO38: 36.46 | JP38: 35.86 | JQ38: 36.19 | JR38: 37.58 | JS38: 37.01 | JT38: 37.12 | JU38: 37.91 | JV38: 37.88 | JW38: 37.11 | JX38: 36.8 | JY38: 37.12 | JZ38: 37.27 | KA38: 37.06 | KB38: 36.67 | KC38: 36.59 | KD38: 36.01 | KE38: 36.1 | KF38: 35.65 | KG38: 35.59 | KH38: 35.47 | KI38: 35.6 | KJ38: 36.51 | KK38: 36.24 | KL38: 35.84 | KM38: 36.12 | KN38: 35.87 | KO38: 35.51 | KP38: 35.59 | KQ38: 36.37 | KR38: 36.19 | KS38: 35.88 | KT38: 36.03
A39: x | D39: =+D38+1 -> 29 | E39: Revolution | F39: RVMD | G39: 187.53 | H39: =+G39*L39 -> 39868.215 | I39: =+[30]Main!$J$5-[30]Main!$J$6 -> 1947.651 | J39: =+H39-I39 -> 37920.564 | K39: Q126 | L39: =+[30]Main!$J$3 -> 212.59646 | M39: 46235 | W39: - | X39: - | Y39: - | Z39: =($J39/$L39)/AI39 -> 48.868149 | AA39: =($J39/$L39)/AJ39 -> 16.530931 | AB39: -3.08 | AC39: -3.86 | AD39: -3.58 | AE39: -5.95 | AF39: -9.42 | AG39: -6.55 | AH39: -3.5 | AI39: 3.65 | AJ39: 10.79 | AK39: 16.75 | AN39: United States
A40: x | D40: =+D39+1 -> 30 | E40: Biogen | F40: BIIB | G40: 202.95 | H40: =+G40*L40 -> 29986.674 | I40: =+[31]Main!$J$5-[31]Main!$J$6 -> -6805.3 | J40: =+H40-I40 -> 36791.974 | K40: Q226 | L40: =+[31]Main!$J$3 -> 147.754 | M40: 46235 | W40: =($J40/$L40)/AF40 -> 19.762565 | X40: =($J40/$L40)/AG40 -> 15.100565 | Y40: =($J40/$L40)/AH40 -> 13.651772 | Z40: =($J40/$L40)/AI40 -> 12.678631 | AA40: =($J40/$L40)/AJ40 -> 12.128997 | AB40: 19.84 | AC40: 11.33 | AD40: 12.4 | AE40: 13.83 | AF40: 12.6 | AG40: 16.49 | AH40: 18.24 | AI40: 19.64 | AJ40: 20.53 | AK40: 21.54 | AL40: 1978 | AM40: Boston | AN40: United States | AO40: =BD40/FV40-1 -> 0.22751293 | AP40: =BD40/BX40-1 -> 0.10219388 | AQ40: =BD40/CA40-1 -> 0.11886265 | AR40: =BD40/KT40-1 -> 0.72012103 | BD40: 216.03 | BE40: 201.96 | BF40: 199.59 | BG40: 197.19 | BH40: 199.71 | BJ40: 196.58 | BK40: 198.67 | BL40: 195.61 | BM40: 198.64 | BN40: 200.05 | BO40: 199.96 | BP40: 194.24 | BQ40: 199.1 | BR40: 192.62 | BS40: 195.34 | BT40: 196.45 | BU40: 195.96 | BV40: 188.83 | BW40: 192.23 | BX40: 196 | BY40: 196.39 | BZ40: 196.97 | CA40: 193.08 | CB40: 193.76 | CC40: 189.47 | CD40: 187.8 | CE40: 190.56 | CF40: 191.91 | CG40: 192.95 | CH40: 191.37 | CI40: 204.53 | CJ40: 199.36 | CK40: 197.95 | CL40: 193.45 | CM40: 191.38 | CN40: 190.68 | CO40: 189.13 | CP40: 187.21 | CQ40: 187.06 | CR40: 189.28 | CS40: 194.38 | CT40: 183.38 | CU40: 180.67 | CV40: 184.38 | CW40: 187.88 | CX40: 190.07 | CY40: 185.95 | CZ40: 183.34 | DA40: 177.35 | DB40: 176.02 | DC40: 180.54 | DD40: 178.96 | DE40: 176.365 | DF40: 172.97 | DG40: 177.11 | DH40: 179.9 | DI40: 175.61 | DJ40: 172.34 | DK40: 177.34 | DL40: 183.78 | DM40: 183.33 | DN40: 187.57 | DO40: 183.84 | DP40: 191.06 | DQ40: 189.18 | DR40: 183.94 | DS40: 183.64 | DT40: 181.46 | DU40: 183.41 | DV40: 182.31 | DW40: 185.29 | DX40: 183.26 | DY40: 181.55 | DZ40: 184.9 | EA40: 190.48 | EB40: 188.41 | EC40: 188.24 | ED40: 184.87 | EE40: 188.08 | EF40: 189.94 | EG40: 184.02 | EH40: 188.05 | EI40: 191.82 | EJ40: 188.02 | EK40: 190.73 | EL40: 195.13 | EM40: 196.34 | EN40: 192.03 | EO40: 192.08 | EP40: 194.13 | EQ40: 195.62 | ER40: 196.52 | ES40: 195.5 | ET40: 191.2 | EU40: 188.99 | EV40: 193.81 | EW40: 201.18 | EX40: 185.36 | EY40: 185.45 | EZ40: 176.76 | FA40: 179.09 | FB40: 179.89 | FC40: 176.18 | FD40: 174.83 | FE40: 174.12 | FF40: 173.12 | FG40: 171.59 | FH40: 173.8 | FI40: 172.62 | FJ40: 165.38 | FK40: 164.42 | FL40: 168.57 | FM40: 169.31 | FN40: 178.3 | FO40: 185.63 | FP40: 187.62 | FQ40: 186 | FR40: 186.91 | FS40: 182.61 | FT40: 174.63 | FU40: 177.82 | FV40: 175.99 | FW40: 176.4 | FX40: 176.83 | FY40: 177.08 | FZ40: 176.33 | GA40: 174.82 | GB40: 174.7 | GC40: 174.8 | GD40: 169.91 | GE40: 172.1 | GF40: 171.5 | GG40: 175.74 | GH40: 174.1 | GI40: 172.5 | GJ40: 177.55 | GK40: 175.84 | GL40: 180.44 | GM40: 181.3 | GN40: 181.98 | GO40: 180.75 | GP40: 180.18 | GQ40: 177.78 | GR40: 182.09 | GS40: 181.94 | GT40: 181.96 | GU40: 176.82 | GV40: 175.3 | GW40: 168.18 | GX40: 167.93 | GY40: 168.83 | GZ40: 164.68 | HA40: 167.55 | HB40: 164.73 | HC40: 161.48 | HD40: 159.56 | HE40: 156.26 | HF40: 155.51 | HG40: 156.74 | HH40: 153.43 | HI40: 149.33 | HJ40: 151.44 | HK40: 154.27 | HL40: 149.61 | HM40: 147.86 | HN40: 149.13 | HO40: 150.43 | HP40: 149.89 | HQ40: 150.08 | HR40: 147.72 | HS40: 146.22 | HT40: 146.63 | HU40: 143 | HV40: 142.26 | HW40: 143.66 | HX40: 145.31 | HY40: 144.69 | HZ40: 146.57 | IA40: 149.61 | IB40: 150.97 | IC40: 152.21 | ID40: 154.05 | IE40: 159.88 | IF40: 155.25 | IG40: 154.22 | IH40: 140.08 | II40: 138.52 | IJ40: 137.37 | IK40: 135.67 | IL40: 137.67 | IM40: 139.31 | IN40: 140.66 | IO40: 142.5 | IP40: 143.81 | IQ40: 144.87 | IR40: 143.68 | IS40: 143.32 | IT40: 144.86 | IU40: 148.84 | IV40: 142.61 | IW40: 143.6 | IX40: 141.35 | IY40: 140.67 | IZ40: 139.94 | JA40: 141.62 | JB40: 139.63 | JC40: 132.22 | JD40: 132.65 | JE40: 136.36 | JF40: 136.72 | JG40: 136.36 | JH40: 139.31 | JI40: 139.12 | JJ40: 138.99 | JK40: 138.86 | JL40: 135.91 | JM40: 138.6 | JN40: 134.94 | JO40: 135.19 | JP40: 128.93 | JQ40: 128 | JR40: 130.67 | JS40: 127.75 | JT40: 129.34 | JU40: 132.89 | JV40: 132.2 | JW40: 131.95 | JX40: 128 | JY40: 126.64 | JZ40: 127.9 | KA40: 129.28 | KB40: 131.52 | KC40: 132.59 | KD40: 130.98 | KE40: 127.85 | KF40: 122.68 | KG40: 124.99 | KH40: 128.69 | KI40: 128.46 | KJ40: 127.5 | KK40: 133.11 | KL40: 134.21 | KM40: 135.33 | KN40: 133.02 | KO40: 134.46 | KP40: 130.13 | KQ40: 132.87 | KR40: 133.19 | KS40: 130.07 | KT40: 125.59
A41: x | D41: =+D40+1 -> 31 | E41: Viatris | F41: VTRS | G41: 17.65 | H41: =G41*[32]Main!$M$3 -> 20554.354 | I41: =[32]Main!$M$5-[32]Main!$M$6 -> -12540.4 | J41: =H41-I41 -> 33094.754 | K41: Q126 | L41: =+[32]Main!$M$3 -> 1164.5527 | M41: 46235 | W41: =($J41/$L41)/AF41 -> 11.413023 | X41: =($J41/$L41)/AG41 -> 10.723935 | Y41: =($J41/$L41)/AH41 -> 9.9018909 | Z41: =($J41/$L41)/AI41 -> 9.4413378 | AA41: =($J41/$L41)/AJ41 -> 8.8255984 | AB41: 1.58 | AC41: 1.22 | AD41: 0.78 | AE41: 0.58 | AF41: 2.49 | AG41: 2.65 | AH41: 2.87 | AI41: 3.01 | AJ41: 3.22 | AK41: - | AL41: 1961 | AN41: United States | AO41: =BD41/FV41-1 -> 0.31164659 | AP41: =BD41/BX41-1 -> 0.0043050431 | AQ41: =BD41/CA41-1 -> 0.0043050431 | AR41: =BD41/KT41-1 -> 0.82866741 | BD41: 16.33 | BE41: 16.07 | BF41: 15.93 | BG41: 15.75 | BH41: 15.38 | BJ41: 15.37 | BK41: 15.73 | BL41: 16.04 | BM41: 16.32 | BN41: 16.48 | BO41: 16.31 | BP41: 15.77 | BQ41: 16.2 | BR41: 15.93 | BS41: 15.88 | BT41: 15.9 | BU41: 15.56 | BV41: 15.69 | BW41: 15.81 | BX41: 16.26 | BY41: 16.11 | BZ41: 16.29 | CA41: 16.26 | CB41: 16.65 | CC41: 16.46 | CD41: 16.59 | CE41: 16.17 | CF41: 16.5 | CG41: 16.48 | CH41: 17.26 | CI41: 17.37 | CJ41: 17.17 | CK41: 16.92 | CL41: 17.17 | CM41: 17.39 | CN41: 15.95 | CO41: 15.52 | CP41: 15.2 | CQ41: 15.04 | CR41: 14.94 | CS41: 14.97 | CT41: 14.82 | CU41: 14.81 | CV41: 14.59 | CW41: 14.75 | CX41: 14.52 | CY41: 14.73 | CZ41: 14.87 | DA41: 14.68 | DB41: 14.01 | DC41: 13.86 | DD41: 13.91 | DE41: 13.83 | DF41: 13.47 | DG41: 13.61 | DH41: 13.57 | DI41: 13.16 | DJ41: 13.41 | DK41: 13.44 | DL41: 13.63 | DM41: 13.51 | DN41: 12.96 | DO41: 13.05 | DP41: 13.37 | DQ41: 13.5 | DR41: 13.36 | DS41: 13.29 | DT41: 13.2 | DU41: 13.5 | DV41: 13.74 | DW41: 13.8 | DX41: 13.51 | DY41: 13.51 | DZ41: 13.8 | EA41: 13.97 | EB41: 14.08 | EC41: 14.22 | ED41: 14.16 | EE41: 14.53 | EF41: 14.71 | EG41: 14.89 | EH41: 15.7 | EI41: 14.93 | EJ41: 15.25 | EK41: 16.08 | EL41: 16.065 | EM41: 15.95 | EN41: 15.92 | EO41: 15.98 | EP41: 16.05 | EQ41: 15.74 | ER41: 15.77 | ES41: 15.79 | ET41: 16.13 | EU41: 15.95 | EV41: 15.56 | EW41: 14.58 | EX41: 14.34 | EY41: 14.36 | EZ41: 13.68 | FA41: 13.68 | FB41: 13.09 | FC41: 13.07 | FD41: 12.97 | FE41: 13.12 | FF41: 13.17 | FG41: 13.21 | FH41: 13.24 | FI41: 13.05 | FJ41: 12.66 | FK41: 12.86 | FL41: 12.84 | FM41: 13.15 | FN41: 13.37 | FO41: 12.68 | FP41: 12.76 | FQ41: 12.6 | FR41: 12.46 | FS41: 12.4 | FT41: 12.37 | FU41: 12.46 | FV41: 12.45 | FW41: 12.54 | FX41: 12.37 | FY41: 12.32 | FZ41: 12.24 | GA41: 12.02 | GB41: 12.01 | GC41: 11.93 | GD41: 11.94 | GE41: 11.7 | GF41: 11.46 | GG41: 11.66 | GH41: 11.65 | GI41: 11.59 | GJ41: 11.6 | GK41: 11.19 | GL41: 11.09 | GM41: 10.93 | GN41: 10.76 | GO41: 10.84 | GP41: 10.71 | GQ41: 10.7 | GR41: 10.69 | GS41: 10.64 | GT41: 10.56 | GU41: 10.57 | GV41: 10.46 | GW41: 10.19 | GX41: 10.46 | GY41: 10.71 | GZ41: 10.66 | HA41: 10.72 | HB41: 10.91 | HC41: 11.01 | HD41: 11.2 | HE41: 10.17 | HF41: 10.12 | HG41: 10.11 | HH41: 10.75 | HI41: 10.49 | HJ41: 10.53 | HK41: 10.36 | HL41: 10.36 | HM41: 10.27 | HN41: 10.29 | HO41: 10.42 | HP41: 10.35 | HQ41: 10.31 | HR41: 10.41 | HS41: 10.39 | HT41: 10.31 | HU41: 10.17 | HV41: 10.1 | HW41: 9.98 | HX41: 9.93 | HY41: 9.86 | HZ41: 9.74 | IA41: 9.99 | IB41: 9.97 | IC41: 10.14 | ID41: 10.13 | IE41: 10.19 | IF41: 10.11 | IG41: 10.09 | IH41: 9.9 | II41: 9.62 | IJ41: 9.52 | IK41: 9.49 | IL41: 9.71 | IM41: 9.6 | IN41: 9.79 | IO41: 9.9 | IP41: 9.86 | IQ41: 9.62 | IR41: 9.56 | IS41: 9.6 | IT41: 9.96 | IU41: 10.17 | IV41: 10.24 | IW41: 10.45 | IX41: 10.48 | IY41: 10.5 | IZ41: 10.33 | JA41: 10.55 | JB41: 10.56 | JC41: 10.55 | JD41: 10.41 | JE41: 10.42 | JF41: 10.41 | JG41: 10.55 | JH41: 10.65 | JI41: 10.69 | JJ41: 10.65 | JK41: 10.68 | JL41: 10.63 | JM41: 10.61 | JN41: 10.69 | JO41: 10.41 | JP41: 10.12 | JQ41: 9.86 | JR41: 9.7 | JS41: 9.39 | JT41: 8.75 | JU41: 8.98 | JV41: 8.94 | JW41: 8.81 | JX41: 8.74 | JY41: 9 | JZ41: 9.19 | KA41: 9.26 | KB41: 9.41 | KC41: 9.35 | KD41: 9.37 | KE41: 9.24 | KF41: 8.9 | KG41: 8.88 | KH41: 9.27 | KI41: 9.08 | KJ41: 8.93 | KK41: 9.14 | KL41: 9.12 | KM41: 9.25 | KN41: 9.23 | KO41: 9.26 | KP41: 9.2 | KQ41: 9.32 | KR41: 9.34 | KS41: 9.18 | KT41: 8.93
A42: x | D42: =+D41+1 -> 32 | E42: Celltrion | F42: 068270 KS | G42: 186700 | H42: =+G42*L42/KRW -> 30091.007 | I42: =([33]Main!$J$5-[33]Main!$J$6)/KRW -> -1833.217 | J42: =H42-I42 -> 31924.224 | K42: Q126 | L42: =+[33]Main!$J$3 -> 230.96097 | M42: 46235 | AN42: South Korea
A43: x | D43: =+D42+1 -> 33 | E43: BeOne | F43: ONC | G43: 316.01 | H43: =+G43*L43 -> 35132.104 | I43: =[34]Main!$L$5-[34]Main!$L$6 -> 3713.021 | J43: =H43-I43 -> 31419.083 | K43: Q126 | L43: =+[34]Main!$L$3 -> 111.17403 | M43: 46235 | AO43: =BD43/FV43-1 -> -0.078733419 | AP43: =BD43/BX43-1 -> -0.027889692 | AQ43: =BD43/CA43-1 -> -0.074560243 | AR43: =BD43/KT43-1 -> 0.1562358 | BD43: 279.89 | BE43: 275.34 | BF43: 277.12 | BG43: 276.13 | BH43: 271.8 | BJ43: 270.15 | BK43: 262.68 | BL43: 263.92 | BM43: 268.2 | BN43: 264.48 | BO43: 260.27 | BP43: 263.61 | BQ43: 268.17 | BR43: 270.8 | BS43: 270.1 | BT43: 279.93 | BU43: 279 | BV43: 274.69 | BW43: 279.68 | BX43: 287.92 | BY43: 290.58 | BZ43: 300.01 | CA43: 302.44 | CB43: 310.25 | CC43: 309.62 | CD43: 308.74 | CE43: 297.01 | CF43: 293.09 | CG43: 293.27 | CH43: 304.62 | CI43: 316.55 | CJ43: 315.07 | CK43: 310.75 | CL43: 312.12 | CM43: 317 | CN43: 313.32 | CO43: 297.49 | CP43: 297.14 | CQ43: 293.86 | CR43: 295.27 | CS43: 290.8 | CT43: 298.16 | CU43: 298.9 | CV43: 300.8 | CW43: 299.81 | CX43: 312.41 | CY43: 312.31 | CZ43: 318.07 | DA43: 323.87 | DB43: 320.7 | DC43: 319.94 | DD43: 310 | DE43: 305.64 | DF43: 309.66 | DG43: 313.42 | DH43: 312.19 | DI43: 303.82 | DJ43: 302.49 | DK43: 310.79 | DL43: 308.44 | DM43: 296.97 | DN43: 284.08 | DO43: 283.03 | DP43: 276.95 | DQ43: 283.45 | DR43: 275.69 | DS43: 274.73 | DT43: 275.28 | DU43: 282.72 | DV43: 282.29 | DW43: 287.33 | DX43: 289.65 | DY43: 284.05 | DZ43: 285.3 | EA43: 298.91 | EB43: 305.39 | EC43: 302.29 | ED43: 301.12 | EE43: 292.94 | EF43: 299.02 | EG43: 297.04 | EH43: 314.36 | EI43: 316.99 | EJ43: 322.37 | EK43: 352.23 | EL43: 369 | EM43: 370.64 | EN43: 362.14 | EO43: 354.48 | EP43: 359.05 | EQ43: 354.86 | ER43: 346.07 | ES43: 346.42 | ET43: 351.27 | EU43: 353.43 | EV43: 348.85 | EW43: 353.92 | EX43: 347 | EY43: 352 | EZ43: 346.38 | FA43: 345 | FB43: 340.38 | FC43: 350 | FD43: 350 | FE43: 336.16 | FF43: 337.79 | FG43: 339.32 | FH43: 338.81 | FI43: 341.64 | FJ43: 334.28 | FK43: 338.19 | FL43: 338.29 | FM43: 346.75 | FN43: 351.06 | FO43: 333.99 | FP43: 337.89 | FQ43: 320.37 | FR43: 333.87 | FS43: 320.35 | FT43: 320.3 | FU43: 311.02 | FV43: 303.81 | FW43: 304.72 | FX43: 310.3 | FY43: 312.39 | FZ43: 311.73 | GA43: 312.32 | GB43: 313.36 | GC43: 316.05 | GD43: 307.02 | GE43: 306.05 | GF43: 304.31 | GG43: 310.67 | GH43: 319.06 | GI43: 320.84 | GJ43: 322.68 | GK43: 318.69 | GL43: 326.49 | GM43: 322.9 | GN43: 331.4 | GO43: 337.86 | GP43: 330.185 | GQ43: 335.6 | GR43: 340.61 | GS43: 340.64 | GT43: 335.17 | GU43: 332.71 | GV43: 347.72 | GW43: 349.29 | GX43: 353.79 | GY43: 363.92 | GZ43: 376.63 | HA43: 365.82 | HB43: 368.36 | HC43: 377.47 | HD43: 343.65 | HE43: 329.2 | HF43: 319.97 | HG43: 332.36 | HH43: 321.39 | HI43: 309.19 | HJ43: 311.86 | HK43: 310.48 | HL43: 308.22 | HM43: 314.85 | HN43: 316.85 | HO43: 315.43 | HP43: 310.81 | HQ43: 310.03 | HR43: 313.54 | HS43: 315.735 | HT43: 318.59 | HU43: 316.42 | HV43: 318.02 | HW43: 316.15 | HX43: 320.94 | HY43: 327.03 | HZ43: 320.1 | IA43: 335.8 | IB43: 351.09 | IC43: 341.62 | ID43: 344.53 | IE43: 343.87 | IF43: 345.17 | IG43: 335.16 | IH43: 340.7 | II43: 332.83 | IJ43: 326.06 | IK43: 328.71 | IL43: 329.84 | IM43: 329.07 | IN43: 337.815 | IO43: 334.4 | IP43: 342.89 | IQ43: 332.2 | IR43: 327.2 | IS43: 332.27 | IT43: 324.34 | IU43: 335.67 | IV43: 313.93 | IW43: 351.13 | IX43: 346.45 | IY43: 341.8 | IZ43: 318.73 | JA43: 336.26 | JB43: 332.04 | JC43: 306.05 | JD43: 297.96 | JE43: 300.14 | JF43: 308.91 | JG43: 308.63 | JH43: 313.67 | JI43: 313.97 | JJ43: 309.33 | JK43: 312.51 | JL43: 319.32 | JM43: 321.36 | JN43: 309.69 | JO43: 307.51 | JP43: 288.1 | JQ43: 289.75 | JR43: 288.18 | JS43: 298.29 | JT43: 298.52 | JU43: 307.23 | JV43: 304.3 | JW43: 299.01 | JX43: 301.13 | JY43: 299.94 | JZ43: 305.74 | KA43: 294.51 | KB43: 291.47 | KC43: 296.46 | KD43: 294.83 | KE43: 295.59 | KF43: 291.93 | KG43: 294.55 | KH43: 290.35 | KI43: 279.16 | KJ43: 269.7 | KK43: 252.14 | KL43: 250.3 | KM43: 253.39 | KN43: 255.69 | KO43: 244.47 | KP43: 240.99 | KQ43: 245.49 | KR43: 244.32 | KS43: 245.16 | KT43: 242.07
A44: x | D44: =+D43+1 -> 34 | E44: Otsuka | F44: 4578 JP | G44: 11100 | H44: =+G44*L44/JPY -> 35707.254 | I44: =([35]Main!$L$5-[35]Main!$L$6)/JPY -> 5737.1681 | J44: =H44-I44 -> 29970.086 | K44: Q226 | L44: =+[35]Main!$L$3 -> 527.08411 | M44: 46235 | AN44: Japan
A45: x | D45: =+D44+1 -> 35 | E45: Sandoz | F45: SDZ SW | G45: 72.12 | H45: =+G45*L45/CHF -> 38652.088 | I45: =[36]Main!$J$5-[36]Main!$J$6 -> -3548 | J45: =+H45-I45 -> 42200.088 | K45: Q226 | L45: =+[36]Main!$J$3 -> 438.4 | M45: 46244
A46: x | D46: =+D45+1 -> 36 | E46: Daiichi Sankyo | F46: 4568 JP | G46: 2568 | H46: =+G46*L46/JPY -> 29689.912 | I46: =([37]Main!$M$5-[37]Main!$M$6)*1000/JPY -> 2444.7116 | J46: =+H46-I46 -> 27245.201 | K46: Q126 | L46: =+[37]Main!$M$3 -> 1894.3505 | M46: 46232 | AN46: Japan
A47: x | D47: =+D46+1 -> 37 | E47: Astellas | F47: 4503 JP | G47: 2202 | H47: =+G47*L47/JPY -> 24070.882 | I47: =([38]Main!$K$5-[38]Main!$K$6)/JPY -> -1389.112 | J47: =+H47-I47 -> 25459.993 | K47: Q126 | L47: =+[38]Main!$K$3 -> 1791.1053 | M47: 46235 | AL47: 1940 | AN47: Japan
A48: x | D48: =+D47+1 -> 38 | E48: Alnylam | F48: ALNY | G48: 204.5 | H48: =+G48*L48 -> 27303.321 | I48: =+[39]Main!$L$5-[39]Main!$L$6 -> 1999.851 | J48: =H48-I48 -> 25303.47 | K48: Q126 | L48: =+[39]Main!$L$3 -> 133.51257 | M48: 46229 | W48: =($J48/$L48)/AF48 -> 22.375591 | X48: =($J48/$L48)/AG48 -> 15.598457 | Y48: =($J48/$L48)/AH48 -> 12.617926 | Z48: =($J48/$L48)/AI48 -> 11.7278 | AA48: =($J48/$L48)/AJ48 -> 9.9853137 | AB48: -8.4 | AC48: -3.66 | AD48: -2.16 | AE48: 2.64 | AF48: 8.47 | AG48: 12.15 | AH48: 15.02 | AI48: 16.16 | AJ48: 18.98 | AK48: 22.69 | AL48: 2002 | AM48: Cambridge, MA | AN48: United States | AO48: =BD48/FV48-1 -> -0.26727021 | AP48: =BD48/BX48-1 -> -0.035134777 | AQ48: =BD48/CA48-1 -> -0.013976311 | AR48: =BD48/KT48-1 -> -0.10647367 | BD48: 291.37 | BE48: 293.17 | BF48: 294.06 | BG48: 288.18 | BH48: 286.41 | BJ48: 278.09 | BK48: 282.72 | BL48: 281.9 | BM48: 287.8 | BN48: 282.85 | BO48: 289.39 | BP48: 291.22 | BQ48: 297.69 | BR48: 292.16 | BS48: 303.05 | BT48: 303.64 | BU48: 292.58 | BV48: 286.12 | BW48: 295.63 | BX48: 301.98 | BY48: 305.06 | BZ48: 295.63 | CA48: 295.5 | CB48: 297.45 | CC48: 300.51 | CD48: 298.48 | CE48: 294.3 | CF48: 286.27 | CG48: 286.98 | CH48: 293.45 | CI48: 291.48 | CJ48: 292.03 | CK48: 284.84 | CL48: 295.05 | CM48: 295.91 | CN48: 303 | CO48: 301.11 | CP48: 297.925 | CQ48: 296.11 | CR48: 309.49 | CS48: 301.19 | CT48: 302.11 | CU48: 308.51 | CV48: 305.54 | CW48: 313.79 | CX48: 310.58 | CY48: 308.43 | CZ48: 310.94 | DA48: 309.66 | DB48: 320.13 | DC48: 333.39 | DD48: 339.41 | DE48: 333 | DF48: 322.11 | DG48: 321.28 | DH48: 327.25 | DI48: 319.52 | DJ48: 330.34 | DK48: 318.85 | DL48: 328.73 | DM48: 330.87 | DN48: 316.09 | DO48: 317.36 | DP48: 328.16 | DQ48: 328.7 | DR48: 308.05 | DS48: 306.66 | DT48: 312.17 | DU48: 311.1 | DV48: 314.8 | DW48: 320.42 | DX48: 318.91 | DY48: 313.41 | DZ48: 317.23 | EA48: 320.43 | EB48: 322.38 | EC48: 323.59 | ED48: 320.66 | EE48: 320.51 | EF48: 327.3 | EG48: 318.65 | EH48: 325.07 | EI48: 332.92 | EJ48: 331.24 | EK48: 327.36 | EL48: 332.85 | EM48: 329.35 | EN48: 336.19 | EO48: 339.37 | EP48: 332.68 | EQ48: 332.61 | ER48: 314.4 | ES48: 308.48 | ET48: 322.28 | EU48: 322.98 | EV48: 320 | EW48: 328.16 | EX48: 331.24 | EY48: 351.96 | EZ48: 351.8 | FA48: 339.11 | FB48: 338.06 | FC48: 346.79 | FD48: 349.58 | FE48: 354.75 | FF48: 361.35 | FG48: 357.98 | FH48: 370 | FI48: 365.46 | FJ48: 355.53 | FK48: 359.27 | FL48: 359.26 | FM48: 366.86 | FN48: 369.96 | FO48: 370.91 | FP48: 398.29 | FQ48: 399.4 | FR48: 422.5 | FS48: 406.4 | FT48: 397.83 | FU48: 400.17 | FV48: 397.65 | FW48: 397.25 | FX48: 398.82 | FY48: 400.59 | FZ48: 400.69 | GA48: 398.7 | GB48: 407.73 | GC48: 400.23 | GD48: 396.04 | GE48: 392.1 | GF48: 391.17 | GG48: 391.5 | GH48: 397.55 | GI48: 412.63 | GJ48: 404.46 | GK48: 415.21 | GL48: 430.02 | GM48: 458.12 | GN48: 465.34 | GO48: 473.29 | GP48: 464.93 | GQ48: 454.56 | GR48: 451.23 | GS48: 445.12 | GT48: 429.8 | GU48: 434.23 | GV48: 436.38 | GW48: 445.79 | GX48: 460.76 | GY48: 462.3 | GZ48: 460.54 | HA48: 449.16 | HB48: 453.97 | HC48: 452.74 | HD48: 451.95 | HE48: 441.7 | HF48: 442.7 | HG48: 440.49 | HH48: 434.56 | HI48: 423.47 | HJ48: 434.07 | HK48: 456.04 | HL48: 449.56 | HM48: 481.59 | HN48: 475.91 | HO48: 478.58 | HP48: 463.43 | HQ48: 464 | HR48: 464.9 | HS48: 474 | HT48: 491.22 | HU48: 481.67 | HV48: 481.07 | HW48: 470.27 | HX48: 469.36 | HY48: 464.95 | HZ48: 460.46 | IA48: 456.95 | IB48: 450.68 | IC48: 459.58 | ID48: 452 | IE48: 456.35 | IF48: 460.99 | IG48: 460.65 | IH48: 456 | II48: 447.49 | IJ48: 446.4 | IK48: 449.58 | IL48: 458.37 | IM48: 454.41 | IN48: 458.92 | IO48: 453.56 | IP48: 452.17 | IQ48: 451.725 | IR48: 461.24 | IS48: 461.14 | IT48: 465.89 | IU48: 468.58 | IV48: 469.31 | IW48: 482.13 | IX48: 455.03 | IY48: 452 | IZ48: 453.54 | JA48: 447.43 | JB48: 447 | JC48: 446.51 | JD48: 452.33 | JE48: 454.18 | JF48: 451.2 | JG48: 443.64 | JH48: 454.38 | JI48: 467.55 | JJ48: 458.31 | JK48: 458.28 | JL48: 456.87 | JM48: 448.91 | JN48: 442.73 | JO48: 432.52 | JP48: 429.93 | JQ48: 435 | JR48: 438.93 | JS48: 435.1 | JT48: 428.14 | JU48: 418.91 | JV48: 419.555 | JW48: 401.8 | JX48: 392.24 | JY48: 339.8 | JZ48: 330.55 | KA48: 324.79 | KB48: 328.81 | KC48: 328 | KD48: 325.64 | KE48: 325.28 | KF48: 320.52 | KG48: 320.53 | KH48: 324.69 | KI48: 322.81 | KJ48: 311.12 | KK48: 315.75 | KL48: 314.94 | KM48: 322.64 | KN48: 320.87 | KO48: 317.5 | KP48: 324.13 | KQ48: 331.91 | KR48: 329.77 | KS48: 322.06 | KT48: 326.09
A49: x | D49: =+D48+1 -> 39 | E49: Roivant | F49: ROIV | G49: 36.34 | H49: =+G49*L49 -> 25930.387 | I49: =+[40]Main!$K$5-[40]Main!$K$6 -> 5436.548 | J49: =+H49-I49 -> 20493.839 | K49: Q224 | L49: =+[40]Main!$K$3 -> 713.54946 | M49: 45540
A50: x | D50: =+D49+1 -> 40 | E50: Genmab | F50: GMAB | G50: 28.87 | H50: =+G50*L50*10 -> 18547.05 | I50: =([41]Main!$K$7-[41]Main!$K$8) -> -3647 | J50: =H50-I50 -> 22194.05 | K50: Q126 | L50: =+[41]Main!$K$4 -> 64.243333 | M50: 46235 | AL50: 1999 | AN50: Denmark
A51: x | D51: =+D50 -> 40 | E51: Genmab | F51: GMAB DC | G51: 1858.5 | H51: =+G51*L51/DKK -> 18414.83 | I51: =+I50 -> -3647 | J51: =H51-I51 -> 22061.83 | K51: Q126 | L51: =+[41]Main!$K$4 -> 64.243333 | M51: =+M50 -> 46235 | AL51: 1999 | AN51: Denmark
D52: =+D51+1 -> 41 | E52: Baxter | F52: BAX | G52: 26.16 | H52: =+G52*L52 -> 13510.829 | I52: =+[42]Main!$K$5-[42]Main!$K$6 -> -7446 | J52: =+H52-I52 -> 20956.829 | K52: Q126 | L52: =+[42]Main!$K$3 -> 516.46901 | M52: 46232 | AL52: 1931 | AN52: United States | AO52: =BD52/FV52-1 -> 0.15332287 | AP52: =BD52/BX52-1 -> 0.17358892 | AQ52: =BD52/CA52-1 -> 0.1372549 | AR52: =BD52/KT52-1 -> -0.27212682 | BD52: 22.04 | BE52: 21.55 | BF52: 21.04 | BG52: 20.1 | BH52: 19.66 | BJ52: 19.89 | BK52: 19.39 | BL52: 20.46 | BM52: 20.81 | BN52: 20.86 | BO52: 20.49 | BP52: 20.31 | BQ52: 20.03 | BR52: 19.24 | BS52: 19.38 | BT52: 19.35 | BU52: 18.54 | BV52: 18.68 | BW52: 18.4 | BX52: 18.78 | BY52: 19.25 | BZ52: 19.33 | CA52: 19.38 | CB52: 19.18 | CC52: 19.03 | CD52: 18.77 | CE52: 18.33 | CF52: 17.79 | CG52: 17.3 | CH52: 17.78 | CI52: 17.31 | CJ52: 17.89 | CK52: 17.53 | CL52: 17.99 | CM52: 17.49 | CN52: 16.98 | CO52: 16.75 | CP52: 16.62 | CQ52: 17.21 | CR52: 17.58 | CS52: 16.9 | CT52: 17.94 | CU52: 18.49 | CV52: 18.16 | CW52: 18.41 | CX52: 18.31 | CY52: 18.49 | CZ52: 18.84 | DA52: 18.71 | DB52: 18.14 | DC52: 17.6 | DD52: 17.59 | DE52: 17.63 | DF52: 17.15 | DG52: 17.3 | DH52: 17.24 | DI52: 16.62 | DJ52: 16.65 | DK52: 16.68 | DL52: 16.78 | DM52: 16.8 | DN52: 15.8 | DO52: 15.97 | DP52: 16.67 | DQ52: 17.12 | DR52: 16.72 | DS52: 16.61 | DT52: 16.15 | DU52: 16.66 | DV52: 17.09 | DW52: 17.62 | DX52: 17.08 | DY52: 17.4 | DZ52: 18.01 | EA52: 18.05 | EB52: 17.46 | EC52: 17.91 | ED52: 17.69 | EE52: 18.6 | EF52: 19.03 | EG52: 19.03 | EH52: 19.69 | EI52: 20.37 | EJ52: 20.36 | EK52: 20.73 | EL52: 20.63 | EM52: 21.26 | EN52: 21.58 | EO52: 21.34 | EP52: 21.87 | EQ52: 20.74 | ER52: 19.79 | ES52: 18.71 | ET52: 22.27 | EU52: 21.94 | EV52: 21.73 | EW52: 21.73 | EX52: 21.77 | EY52: 21.03 | EZ52: 19.91 | FA52: 19.87 | FB52: 20.07 | FC52: 19.73 | FD52: 19.61 | FE52: 19.57 | FF52: 19.65 | FG52: 19.84 | FH52: 20.07 | FI52: 19.71 | FJ52: 19.38 | FK52: 20.11 | FL52: 20.37 | FM52: 19.84 | FN52: 19.65 | FO52: 20.15 | FP52: 21.07 | FQ52: 20.69 | FR52: 20.4 | FS52: 20.55 | FT52: 19.89 | FU52: 19.5 | FV52: 19.11 | FW52: 19.3 | FX52: 19.25 | FY52: 19.38 | FZ52: 19.11 | GA52: 18.93 | GB52: 18.98 | GC52: 18.96 | GD52: 19.07 | GE52: 19.29 | GF52: 19.05 | GG52: 19.53 | GH52: 19.15 | GI52: 18.9 | GJ52: 18.26 | GK52: 18.16 | GL52: 18.16 | GM52: 18.54 | GN52: 18.48 | GO52: 18.89 | GP52: 18.84 | GQ52: 19.08 | GR52: 18.74 | GS52: 18.91 | GT52: 18.66 | GU52: 18.18 | GV52: 18.31 | GW52: 17.42 | GX52: 17.69 | GY52: 18.15 | GZ52: 17.77 | HA52: 18.47 | HB52: 18.7 | HC52: 18.7 | HD52: 18.25 | HE52: 17.75 | HF52: 18 | HG52: 17.98 | HH52: 17.95 | HI52: 17.94 | HJ52: 18.21 | HK52: 18.47 | HL52: 19.16 | HM52: 22.42 | HN52: 22.86 | HO52: 23.17 | HP52: 23.02 | HQ52: 22.99 | HR52: 22.93 | HS52: 22.75 | HT52: 23.13 | HU52: 23.09 | HV52: 22.97 | HW52: 22.75 | HX52: 22.82 | HY52: 22.11 | HZ52: 21.95 | IA52: 22.51 | IB52: 22.75 | IC52: 22.9 | ID52: 23.15 | IE52: 23.86 | IF52: 23.23 | IG52: 23.36 | IH52: 22.77 | II52: 22.38 | IJ52: 21.98 | IK52: 21.71 | IL52: 22.56 | IM52: 22.86 | IN52: 22.81 | IO52: 23.02 | IP52: 23.69 | IQ52: 23.2 | IR52: 23.87 | IS52: 23.8 | IT52: 23.99 | IU52: 24.49 | IV52: 23.98 | IW52: 24.45 | IX52: 24.09 | IY52: 24.42 | IZ52: 23.58 | JA52: 23.54 | JB52: 24.17 | JC52: 24.69 | JD52: 24.4 | JE52: 24.53 | JF52: 24.5 | JG52: 24.56 | JH52: 24.54 | JI52: 23.85 | JJ52: 24.27 | JK52: 24.33 | JL52: 23.61 | JM52: 24.18 | JN52: 24.45 | JO52: 24.11 | JP52: 23.98 | JQ52: 23.46 | JR52: 23.69 | JS52: 23.54 | JT52: 22.5 | JU52: 22.84 | JV52: 22.44 | JW52: 21.96 | JX52: 21.76 | JY52: 28.05 | JZ52: 28.84 | KA52: 28.52 | KB52: 29.22 | KC52: 28.77 | KD52: 28.56 | KE52: 27.51 | KF52: 27.37 | KG52: 27.77 | KH52: 27.89 | KI52: 28.37 | KJ52: 28.25 | KK52: 28.53 | KL52: 28.7 | KM52: 29.7 | KN52: 29.81 | KO52: 30.66 | KP52: 29.69 | KQ52: 31.01 | KR52: 31.13 | KS52: 31.23 | KT52: 30.28
A53: x | B53: 1 | C53: 3 | D53: =+D52+1 -> 42 | E53: Insmed | F53: INSM | G53: 98.6 | H53: =+G53*L53 -> 21371.792 | I53: =+[43]Main!$L$5-[43]Main!$L$6 -> 681.299 | J53: =+H53-I53 -> 20690.493 | K53: Q126 | L53: =+[43]Main!$L$3 -> 216.75245 | M53: 46217 | AL53: 1999 | AN53: United States | AO53: =BD53/FV53-1 -> -0.40599862 | AP53: =BD53/BX53-1 -> -0.033018427 | AQ53: =BD53/CA53-1 -> -0.050427115 | AR53: =BD53/KT53-1 -> 0.027225755 | BD53: 103.38 | BE53: 104.47 | BF53: 103.46 | BG53: 102.15 | BH53: 98.605 | BJ53: 95.8 | BK53: 98.45 | BL53: 95.52 | BM53: 97.46 | BN53: 97.85 | BO53: 96.72 | BP53: 91.88 | BQ53: 99.04 | BR53: 94.17 | BS53: 94.22 | BT53: 104.92 | BU53: 103.86 | BV53: 103.73 | BW53: 106.03 | BX53: 106.91 | BY53: 108.37 | BZ53: 106.4 | CA53: 108.87 | CB53: 106.24 | CC53: 109.53 | CD53: 107.91 | CE53: 107.41 | CF53: 107.15 | CG53: 109.14 | CH53: 115.62 | CI53: 117.99 | CJ53: 116 | CK53: 103.89 | CL53: 101.35 | CM53: 105 | CN53: 137.09 | CO53: 139.44 | CP53: 140.01 | CQ53: 133.26 | CR53: 136.33 | CS53: 135.03 | CT53: 134.94 | CU53: 135.98 | CV53: 135.17 | CW53: 143.83 | CX53: 144.48 | CY53: 140.98 | CZ53: 142.82 | DA53: 144.48 | DB53: 142.79 | DC53: 146.74 | DD53: 153.4 | DE53: 151.14 | DF53: 154.81 | DG53: 159.59 | DH53: 160.18 | DI53: 163.03 | DJ53: 163.81 | DK53: 162.43 | DL53: 164.86 | DM53: 163.52 | DN53: 153.32 | DO53: 145.3 | DP53: 147.6 | DQ53: 148.31 | DR53: 139.14 | DS53: 143.98 | DT53: 136 | DU53: 144 | DV53: 142.7 | DW53: 143.93 | DX53: 144.6 | DY53: 139.5 | DZ53: 139.52 | EA53: 139.4 | EB53: 143.85 | EC53: 143.13 | ED53: 140.13 | EE53: 143.57 | EF53: 149.88 | EG53: 147 | EH53: 146.32 | EI53: 149.33 | EJ53: 150 | EK53: 148.61 | EL53: 158.62 | EM53: 159.03 | EN53: 164.91 | EO53: 161 | EP53: 151.11 | EQ53: 150.52 | ER53: 148.75 | ES53: 146.17 | ET53: 148.43 | EU53: 148.55 | EV53: 149.54 | EW53: 149.86 | EX53: 151.03 | EY53: 152.44 | EZ53: 157.16 | FA53: 153.98 | FB53: 156.87 | FC53: 157.82 | FD53: 155.89 | FE53: 162.64 | FF53: 159.72 | FG53: 156.21 | FH53: 160.39 | FI53: 156.32 | FJ53: 163.51 | FK53: 161.42 | FL53: 159.27 | FM53: 163.46 | FN53: 163.72 | FO53: 167.72 | FP53: 175.97 | FQ53: 170.27 | FR53: 176 | FS53: 175.07 | FT53: 175.2 | FU53: 177.12 | FV53: 174.04 | FW53: 174.09 | FX53: 176.34 | FY53: 177.88 | FZ53: 177.42 | GA53: 176.77 | GB53: 175.76 | GC53: 174.84 | GD53: 166.55 | GE53: 198.46 | GF53: 200.67 | GG53: 196.92 | GH53: 197.01 | GI53: 195.24 | GJ53: 189.85 | GK53: 194.17 | GL53: 196.55 | GM53: 204 | GN53: 205.04 | GO53: 206.78 | GP53: 206.6 | GQ53: 211.41 | GR53: 207.77 | GS53: 204.51 | GT53: 209.02 | GU53: 206.93 | GV53: 198.76 | GW53: 199.64 | GX53: 203.56 | GY53: 201.62 | GZ53: 197.4 | HA53: 193.22 | HB53: 190.96 | HC53: 194.39 | HD53: 193.69 | HE53: 191.92 | HF53: 189.7 | HG53: 185.68 | HH53: 186.88 | HI53: 182.77 | HJ53: 186.23 | HK53: 189.6 | HL53: 194.22 | HM53: 166.95 | HN53: 165.29 | HO53: 164.02 | HP53: 159.66 | HQ53: 160.12 | HR53: 160.4 | HS53: 165.31 | HT53: 167.91 | HU53: 165.76 | HV53: 163.19 | HW53: 163.54 | HX53: 161.38 | HY53: 163.94 | HZ53: 162.33 | IA53: 164.4 | IB53: 161.81 | IC53: 162.32 | ID53: 158.28 | IE53: 157.16 | IF53: 152.8 | IG53: 147.28 | IH53: 144.01 | II53: 141.65 | IJ53: 137.03 | IK53: 135.59 | IL53: 141 | IM53: 145.38 | IN53: 145.03 | IO53: 144.76 | IP53: 145.86 | IQ53: 144.78 | IR53: 144.75 | IS53: 143.14 | IT53: 145.93 | IU53: 145.785 | IV53: 145.93 | IW53: 147.2 | IX53: 146.68 | IY53: 145.1 | IZ53: 142.53 | JA53: 143.5 | JB53: 145.3 | JC53: 136.1 | JD53: 134.97 | JE53: 134.53 | JF53: 132.17 | JG53: 128.32 | JH53: 131.88 | JI53: 132.6 | JJ53: 129.45 | JK53: 127.21 | JL53: 127.27 | JM53: 127.8 | JN53: 127.75 | JO53: 122.87 | JP53: 122 | JQ53: 112.89 | JR53: 109.55 | JS53: 109.3 | JT53: 111.26 | JU53: 111.61 | JV53: 111.24 | JW53: 108.69 | JX53: 107.28 | JY53: 105.18 | JZ53: 105 | KA53: 101.75 | KB53: 103.95 | KC53: 103.52 | KD53: 103.44 | KE53: 102.92 | KF53: 102.78 | KG53: 102.555 | KH53: 104.17 | KI53: 104.59 | KJ53: 102.87 | KK53: 101.89 | KL53: 98.18 | KM53: 96.66 | KN53: 96.47 | KO53: 96.14 | KP53: 96.95 | KQ53: 97.8 | KR53: 98.24 | KS53: 97.62 | KT53: 100.64
A54: x | D54: =+D53+1 -> 43 | E54: Incyte | F54: INCY | G54: 119.52 | H54: =+G54*L54 -> 24226.435 | I54: =+[44]Main!$K$5-[44]Main!$K$6 -> 4640.127 | J54: =H54-I54 -> 19586.308 | K54: Q226 | L54: =+[44]Main!$K$3 -> 202.69775 | M54: 46235 | AN54: United States
A55: x | D55: =+D54+1 -> 44 | E55: United | F55: UTHR | G55: 517.71 | H55: =+G55*L55 -> 21975.098 | I55: =[45]Main!$K$5-[45]Main!$K$6 -> 3471.1 | J55: =H55-I55 -> 18503.998 | K55: Q126 | L55: =+[45]Main!$K$3 -> 42.446733 | M55: 46235 | AN55: United States
A56: x | D56: =+D55+1 -> 45 | E56: Jazz | F56: JAZZ | G56: 250 | H56: =+G56*L56 -> 15475 | I56: =+[46]Main!$K$5-[46]Main!$K$6 -> -2500 | J56: =+H56-I56 -> 17975 | K56: Q126 | L56: =+[46]Main!$K$3 -> 61.9 | M56: 46230 | N56: =+[46]Model!$AU$31 -> 0 | O56: =+N56/G56-1 -> -1 | P56: =+[46]Model!$AU$28 -> 65.8225 | Q56: =+[46]Model!$AU$27 -> 36.378824 | R56: =+[46]Model!$AU$29 -> 0
A57: x | B57: -1 | C57: 3 | D57: =+D56+1 -> 46 | E57: Moderna | F57: MRNA | G57: 54.58 | H57: =+G57*L57 -> 21656.594 | I57: =+[47]Main!$K$5-[47]Main!$K$6 -> 5916 | J57: =H57-I57 -> 15740.594 | K57: Q126 | L57: =+[47]Main!$K$3 -> 396.78626 | M57: 46209 | AM57: Cambridge, MA
A58: x | B58: 1 | C58: 3 | D58: =+D57+1 -> 47 | E58: Grifols | F58: GRFS | G58: 7.87 | H58: =+G58*L58 -> 5411.0571 | I58: =([48]Main!$L$5-[48]Main!$L$6)*EUR -> -9653.0695 | J58: =H58-I58 -> 15064.127 | K58: Q424 | L58: =+[48]Main!$L$3 -> 687.55491 | M58: 45749
A59: x | B59: -1 | C59: 1 | D59: =+D58+1 -> 48 | E59: Exelixis | F59: EXEL | G59: 52.9 | H59: =+G59*L59 -> 14426.268 | I59: =+[49]Main!$M$5-[49]Main!$M$6 -> 1426.351 | J59: =+H59-I59 -> 12999.917 | K59: Q126 | L59: =+[49]Main!$M$3 -> 272.70828 | M59: 46220
A60: x | D60: =+D59+1 -> 49 | E60: Recordati | F60: REC IM | G60: 50.55 | H60: =G60*L60 -> 10428.423 | I60: =([50]Main!$M$5-[50]Main!$M$6)*EUR -> -1631.034 | J60: =+H60-I60 -> 12059.457 | K60: Q224 | L60: =[50]Main!$M$3 -> 206.29916 | M60: 45540 | AL60: 1926
A61: x | D61: =+D60+1 -> 50 | E61: Organon | F61: OGN | G61: 13.55 | H61: =+G61*L61 -> 3488.7656 | I61: =[51]Main!$L$5-[51]Main!$L$6 -> -8205 | J61: =+H61-I61 -> 11693.766 | K61: Q224 | L61: =+[51]Main!$L$3 -> 257.47348 | M61: 45562
A62: x | D62: =+D61+1 -> 51 | E62: Halozyme | F62: HALO | G62: 82.57 | H62: =+G62*L62 -> 9793.8754 | I62: =+[52]Main!$M$5-[52]Main!$M$6 -> -1826.017 | J62: =+H62-I62 -> 11619.892 | K62: Q126 | L62: =+[52]Main!$M$3 -> 118.613 | M62: 46235
A63: x | D63: =+D62+1 -> 52 | E63: Neurocrine | F63: NBIX | G63: 128.29 | H63: =+G63*L63 -> 13213.87 | I63: =+[53]Main!$L$5-[53]Main!$L$6 -> 1940 | J63: =H63-I63 -> 11273.87 | K63: Q424 | L63: =+[53]Main!$L$3 -> 103 | M63: 45707
A64: x | D64: =+D63+1 -> 53 | E64: Orion | F64: ORNBV FH | G64: 71.1 | H64: =+G64*L64*EUR -> 11138.436 | I64: =([54]Main!$L$5-[54]Main!$L$6)*EUR -> -123.432 | J64: =+H64-I64 -> 11261.868 | K64: Q224 | L64: =+[54]Main!$L$3 -> 141.134 | M64: 45566
A65: x | B65: 8 | C65: 8 | D65: =+D64+1 -> 54 | E65: Biomarin | F65: BMRN | G65: 60.02 | H65: =+G65*L65 -> 11763.92 | I65: =+[55]Main!$L$5-[55]Main!$L$6 -> 1183 | J65: =H65-I65 -> 10580.92 | K65: Q125 | L65: =+[55]Main!$L$3 -> 196 | M65: 45798 | AL65: 1997 | AM65: San Rafael, CA
A66: x | D66: =+D65+1 -> 55 | E66: Bridgebio | F66: BBIO | G66: 47.92 | H66: =+G66*L66 -> 8989.1211 | I66: =+[56]Main!$N$5-[56]Main!$N$6 -> -1130.399 | J66: =+H66-I66 -> 10119.52 | K66: Q224 | L66: =+[56]Main!$N$3 -> 187.586 | M66: 45579
A67: x | D67: =+D66+1 -> 56 | E67: Cytokinetics | F67: CYTK | G67: 80.13 | H67: =+G67*L67 -> 10584.051 | I67: =+[57]Main!$K$5-[57]Main!$K$6 -> 556.916 | J67: =+H67-I67 -> 10027.135 | K67: Q126 | L67: =+[57]Main!$K$3 -> 132.086 | M67: 46230
A68: x | D68: =+D67+1 -> 57 | E68: Arrowhead | F68: ARWR | G68: 86.25 | H68: =+G68*L68 -> 12283.466 | I68: =+[58]Main!$L$5-[58]Main!$L$6 -> 1102.06 | J68: =+H68-I68 -> 11181.406 | K68: Q126 | L68: =+[58]Main!$L$3 -> 142.417 | M68: 46209
A69: x | D69: =+D68+1 -> 58 | E69: Ipsen | F69: IPN | G69: 106.1 | H69: =+G69*L69*EUR -> 9870.9205 | I69: =([59]Main!$L$5-[59]Main!$L$6)*EUR -> 7.548 | J69: =+H69-I69 -> 9863.3725 | K69: Q224 | L69: =+[59]Main!$L$3 -> 83.814526 | M69: 45563
A70: x | D70: =+D69+1 -> 59 | E70: Summit | F70: SMMT | G70: 13.1 | H70: =+G70*L70 -> 10014.687 | I70: =+[60]Main!$K$5-[60]Main!$K$6 -> 738.6 | J70: =H70-I70 -> 9276.0865 | K70: Q224 | L70: =+[60]Main!$K$3 -> 764.47989 | M70: 45544 | AN70: United States
A71: x | D71: =+D70+1 -> 60 | E71: BioNTech | F71: BNTX | G71: 111.06 | H71: =+G71*L71 -> 26625.497 | I71: =+[61]Main!$K$5-[61]Main!$K$6 -> 18066.8 | J71: =+H71-I71 -> 8558.6969 | K71: Q324 | L71: =+[61]Main!$K$3 -> 239.73975 | M71: 45684 | AL71: 2008
A72: x | D72: =+D71+1 -> 61 | E72: Divi Labs | F72: DIVI IN | G72: 6489.5
A73: x | D73: =+D72+1 -> 62 | E73: Torrent | F73: TRP | G73: 3612
A74: x | D74: =+D73+1 -> 63 | E74: Swedish Orphan | F74: SOBI SS | G74: 269.8
A75: x | D75: =+D74+1 -> 64 | E75: Pharmaessentia | F75: 6446 TT | G75: 498.5
A76: x | D76: =+D75+1 -> 65 | E76: Shionogi | F76: 4507 JP | G76: 2547
A77: x | D77: =+D76+1 -> 66 | E77: Ascendis | F77: ASND | G77: 243 | H77: =G77*L77 -> 15157.574 | I77: =[62]Main!$K$5-[62]Main!$K$6 -> -323.664 | J77: =H77-I77 -> 15481.238 | K77: Q126 | L77: =[62]Main!$K$3 -> 62.376846 | M77: 46235 | AL77: 2007 | AM77: Copenhagen, Denmark
A78: x | D78: =+D77+1 -> 67 | E78: Alteogen | F78: 196170 KS | G78: 432000 | H78: 12895
A79: x | D79: =+D78+1 -> 68 | E79: Corcept | F79: CORT | G79: 70.53 | H79: 2150
A80: x | D80: =+D79+1 -> 69 | E80: Cipla | F80: CIPLA | G80: 1515
D81: =+D80+1 -> 70 | E81: Lantheus | F81: LNTH | G81: 72.03 | H81: =+G81*L81 -> 5001.0891 | I81: =+[63]Main!$K$5-[63]Main!$K$6 -> 310.253 | J81: =+H81-I81 -> 4690.8361 | K81: Q224 | L81: =+[63]Main!$K$3 -> 69.430642 | M81: 45586
A82: x | D82: =+D81+1 -> 71 | E82: Vaxcyte | F82: PCVX | G82: 58.26 | H82: =+G82*L82 -> 8412.609 | I82: =+[64]Main!$L$5-[64]Main!$L$6 -> 2741.195 | J82: =+H82-I82 -> 5671.414 | K82: Q126 | L82: =+[64]Main!$L$3 -> 144.39768 | M82: 46209 | AL82: 2013
A83: x | D83: =+D82+1 -> 72 | E83: Ionis | F83: IONS | G83: 43.08 | H83: =+G83*L83 -> 6298.7738 | I83: =+[65]Main!$L$5-[65]Main!$L$6 -> 309.908 | J83: =+H83-I83 -> 5988.8658 | K83: Q224 | L83: =+[65]Main!$L$3 -> 146.21109 | M83: 45539 | AL83: 1989
A84: x | D84: =+D83+1 -> 73 | E84: Kyowa Kirin | F84: 4151 JP | G84: 2565 | H84: =+G84*L84/JPY -> 8357.6258 | I84: =([66]Main!$L$5-[66]Main!$L$6)/JPY -> 2227.7022 | J84: =+H84-I84 -> 6129.9236 | K84: Q224 | L84: =+[66]Main!$L$3 -> 533.87797 | M84: 45567
D85: =+D84+1 -> 74 | E85: Perrigo | F85: PRGO | G85: 26.7 | H85: =+G85*L85 -> 3642.2917 | I85: =+[67]Main!$N$5-[67]Main!$N$6 -> -3514.8 | J85: =+H85-I85 -> 7157.0917 | K85: Q224 | L85: =+[67]Main!$N$3 -> 136.41542 | M85: 45566
A86: x | D86: =+D85+1 -> 75 | E86: Madrigal | F86: MDGL | G86: 328 | H86: =+G86*L86 -> 7121.7581 | I86: =+[68]Main!$M$5-[68]Main!$M$6 -> 946.187 | J86: =+H86-I86 -> 6175.5711 | K86: Q224 | L86: =+[68]Main!$M$3 -> 21.712677 | M86: 45783
A87: x | D87: =+D86+1 -> 76 | E87: Zydus Lifesciences | F87: ZYDUS | G87: 958.85
A88: x | D88: =+D87+1 -> 77 | E88: Abivax | F88: ABVX FP | G88: 111.1 | H88: =+G88*L88*EUR -> 7812.1186 | I88: =([69]Main!$M$5-[69]Main!$M$6) -> 47.805 | J88: =+H88-I88 -> 7764.3136 | K88: Q424 | L88: =+[69]Main!$M$3 -> 63.347837 | M88: 46244
A89: x | D89: =D88 -> 77 | E89: Abivax | F89: ABVX | G89: 128.31 | H89: =+G89*L89 -> 8128.161 | I89: =([69]Main!$M$5-[69]Main!$M$6) -> 47.805 | J89: =+H89-I89 -> 8080.356 | K89: Q424 | L89: =+[69]Main!$M$3 -> 63.347837 | M89: 46244
A90: x | D90: =+D89+1 -> 78 | E90: TG Therapeutics | F90: TGTX | G90: 27.93 | H90: =+G90*L90 -> 4324.2102 | I90: =+[70]Main!$J$5-[70]Main!$J$6 -> 115.662 | J90: =+H90-I90 -> 4208.5482 | K90: Q224 | L90: =+[70]Main!$J$3 -> 154.82314 | M90: 45580
A91: x | D91: =+D90+1 -> 79 | E91: Axsome | F91: AXSM | G91: 106 | H91: =+G91*L91 -> 5134.2274 | I91: =+[71]Main!$L$5-[71]Main!$L$6 -> 206.87 | J91: =+H91-I91 -> 4927.3574 | K91: Q224 | L91: =+[71]Main!$L$3 -> 48.436108 | M91: 45540
A92: x | D92: =+D91+1 -> 80 | E92: Lupin | F92: LPC | G92: 1882.2
A93: x | D93: =+D92+1 -> 81 | E93: Mankind | F93: MANKIND | G93: 2628.9
A94: x | D94: =+D93+1 -> 82 | E94: Laurus Labs | F94: LAURUS | G94: 861.2
A95: x | D95: =+D94+1 -> 83 | E95: Dr. Reddy's | F95: RDY | G95: 13.71
A96: x | D96: =+D95+1 -> 84 | E96: Apogee | F96: APGE | G96: 37.75 | H96: =+G96*L96 -> 2249.7644 | I96: =+[72]Main!$L$5-[72]Main!$L$6 -> 621.189 | J96: =+H96-I96 -> 1628.5754 | K96: Q424 | L96: =+[72]Main!$L$3 -> 59.596409 | M96: 45733
A97: x | D97: =+D96+1 -> 85 | E97: Praxis Precision Medicines | F97: PRAX | G97: 305 | H97: =+G97*L97 -> 8509.5 | I97: =+[73]Main!$L$5-[73]Main!$L$6 -> 1400 | J97: =+H97-I97 -> 7109.5 | K97: Q126 | L97: =+[73]Main!$L$3 -> 27.9 | M97: 46226
A98: x | D98: =+D97+1 -> 86 | E98: Aurobindo | F98: ARBP | G98: 1090.4
A99: x | D99: =+D98+1 -> 87 | E99: KRKA | F99: KRKG SV | G99: 198
D100: =+D99+1 -> 88 | E100: Alkermes | F100: ALKS | G100: 26.36 | H100: =+L100*G100 -> 4340.6572 | I100: =+[74]Main!$L$5-[74]Main!$L$6 -> 673.06 | J100: =+H100-I100 -> 3667.5972 | K100: Q224 | L100: =+[74]Main!$L$3 -> 164.66833 | M100: 45540
A101: x | D101: =+D100+1 -> 89 | E101: Krystal | F101: KRYS | G101: 132.99 | H101: =+G101*L101 -> 3824.8653 | I101: =+[75]Main!$K$5-[75]Main!$K$6 -> 694.212 | J101: =+H101-I101 -> 3130.6533 | K101: Q324 | L101: =+[75]Main!$K$3 -> 28.760548 | M101: 45631
...

Sheet China
C2: Name
A3: x | B3: =Acquisitions!A14+1 -> 1 | C3: Jiangsu Hengrui | D3: 600276 CH
A4: x | B4: 2 | C4: Hansoh | D4: 3692 HK | E4: 32.18 | F4: =+E4*J4/CNY -> 27483.039 | G4: =([217]Main!$J$5-[217]Main!$J$6)/CNY -> 4552.9835 | H4: =F4-G4 -> 22930.056 | I4: Q425 | J4: =+[217]Main!$J$3 -> 6055.1507 | K4: 46235 | AK4: 1995
A5: x | B5: 3 | C5: Innovent | D5: 1801 HK | E5: 92.9 | AK5: 2011
A6: x | B6: 4 | C6: Sichuan Biokin | D6: 688506 CH
A7: x | B7: 5 | C7: Zhejiang Nhu | D7: 002001 CH
A8: x | B8: 6 | C8: CSPC | D8: 1093 HK | E8: 9.66
A9: x | B9: 7 | C9: Zhangzhou Pientzehuang | D9: 600436 CH
A10: x | B10: 8 | C10: Sino Biopharm | D10: 1177 HK | E10: 5.03 | F10: =+E10*J10/HKD -> 11870.995 | G10: =([218]Main!$K$5-[218]Main!$K$6)/HKD -> 3986.4565 | H10: =F10-G10 -> 7884.538 | I10: Q224 | J10: =+[218]Main!$K$3 -> 18408.302 | K10: 45539
A11: x | B11: 9 | C11: Haisco | D11: 002653 CH
A12: x | B12: 10 | C12: Akeso | D12: 9926 HK | E12: 152.1
A13: x | B13: 11 | C13: Sichuan Kelun | D13: 6990 HK | E13: 404.2
A14: x | B14: 12 | C14: Sichuan Kelun | D14: 002422 CH | E14: 27.98 | F14: {=40290/CNY} -> 5682.6516
A15: x | B15: 13 | C15: Wuxi XDC | D15: 2268 HK | E15: 57.55
A16: x | B16: 14 | C16: Remegen | D16: 9995 HK
A17: x | B17: 15 | C17: Shanghai Fosun | D17: 600196 CH | E17: 23.23 | F17: =+E17*J17/CNY -> 8755.9693 | G17: =([219]Main!$K$6-[219]Main!$K$7)/CNY -> -2662.9055 | H17: =+F17-G17 -> 11418.875 | I17: Q423 | J17: =+[219]Main!$K$4 -> 2672.3987 | K17: 45542
A18: x | B18: 15 | C18: Shanghai Fosun | D18: 2196 HK | E18: 16.42 | F18: =+E18*J18/HKD -> 5625.7419 | G18: =([219]Main!$K$6-[219]Main!$K$7)/CNY -> -2662.9055 | H18: =+F18-G18 -> 8288.6474 | I18: Q423 | J18: =+[219]Main!$K$4 -> 2672.3987 | K18: 45542
A19: x | B19: 16 | C19: CSPC Innovation | D19: 300765 CH
A20: x | B20: 17 | C20: Shanghai Allist | D20: 688578 CH
A21: x | B21: 29 | C21: Changchun High Tech | D21: 000661 CH
A22: x | B22: 18 | C22: Huadong Medicine | D22: 000963 CH
A23: x | B23: 19 | C23: Biocytogen | D23: 688796 CH
A24: x | B24: 20 | C24: Sunshine Guojian | D24: 688336 CH
A25: x | B25: 21 | C25: China Resources Sanjiu | D25: 000999 CH
A26: x | B26: 22 | C26: Gan & Lee | D26: 603087 CH
A27: x | B27: 23 | C27: Shenzhen Salubris | D27: 002294 CH
A28: x | B28: 24 | C28: 3SBio | D28: 1530 HK
A29: x | B29: 36 | C29: Walvax Biotech | D29: 300142 CH
A30: x | B30: 26 | C30: Beijing Tongren | D30: 600085 CH
... A56: x | B56: 52 | C56: Hebei Changshan | D56: 300255 CH
C57: Chongqing Zhifei | D57: 300122 CH
C58: Shanghai Junshi | D58: 1877 HK | E58: 24.06 | F58: =+E58*J58/HKD -> 3040.4741 | G58: =([220]Main!$J$6-[220]Main!$J$7)/HKD -> 376.08885 | H58: =+F58-G58 -> 2664.3853 | I58: Q423 | J58: =+[220]Main!$J$4 -> 985.68987 | K58: 45543 | AL58: 2012
C59: Shanghai Junshi | D59: 688180 CH | E59: 37.66 | I59: =+I58 -> Q423 | K59: =+K58 -> 45543
C60: Yunnan Baiyao | D60: 000538 CH
C61: Shanghai Pharma | D61: 601607 CH

Sheet Drugs
A1: Main
B2: Brand | C2: Generic | D2: DBID | E2: Target | F2: MOA | G2: MW | H2: FDA | I2: Class | J2: AA
B3: Refludan | C3: lepirudin | D3: 1 | E3: thrombin | F3: peptide inhibitor | G3: 6979 | I3: rhProtein | J3: 65
B4: Erbitux | C4: cetuximab | D4: 2 | E4: EGFR | F4: mab | G4: 145781.6 | I4: mab
B5: Pulmozyme | C5: dornase alfa | D5: 3 | E5: extracellular DNA | F5: recombinant enzyme | G5: 29253.9 | I5: rhProtein | J5: 260
B6: Ontak | C6: denileukin difitox | D6: 4 | E6: IL-2 | F6: protein-toxin conjugate | G6: 58000 | I6: fusion protein | J6: =387+133 -> 520
B7: Enbrel | C7: etanercept | D7: 5 | E7: TNF-alpha | F7: soluble receptor | G7: 51235 | I7: rhProtein | J7: 934
B8: Angiomax | C8: bivalirudin | D8: 6 | E8: thrombin | F8: peptide inhibitor | G8: 2180 | I8: peptide | J8: 20
B9: Lupron | C9: leuprolide | D9: 7 | E9: GnRHR | F9: GnRH analog | G9: 1209 | I9: peptide | J9: 9
B10: Pegasys | C10: peginterferon alfa-2a | D10: 8 | E10: Type 1 IFNR | F10: IFNR agonist | G10: 60000 | I10: rhProtein | J10: 165
B11: Activase | C11: alteplase | D11: 9 | E11: fibrin, plasminogen | F11: recombinant enzyme | G11: 59000 | I11: rhProtein | J11: 527
B12: Geref | C12: sermorelin | D12: 10 | E12: GHRHR | F12: GRF mimetic | G12: 3358 | I12: peptide | J12: 29
B13: Wellferon | C13: interferon alfa-n1 | D13: 11 | E13: Type 1 IFNR | F13: IFNR agonist | G13: 19241 | I13: purified protein | J13: 166
B14: Aranesp | C14: darbepoetin alfa | D14: 12 | E14: EPOR | F14: EPOR agonist | G14: 18396 | I14: rhProtein
B15: Kinlytic | C15: urokinase | D15: 13 | E15: plasminogen | F15: protease | G15: 31126.5 | I15: rhProtein
B16: Zoladex | C16: goserelin | D16: 14 | E16: GnRHR | F16: LHRH analog | G16: 1269 | I16: small molecule | J16: N/A
C17: reteplase | D17: 15 | E17: plasminogen | F17: tPA analog | G17: 39589.6 | I17: rhProtein | J17: 355
B18: Procrit | C18: erythropoietin | D18: 16 | E18: EPOR | F18: EPOR agonist | G18: 18396 | I18: rhProtein | J18: 165
C19: salmon calcitonin | D19: 17 | E19: Calcitonin receptor | F19: calcitonin receptor agonist | G19: 3431.853 | I19: peptide | J19: 32
C20: interferon alfa-n3 | D20: 18 | E20: Type 1 IFNR | F20: IFNR agonist | I20: purified protein | J20: 166
B21: Neulasta | C21: pegfilgrastim | D21: 19 | E21: G-CSF Receptor | F21: G-CSF | G21: 39000 | I21: rhProtein
B22: Leukine | C22: sargramostim | D22: 20 | E22: GM-CSF-R-alpha | F22: GM-CSF | G22: 14434.5 | I22: rhProtein | J22: 127
C23: secretin | D23: 21 | E23: secretin receptor | F23: secretin receptor agonist | G23: 3039 | I23: peptide | J23: 27
C24: peginterferon alfa-2b | D24: 22 | E24: Type 1 IFNR | F24: IFNR agonist | G24: 31000 | I24: rhProtein
B25: Rylaze | C25: asparginase | D25: 23 | E25: L-asparagine | F25: recombinant enzyme
B26: Thyrogen | C26: thyrotropin alfa | D26: 24 | E26: TSH receptor | F26: TSH receptor agonist | G26: 22673 | I26: rhProtein
B27: Advate | C27: antihemophilic factor | D27: 25 | E27: Factor IXa | F27: Factor IXa complex component | G27: 264726 | I27: rhProtein | J27: 2332
B28: Kineret | C28: anakinra | D28: 26 | E28: IL-1 | F28: soluble receptor | G28: 17257.6 | I28: rhProtein | J28: 153
C29: gramicidin D | D29: 27 | G29: 1811.253 | I29: peptide | J29: 15
B30: Gammagard | C30: human immunoglobulin G | D30: 28 | G30: 142682.3 | I30: purified protein
C31: anistreplase | D31: 29 | E31: plasminogen | F31: recombinant enzyme | G31: 59042.3 | I31: rhProtein | J31: 527
B32: Humulin | C32: insulin human | D32: 30 | E32: Insulin Receptor | F32: insulin receptor agonist | G32: 5808 | I32: rhProtein | J32: 51
B33: TNKase | C33: tenecteplase | D33: 31 | E33: plasminogen | F33: tPA analog | G33: 58951.2 | I33: rhProtein | J33: 527
B34: Menopur | C34: menotropins | D34: 32 | E34: FSH receptor | F34: FSH agonist | G34: 23390.3 | I34: purified protein
B35: Actimmune | C35: interferon gamma-1b | D35: 33 | E35: Type 1 IFNR | F35: IFNR agonist | G35: 17145.6 | I35: rhProtein | J35: 140
C36: interferon alfa-2a | D36: 34 | E36: Type 1 IFNR | F36: IFNR agonist | G36: 19241.1 | I36: rhProtein | J36: 165
B37: Ddavp | C37: desmopressin | D37: 35 | E37: V1, V2, V3 receptors | F37: vasopressin receptor agonist | G37: 1069 | I37: peptide | J37: 8
B38: NovoSeven | C38: coagulation factor VIIa recombinant human | D38: 36 | E38: Factor IX, Factor X | F38: recombinant enzyme | G38: 45079
C39: interferon alfa-2a | D39: 37 | E39: Type 1 IFNR | F39: IFNR agonist | G39: 19241.1 | I39: rhProtein | J39: 165
B40: Neumega | C40: oprelvekin | D40: 38 | E40: IL-11 receptor | F40: IL-11 receptor agonist | G40: 19047 | I40: rhProtein | J40: 177
B41: Kepivance | C41: palifermin | D41: 39 | E41: KGF receptor | F41: KGF receptor agonist | G41: 16192.7 | I41: rhProtein | J41: 140
B42: Glucagen | C42: glucagon | D42: 40 | E42: Glucagon receptor | F42: Glucagon receptor agonist | G42: 3767.1 | I42: peptide | J42: 29
B43: Proleukin | C43: aldesleukin | D43: 41 | E43: IL-2 receptor | F43: IL-2 receptor agonist | G43: 15314.8 | I43: rhProtein | J43: 12
B44: Myobloc | C44: botulinum toxin type B | D44: 42 | G44: 150804
B45: Xolair | C45: omalizumab | D45: 43 | E45: IgE | F45: mab | G45: 149000 | I45: mab
C46: lutropin alfa | D46: 44 | E46: LH receptor | F46: LH receptor agonist | G46: 30000 | I46: rhProtein
C47: lyme disease vaccine | D47: 45 | G47: 27743
B48: Humalog | C48: insulin lispro | D48: 46 | E48: Insulin Receptor | F48: insulin receptor agonist | G48: 5808 | I48: rhProtein | J48: 51
B49: Lantus | C49: insulin glargine | D49: 47 | E49: Insulin Receptor | F49: insulin receptor agonist | G49: 6063 | I49: rhProtein
B50: Xiaflex | C50: collagenase clostridium histolyticum | D50: 48 | F50: recombinant enzyme
B51: Elitek | C51: rasburicase | D51: 49 | G51: 34109.5
C52: cetrorelix | D52: 50 | E52: GnRHR | F52: GnRH analog | G52: 1431 | I52: peptide | J52: 10
B53: Humira | C53: adalimumab | D53: 51 | E53: TNF-alpha | F53: mab | G53: 144190 | I53: mab
B54: Genotropin | C54: somatotropin | D54: 52 | E54: Growth Hormone receptor | F54: GH receptor agonist | G54: 22129 | I54: rhProtein
B55: Cerezyme | C55: imiglucerase | D55: 53 | F55: recombinant enzyme | G55: 55597.4 | I55: rhProtein | J55: 497
C56: abciximab | D56: 54 | F56: mab | G56: 145651 | I56: mab
B57: Cosentyx | C57: secukinumab | D57: 9029 | E57: IL-17A | F57: mab | I57: mab
C58: secretin | D58: 9532 | E58: secretin receptor | F58: secretin receptor agonist | G58: 3039 | I58: peptide | J58: 27

Sheet Industry Model
A1: Main
C2: Q123 | D2: Q223 | E2: Q323 | F2: Q423 | G2: Q124 | H2: Q224 | I2: Q324 | J2: Q424 | M2: 2023 | N2: 2024
B3: J&J | G3: 21382 | H3: 22453
B4: Merck | G4: 15775 | H4: 16112
B5: AbbVie | G5: 12310 | H5: 14462
B6: Lilly | G6: 8768 | H6: 11303
B7: Novo | G7: =65349/DKK -> 10078.967 | H7: =68060/DKK -> 10497.093
B8: Revenue | C8: =SUM(C3:C7) -> 0 | D8: =SUM(D3:D7) -> 0 | E8: =SUM(E3:E7) -> 0 | F8: =SUM(F3:F7) -> 0 | G8: =SUM(G3:G7) -> 68313.967 | H8: =SUM(H3:H7) -> 74827.093
B9: Lilly COGS | G9: 1534.4 | H9: 2031.1
B10: J&J COGS | G10: 5404 | H10: 6869
B11: AbbVie COGS | G11: 2108 | H11: 2135
B12: Merck COGS | G12: 2961 | H12: 3073
B13: Novo COGS | G13: =9916/DKK -> 1529.3737 | H13: =10274/DKK -> 1584.589
B14: COGS | G14: =SUM(G9:G13) -> 13536.774 | H14: =SUM(H9:H13) -> 15692.689
B15: Gross Margin | G15: =+G8-G14 -> 54777.194 | H15: =+H8-H14 -> 59134.404
B16: R&D | N16: =SUM(N17:N21) -> 53959.552
B17: Lilly R&D | N17: 9998
B18: AbbVie R&D | N18: 7795
B19: Novo R&D | N19: =45766/7.25 -> 6312.5517
B20: Pfizer R&D | M20: 11988 | N20: 11988
B21: Merck R&D | N21: 17866
B22: Novartis R&D | N22: 9214
B23: J&J R&D
B24: Sanofi R&D
B25: GSK R&D
B26: Amgen R&D
B31: Industry GM% | C31: =+C15/C8 -> #DIV/0! | D31: =+D15/D8 -> #DIV/0! | G31: =+G15/G8 -> 0.80184471 | H31: =+H15/H8 -> 0.79028065

Sheet Todo
B2: ORGO - look at new product for OA
B3: DCTH - assess revenue potential, look at dilutive instruments
B4: QXO - study Brad Jacobs
B5: SAVA - continue
B6: HIMS - listen to conference calls
B7: ABCL - deeper dive
B8: SQ - listen to conference calls, check if new product/pipeline disclosed
B9: JBL - listen to conference calls, model more years, do forecasts, look into customers, compare to macroeconomic data
B10: PCVX - deeper dive, conf calls, patents
B11: SYM - keep an eye on it
B12: CTAS
B13: ACET
... B23: TRVI - dig deeper

Sheet Launches
A1: Main | AR1: =AVERAGE(AR3:AR7,AR15:AR37,AR44:AR60) -> 297.49812
A2: # | B2: Drug | C2: Company | D2: Indication | E2: # in Class | F2: Launch | G2: MOA | H2: Lifetime | J2: Y1 | K2: Y2 | L2: Y3 | M2: Y4 | N2: Y5 | O2: Y6 | P2: Y7 | Q2: Y8 | R2: Y9 | S2: Y10 | T2: Y11 | U2: Y12 | V2: Y13 | W2: Y14 | X2: Y15 | Y2: Y16 | Z2: Y17 | AA2: Y18 | AB2: Y19 | AC2: Y20 | AD2: Y21 | AE2: Y22 | AF2: Y23 | AG2: Y24 | AH2: Y25 | AI2: Y26 | AJ2: Y27 | AK2: Y28 | AL2: Y29 | AM2: Y30 | AO2: Q1 | AP2: Q2 | AQ2: Q3 | AR2: Q4 | AS2: Q5 | AT2: Q6 | AU2: Q7 | AV2: Q8 | AW2: Q9 | AX2: Q10 | AY2: Q11 | AZ2: Q12 | BA2: Q13 | BB2: Q14 | BC2: Q15 | BD2: Q16 | BE2: Q17 | BF2: Q18 | BG2: Q19 | BH2: Q20 | BI2: Q21 | BJ2: Q22 | BK2: Q23 | BL2: Q24 | BM2: Q25 | BN2: Q26 | BO2: Q27 | BP2: Q28 | BQ2: Q29
A3: 1 | B3: Humira | C3: ABBV | D3: Autoimmune | E3: 3 | F3: Q103 | G3: TNF-alpha | H3: =SUM(AO3:GL3) -> 233470 | J3: =SUM(AO3:AR3) -> 280 | K3: =SUM(AS3:AV3) -> 852 | L3: =SUM(AW3:AZ3) -> 1400 | M3: =SUM(BA3:BD3) -> 2044 | N3: =SUM(BE3:BH3) -> 3063 | O3: =SUM(BI3:BL3) -> 4522 | P3: =SUM(BM3:BP3) -> 5488 | Q3: =SUM(BQ3:BT3) -> 6548 | R3: =SUM(BU3:BX3) -> 7932 | S3: =SUM(BY3:CB3) -> 9266 | T3: =SUM(CC3:CF3) -> 10659 | U3: =SUM(CG3:CJ3) -> 12543 | V3: =SUM(CK3:CN3) -> 14012 | W3: =SUM(CO3:CR3) -> 16078 | X3: =SUM(CS3:CV3) -> 18427 | Y3: =SUM(CW3:CZ3) -> 19936 | AO3: 30 | AP3: 60 | AQ3: 80 | AR3: 110 | AS3: 149 | AT3: 203 | AU3: 227 | AV3: 273 | AW3: 282 | AX3: 321 | AY3: 356 | AZ3: 441 | BA3: 392 | BB3: 491 | BC3: 541 | BD3: 620 | BE3: 571 | BF3: 735 | BG3: 803 | BH3: 954 | BI3: 878 | BJ3: 1089 | BK3: 1204 | BL3: 1351 | BM3: 1024 | BN3: 1311 | BO3: 1491 | BP3: 1662 | BQ3: 1397 | BR3: 1593 | BS3: 1679 | BT3: 1879 | BU3: 1646 | BV3: 1997 | BW3: 2111 | BX3: 2178 | BY3: 1934 | BZ3: 2326 | CA3: 2325 | CB3: 2681 | CC3: 2244 | CD3: 2606 | CE3: 2770 | CF3: 3039 | CG3: 2637 | CH3: 3288 | CI3: 3255 | CJ3: 3363 | CK3: 3111 | CL3: 3537 | CM3: 3647 | CN3: 3717 | CO3: 3577 | CP3: 4149 | CQ3: 4060 | CR3: 4292 | CS3: 4118 | CT3: 4716 | CU3: 4701 | CV3: 4892 | CW3: 4709 | CX3: 5185 | CY3: 5124 | CZ3: 4918 | DA3: 4446 | DB3: 4870 | DC3: 4936 | DD3: 4917 | DE3: 4703 | DF3: 4837 | DG3: 5140 | DH3: 5152 | DI3: 4867 | DJ3: 5068 | DK3: 5425 | DL3: 5334 | DM3: 4736 | DN3: 5363 | DO3: 5559 | DP3: 5579 | DQ3: 3541 | DR3: 4012 | DS3: 3547 | DT3: 3304 | DU3: 2270 | DV3: 2814
A4: 2 | B4: Lipitor | C4: PFE | D4: Cardiovascular | F4: Q197 | G4: HmG-CoA | H4: =SUM(AO4:GL4) -> 146735 | J4: =SUM(AO4:AR4) -> 865 | K4: =SUM(AS4:AV4) -> 2208 | L4: =SUM(AW4:AZ4) -> 3796 | M4: =SUM(BA4:BD4) -> 5031 | N4: =SUM(BE4:BH4) -> 6449 | O4: =SUM(BI4:BL4) -> 7972 | P4: =SUM(BM4:BP4) -> 9230 | Q4: =SUM(BQ4:BT4) -> 10862 | R4: =SUM(BU4:BX4) -> 12187 | S4: =SUM(BY4:CB4) -> 12886 | T4: =SUM(CC4:CF4) -> 12675 | U4: =SUM(CG4:CJ4) -> 12401 | V4: =SUM(CK4:CN4) -> 11434 | W4: =SUM(CO4:CR4) -> 10733 | X4: =SUM(CS4:CV4) -> 9577 | Y4: =SUM(CW4:CZ4) -> 3948 | AO4: 49 | AP4: 151 | AQ4: 257 | AR4: 408 | AS4: 375 | AT4: 536 | AU4: 578 | AV4: 719 | AW4: 767 | AX4: 900 | AY4: 995 | AZ4: 1134 | BA4: 1119 | BB4: 1262 | BC4: 1216 | BD4: 1434 | BE4: 1467 | BF4: 1439 | BG4: 1660 | BH4: 1883 | BI4: 1852 | BJ4: 1783 | BK4: 2020 | BL4: 2317 | BM4: 2099 | BN4: 2015 | BO4: 2468 | BP4: 2648 | BQ4: 2497 | BR4: 2363 | BS4: 2738 | BT4: 3264 | BU4: 3075 | BV4: 2858 | BW4: 2897 | BX4: 3357 | BY4: 3107 | BZ4: 3123 | CA4: 3321 | CB4: 3335 | CC4: 3358 | CD4: 2719 | CE4: 3170 | CF4: 3428 | CG4: 3137 | CH4: 2976 | CI4: 3142 | CJ4: 3146 | CK4: 2721 | CL4: 2685 | CM4: 2853 | CN4: 3175 | CO4: 2757 | CP4: 2813 | CQ4: 2534 | CR4: 2629 | CS4: 2385 | CT4: 2591 | CU4: 2602 | CV4: 1999 | CW4: 1395 | CX4: 1220 | CY4: 749 | CZ4: 584 | DA4: 626 | DB4: 545 | DC4: 533 | DD4: 611 | DE4: 457 | DF4: 543 | DG4: 490 | DH4: 572 | DI4: 441 | DJ4: 509 | DK4: 454 | DL4: 456 | DM4: 411 | DN4: 461 | DO4: 422 | DP4: 464 | DQ4: 404 | DR4: 445 | DS4: 491 | DT4: 574 | DU4: 511 | DV4: 521 | DW4: 507 | DX4: 524 | DY4: 622 | DZ4: 107 | EA4: 476 | EB4: 468 | EC4: 405 | ED4: 431
A5: 3 | B5: Keytruda | C5: MRK | D5: Oncology | E5: 2 | F5: Q314 | G5: PD-1 | H5: =SUM(AO5:GL5) -> 123247 | J5: =SUM(AO5:AR5) -> 247 | K5: =SUM(AS5:AV5) -> 936 | L5: =SUM(AW5:AZ5) -> 2304 | M5: =SUM(BA5:BD5) -> 5475 | N5: =SUM(BE5:BH5) -> 8943 | O5: =SUM(BI5:BL5) -> 12853 | P5: =SUM(BM5:BP5) -> 15783 | Q5: =SUM(BQ5:BT5) -> 19172 | R5: =SUM(BU5:BX5) -> 22942 | S5: =SUM(BY5:CB5) -> 27163 | T5: =SUM(CC5:CF5) -> 7429 | U5: =SUM(CG5:CJ5) -> 0 | V5: =SUM(CK5:CN5) -> 0 | W5: =SUM(CO5:CR5) -> 0 | AO5: 4 | AP5: 50 | AQ5: 83 | AR5: 110 | AS5: 159 | AT5: 214 | AU5: 249 | AV5: 314 | AW5: 356 | AX5: 483 | AY5: 584 | AZ5: 881 | BA5: 1047 | BB5: 1297 | BC5: 1464 | BD5: 1667 | BE5: 1889 | BF5: 2151 | BG5: 2269 | BH5: 2634 | BI5: 3070 | BJ5: 3111 | BK5: 3284 | BL5: 3388 | BM5: 3715 | BN5: 3993 | BO5: 3899 | BP5: 4176 | BQ5: 4534 | BR5: 4577 | BS5: 4809 | BT5: 5252 | BU5: 5426 | BV5: 5450 | BW5: 5795 | BX5: 6271 | BY5: 6338 | BZ5: 6608 | CA5: 6947 | CB5: 7270 | CC5: 7429
A6: 4 | B6: Eliquis WW | C6: PFE/BMY | D6: Cardiovascular | E6: 2 | F6: Q113 | G6: Factor X | H6: =+H82+H83 -> 118779 | J6: =+J82+J83 -> 412 | K6: =+K82+K83 -> 1562 | L6: =+L82+L83 -> 3260 | M6: =+M82+M83 -> 5005 | N6: =+N82+N83 -> 7395 | O6: =+O82+O83 -> 9872 | P6: =+P82+P83 -> 12149 | Q6: =+Q82+Q83 -> 13881 | ... W6: =+W82+W83 -> 0
A7: 5 | B7: Remicade US | C7: JNJ | D7: Autoimmune | E7: 1 | G7: TNF-alpha | H7: =SUM(AO7:GL7) -> 92404 | J7: =SUM(AO7:AR7) -> 115 | K7: =SUM(AS7:AV7) -> 370 | L7: =SUM(AW7:AZ7) -> 721 | M7: =SUM(BA7:BD7) -> 1297 | N7: =SUM(BE7:BH7) -> 1730 | O7: =SUM(BI7:BL7) -> 2146 | P7: =SUM(BM7:BP7) -> 2535 | Q7: =SUM(BQ7:BT7) -> 3014 | R7: =SUM(BU7:BX7) -> 3327 | S7: =SUM(BY7:CB7) -> 3748 | T7: =SUM(CC7:CF7) -> 4304 | U7: =SUM(CG7:CJ7) -> 4610 | V7: =SUM(CK7:CN7) -> 5492 | W7: =SUM(CO7:CR7) -> 6139 | AO7: 21 | AP7: 26 | AQ7: 27 | AR7: 41 | AS7: 49 | AT7: 91.2 | AU7: 90.8 | AV7: 139 | AW7: 131 | AX7: 171 | AY7: 209 | AZ7: 210 | BA7: 245 | BB7: 332 | BC7: 341 | BD7: 379 | BE7: 409 | BF7: 421 | BG7: 444 | BH7: 456 | BI7: 464 | BJ7: 539 | BK7: 545 | BL7: 598 | BM7: 577 | BN7: 642 | BO7: 624 | BP7: 692 | BQ7: 681 | BR7: 777 | BS7: 776 | BT7: 780 | BU7: 731 | BV7: 869 | BW7: 819 | BX7: 908 | BY7: 998 | BZ7: 886 | CA7: 978 | CB7: 886 | CC7: 1028 | CD7: 1102 | CE7: 1036 | CF7: 1138 | CG7: 1186 | CH7: 1130 | CI7: 1229 | CJ7: 1065 | CK7: 1285 | CL7: 1371 | CM7: 1408 | CN7: 1428 | CO7: 1521 | CP7: 1523 | CQ7: 1591 | CR7: 1504 | CS7: 1600 | CT7: 1672 | CU7: 1689 | CV7: 1712 | CW7: 1610 | CX7: 1804 | CY7: 1782 | CZ7: 1672 | DA7: 1600 | DB7: 1668 | DC7: 1613 | DD7: 1680 | DE7: 1779 | DF7: 1780 | DG7: 1783 | DH7: 1624 | DI7: 1672 | DJ7: 1530 | DK7: 1647 | DL7: 1466 | DM7: 1389 | DN7: 1320 | DO7: 1379 | DP7: 1238 | DQ7: 1102 | DR7: 1107 | DS7: 1136 | DT7: 1035 | DU7: 990 | DV7: 935 | DW7: 921 | DX7: 901 | DY7: 777 | DZ7: 888 | EA7: 761 | EB7: 764 | EC7: 663 | ED7: 647 | EE7: 558 | EF7: 475 | EG7: 487
A8: 6 | B8: Comirnaty | C8: PFE | D8: Vaccine | G8: mRNA vaccine | H8: =SUM(AO8:GL8) -> 86510 | J8: =SUM(AO8:AR8) -> 24431 | K8: =SUM(AS8:AV8) -> 38981 | L8: =SUM(AW8:AZ8) -> 17188 | M8: =SUM(BA8:BD8) -> 5910 | N8: =SUM(BE8:BH8) -> 0 | O8: =SUM(BI8:BL8) -> 0 | P8: =SUM(BM8:BP8) -> 0 | Q8: =SUM(BQ8:BT8) -> 0 | R8: =SUM(BU8:BX8) -> 0 | S8: =SUM(BY8:CB8) -> 0 | T8: =SUM(CC8:CF8) -> 0 | U8: =SUM(CG8:CJ8) -> 0 | V8: =SUM(CK8:CN8) -> 0 | W8: =SUM(CO8:CR8) -> 0 | AO8: 154 | AP8: 3462 | AQ8: 7838 | AR8: 12977 | AS8: 12504 | AT8: 13227 | AU8: 8848 | AV8: 4402 | AW8: 11329 | AX8: 3064 | AY8: 1488 | AZ8: 1307 | BA8: 5361 | BB8: 354 | BC8: 195
A9: 7 | B9: Prevnar | C9: PFE | D9: Vaccine | H9: =SUM(J9:BR9) -> 82695.365 | J9: 460.6 | K9: 798.2 | L9: 647.5 | M9: 945.6 | N9: 1053.6 | O9: 1508.3 | P9: 1961.3 | Q9: 2,439 | R9: 2,716 | S9: 1825.265 | T9: 3669 | U9: 4145 | V9: 4117 | W9: 3974 | X9: 4464 | Y9: 6247 | Z9: 5719 | AA9: 5601 | AB9: 5802 | AC9: 5847 | AD9: 5850 | AE9: 5274 | AF9: 6337 | AG9: 6449
A10: =+A9+1 -> 8 | B10: Januvia+Janumet | C10: MRK | D10: Diabetes | E10: 1 | G10: DPP-4 | H10: =SUM(AO10:GL10) -> 74776.5 | J10: =SUM(AO10:AR10) -> 589 | K10: =SUM(AS10:AV10) -> 1600.5 | L10: =SUM(AW10:AZ10) -> 2095 | M10: =SUM(BA10:BD10) -> 3327 | N10: =SUM(BE10:BH10) -> 4488 | O10: =SUM(BI10:BL10) -> 5589 | P10: =SUM(BM10:BP10) -> 5912 | Q10: =SUM(BQ10:BT10) -> 6073 | R10: =SUM(BU10:BX10) -> 6172 | S10: =SUM(BY10:CB10) -> 6087 | T10: =SUM(CC10:CF10) -> 5937 | U10: =SUM(CG10:CJ10) -> 5907 | V10: =SUM(CK10:CN10) -> 5483 | W10: =SUM(CO10:CR10) -> 5346 | AO10: =AO84+AO85 -> 66 | AP10: =AP84+AP85 -> 106 | AQ10: =AQ84+AQ85 -> 174 | AR10: =AR84+AR85 -> 243 | AS10: =AS84+AS85 -> 272 | AT10: =AT84+AT85 -> 373 | AU10: =AU84+AU85 -> 448.5 | AV10: =AV84+AV85 -> 507 | ... DD10: =DD84+DD85 -> 0
A11: 9 | B11: tirzepatide | C11: LLY | G11: GLP-1 | H11: =+H16+H38 -> 71616.8 | J11: =+J16+J38 -> 4244.8 | K11: =+K16+K38 -> 17590.6 | L11: =+L16+L38 -> 21996.4 | M11: =+M16+M38 -> 27785
A12: 10 | B12: Zyprexa | C12: LLY | D12: Psychiatry | G12: D2 | H12: =SUM(AO12:GL12) -> 63245.2 | J12: =SUM(AO12:AR12) -> 550.2 | K12: =SUM(AS12:AV12) -> 1278 | L12: =SUM(AW12:AZ12) -> 1726.1 | M12: =SUM(BA12:BD12) -> 2246.6 | N12: =SUM(BE12:BH12) -> 2882.4 | O12: =SUM(BI12:BL12) -> 3604.1 | P12: =SUM(BM12:BP12) -> 4128.1 | Q12: =SUM(BQ12:BT12) -> 4479.8 | R12: =SUM(BU12:BX12) -> 4255.6 | S12: =SUM(BY12:CB12) -> 4239.3 | T12: =SUM(CC12:CF12) -> 4643.6 | U12: =SUM(CG12:CJ12) -> 4823.3 | V12: =SUM(CK12:CN12) -> 4695.9 | W12: =SUM(CO12:CR12) -> 5057.1 | AO12: 87 | AP12: 105.4 | AQ12: 156 | AR12: 201.8 | AS12: 267 | AT12: 287 | AU12: 328 | AV12: 396 | AW12: 429 | AX12: 401.2 | AY12: 393 | AZ12: 502.9 | BA12: 592.9 | BB12: 458.1 | BC12: 550.7 | BD12: 644.9 | BE12: 696.3 | BF12: 637 | BG12: 736.6 | BH12: 812.5 | BI12: 903.9 | BJ12: 819.4 | BK12: 906.8 | BL12: 974 | BM12: 989.8 | BN12: 958.3 | BO12: 1050 | BP12: 1130 | BQ12: 1145.5 | BR12: 1098.3 | BS12: 1212.3 | BT12: 1023.7 | BU12: 1085.5 | BV12: 1038.2 | BW12: 1096.8 | BX12: 1035.1 | BY12: 1032.2 | BZ12: 1007.4 | CA12: 1115 | CB12: 1084.7 | CC12: 1156.5 | CD12: 1108 | CE12: 1213 | CF12: 1166.1 | CG12: 1273.9 | CH12: 1120.2 | CI12: 1239.7 | CJ12: 1189.5 | CK12: 1146.7 | CL12: 1123 | CM12: 1203.2 | CN12: 1223 | CO12: 1366.5 | CP12: 1215 | CQ12: 1262.9 | CR12: 1212.7 | CS12: 1335.8 | CT12: 1281.9 | CU12: 1408.3 | CV12: 1182.3 | CW12: 749.6 | CX12: 562.7 | CY12: 379.5 | CZ12: 374.5 | DA12: 384.8 | DB12: 284.8 | DC12: 283.2 | DD12: 278.7 | DE12: 348.2 | DF12: 283.1 | DG12: 243.8 | DH12: 257.4 | DI12: 253.1 | DJ12: 219.5 | DK12: 253.7 | DL12: 237.9 | DM12: 229.1 | DN12: 212.8 | DO12: 210.7 | DP12: 148.9 | DQ12: 153 | DR12: 147.5 | DS12: 140.8 | DT12: 140.6 | DU12: 152.2 | DV12: 122.6 | DW12: 128 | DX12: 109.9 | DY12: 110.8 | DZ12: 107.2 | EA12: 104.3 | EB12: 105.4 | EC12: 101.8 | ED12: 98.4 | EE12: 96.6 | EF12: 112.7 | EG12: 98.9 | EH12: 95.8 | EI12: 95.4 | EJ12: 101.7 | EK12: 137.4 | EL12: 93.1 | EM12: 87.3 | EN12: 81.4 | EO12: 75.1 | EP12: 106.5 | EQ12: 106.5 | ER12: 61.4 | ES12: 31.7 | ET12: 31.7 | EU12: 31.7 | EV12: 31.7 | EW12: 31.7
A13: =+A12+1 -> 11 | B13: Opdivo | C13: BMY | D13: Oncology | E13: 1 | G13: PD-1 | H13: =SUM(AO13:GL13) -> 59847 | J13: 942 | K13: 3774 | L13: 4948 | M13: 6735 | N13: 7204 | O13: 6992 | P13: 7523 | Q13: =SUM(BQ13:BT13) -> 7879 | R13: =SUM(BU13:BX13) -> 8610 | S13: =SUM(BY13:CB13) -> 9127 | T13: =SUM(CC13:CF13) -> 0 | U13: =SUM(CG13:CJ13) -> 0 | V13: =SUM(CK13:CN13) -> 0 | W13: =SUM(CO13:CR13) -> 0 | AO13: 1 | AP13: 5 | AQ13: 40 | AR13: 122 | AS13: 305 | AT13: 475 | AU13: 704 | AV13: 840 | AW13: 920 | AX13: 1310 | AY13: 1127 | AZ13: 1195 | BA13: 1265 | BB13: 1361 | BC13: 1511 | BD13: 1627 | BE13: 1793 | BF13: 1804 | BG13: 1801 | BH13: 1823 | BI13: 1817 | BJ13: 1763 | BK13: 1766 | BL13: 1653 | BM13: 1780 | BN13: 1793 | BO13: 1720 | BP13: 1910 | BQ13: 1905 | BR13: 1988 | BS13: 1923 | BT13: 2063 | BU13: 2047 | BV13: 2216 | BW13: 2202 | BX13: 2145 | BY13: 2275 | BZ13: 2387 | CA13: 2078 | CB13: 2387
A14: =+A15+1 -> 13 | B14: Humalog | C14: LLY | D14: Diabetes | H14: =SUM(AO14:GL14) -> 52236.767 | J14: =SUM(AO14:AR14) -> 11 | K14: =SUM(AS14:AV14) -> 80 | L14: =SUM(AW14:AZ14) -> 167.5 | M14: =SUM(BA14:BD14) -> 280.4 | N14: =SUM(BE14:BH14) -> 472.2 | O14: =SUM(BI14:BL14) -> 739.2 | P14: =SUM(BM14:BP14) -> 954.9 | Q14: =SUM(BQ14:BT14) -> 1069.6 | R14: =SUM(BU14:BX14) -> 1131.6 | S14: =SUM(BY14:CB14) -> 1241.7667 | T14: =SUM(CC14:CF14) -> 1372.1 | U14: =SUM(CG14:CJ14) -> 1622 | V14: =SUM(CK14:CN14) -> 1818.6 | W14: =SUM(CO14:CR14) -> 2042 | X14: =SUM(CS14:CV14) -> 2155.4 | Y14: =SUM(CW14:CZ14) -> 2458.9 | Z14: =SUM(DA14:DD14) -> 2453.1 | AA14: =SUM(DE14:DH14) -> 2700 | AB14: =SUM(DI14:DL14) -> 2773.5 | AC14: =SUM(DM14:DP14) -> 2811.9 | AD14: =SUM(DQ14:DT14) -> 2847.4 | AE14: =SUM(DU14:DX14) -> 3039.9 | AF14: =SUM(DY14:EB14) -> 2843.4 | AG14: =SUM(EC14:EF14) -> 2663.2 | AH14: =SUM(EG14:EJ14) -> 2599.7 | AI14: =SUM(EK14:EN14) -> 2293.7 | AJ14: =SUM(EO14:ER14) -> 1896.6 | AK14: =SUM(ES14:EV14) -> 1932.3 | AL14: =SUM(EW14:EZ14) -> 2194.8 | AM14: =SUM(FA14:FD14) -> 1570.1 | AO14: 1 | AP14: 2 | AQ14: 3 | AR14: 5 | AS14: 10 | AT14: 15 | AU14: 25 | AV14: 30 | AW14: 32 | AX14: 42.6 | AY14: 42.5 | AZ14: 50.4 | BA14: 58.7 | BB14: 72.9 | BC14: 72.1 | BD14: 76.7 | BE14: 90.6 | BF14: 110.8 | BG14: 125.2 | BH14: 145.6 | BI14: 164.3 | BJ14: 192.7 | BK14: 177.4 | BL14: 204.8 | BM14: 214.1 | BN14: 237.9 | BO14: 248.8 | BP14: 254.1 | BQ14: 240.2 | BR14: 276.9 | BS14: 267.2 | BT14: 285.3 | BU14: 264.6 | BV14: 284.6 | BW14: 286.2 | BX14: 296.2 | BY14: 306.66667 | BZ14: 309.1 | CA14: 305 | CB14: 321 | CC14: 322 | CD14: 352.2 | CE14: 339.5 | CF14: 358.4 | CG14: 362.5 | CH14: 414.2 | CI14: 407.4 | CJ14: 437.9 | CK14: 432.6 | CL14: 457.9 | CM14: 450.6 | CN14: 477.5 | CO14: 500.2 | CP14: 530.8 | CQ14: 506.4 | CR14: 504.6 | CS14: 494 | CT14: 549.1 | CU14: 525.4 | CV14: 586.9 | CW14: 593.2 | CX14: 662 | CY14: 590.3 | CZ14: 613.4 | DA14: 575.8 | DB14: 616 | DC14: 632.7 | DD14: 628.6 | DE14: 616 | DF14: 733.9 | DG14: 650 | DH14: 700.1 | DI14: 706.1 | DJ14: 729.1 | DK14: 684 | DL14: 654.3 | DM14: 705 | DN14: 798.7 | DO14: 606.3 | DP14: 701.9 | DQ14: 640.8 | DR14: 819.8 | DS14: 708.4 | DT14: 678.4 | DU14: 696.2 | DV14: 782.2 | DW14: 791.7 | DX14: 769.8 | DY14: 664.6 | DZ14: 770.4 | EA14: 730.8 | EB14: 677.6 | EC14: 648.9 | ED14: 763.4 | EE14: 695.8 | EF14: 555.1 | EG14: 656.9 | EH14: 718.1 | EI14: 617.1 | EJ14: 607.6 | EK14: 626.7 | EL14: 601.7 | EM14: 618.2 | EN14: 447.1 | EO14: 447 | EP14: 548.3 | EQ14: 460.9 | ER14: 440.4 | ES14: 395.4 | ET14: 366.6 | EU14: 538.7 | EV14: 631.6 | EW14: 534.6 | EX14: 619.9 | EY14: 537.2 | EZ14: 503.1 | FA14: 599.1 | FB14: 529 | FC14: 442
A15: =+A13+1 -> 12 | B15: Biktarvy | C15: GILD | D15: HIV | G15: integrase | H15: =SUM(AO15:GL15) -> 50224 | J15: =SUM(AO15:AR15) -> 1184 | K15: =SUM(AS15:AV15) -> 4738 | L15: =SUM(AW15:AZ15) -> 7259 | M15: =SUM(BA15:BD15) -> 8624 | N15: =SUM(BE15:BH15) -> 10391 | O15: =SUM(BI15:BL15) -> 11850 | P15: =SUM(BM15:BP15) -> 6178 | Q15: =SUM(BQ15:BT15) -> 0 | R15: =SUM(BU15:BX15) -> 0 | S15: =SUM(BY15:CB15) -> 0 | T15: =SUM(CC15:CF15) -> 0 | U15: =SUM(CG15:CJ15) -> 0 | V15: =SUM(CK15:CN15) -> 0 | W15: =SUM(CO15:CR15) -> 0 | AO15: 35 | AP15: 185 | AQ15: 386 | AR15: 578 | AS15: 793 | AT15: 1116 | AU15: 1259 | AV15: 1570 | AW15: 1693 | AX15: 1604 | AY15: 1891 | AZ15: 2071 | BA15: 1824 | BB15: 1994 | BC15: 2276 | BD15: 2530 | BE15: 2151 | BF15: 2556 | BG15: 2766 | BH15: 2918 | BI15: 2677 | BJ15: 2979 | BK15: 3085 | BL15: 3109 | BM15: 2946 | BN15: 3232
A16: =+A43+1 -> 39 | B16: Mounjaro | C16: LLY | F16: US launch 6/2022. First reported quarter Q222 | H16: =SUM(AO16:GL16) -> 48813.4 | J16: =SUM(AO16:AR16) -> 1051 | K16: =SUM(AS16:AV16) -> 6402 | L16: =SUM(AW16:AZ16) -> 13575.4 | M16: =SUM(BA16:BD16) -> 27785 | N16: =SUM(BE16:BH16) -> 0 | O16: =SUM(BI16:BL16) -> 0 | P16: =SUM(BM16:BP16) -> 0 | Q16: =SUM(BQ16:BT16) -> 0 | R16: =SUM(BU16:BX16) -> 0 | S16: =SUM(BY16:CB16) -> 0 | T16: =SUM(CC16:CF16) -> 0 | U16: =SUM(CG16:CJ16) -> 0 | AO16: 16 | AP16: 187.3 | AQ16: 279.2 | AR16: 568.5 | AS16: 980 | AT16: 1409 | AU16: 2206 | AV16: 1807 | AW16: 3090.8 | AX16: 3112.7 | AY16: 3530.1 | AZ16: 3841.8 | BA16: 5198.9 | BB16: 6515.1 | BC16: 7409 | BD16: 8662
A17: =+A22+1 -> 22 | B17: Trulicity | C17: LLY | D17: Diabetes | E17: 3 | H17: =SUM(AO17:GL17) -> 47102.6 | J17: =SUM(AO17:AR17) -> 146.5 | K17: =SUM(AS17:AV17) -> 701 | L17: =SUM(AW17:AZ17) -> 1717.8 | M17: =SUM(BA17:BD17) -> 2923.3 | N17: =SUM(BE17:BH17) -> 3844.4 | O17: =SUM(BI17:BL17) -> 4773.9 | P17: =SUM(BM17:BP17) -> 6090.5 | Q17: =SUM(BQ17:BT17) -> 7387.3 | R17: =SUM(BU17:BX17) -> 7399.9 | S17: =SUM(BY17:CB17) -> 5672.6 | T17: =SUM(CC17:CF17) -> 4489.4 | U17: =SUM(CG17:CJ17) -> 1956 | V17: =SUM(CK17:CN17) -> 0 | W17: =SUM(CO17:CR17) -> 0 | AO17: 10.2 | AP17: 18.3 | AQ17: 44.3 | AR17: 73.7 | AS17: 112.5 | AT17: 143.6 | AU17: 201.3 | AV17: 243.6 | AW17: 337 | AX17: 372.9 | AY17: 480.2 | AZ17: 527.7 | BA17: 649 | BB17: 678.3 | BC17: 779.8 | BD17: 816.2 | BE17: 924.7 | BF17: 879.7 | BG17: 1028.5 | BH17: 1011.5 | BI17: 1208.1 | BJ17: 1229.4 | BK17: 1229.8 | BL17: 1106.6 | BM17: 1502.4 | BN17: 1452.4 | BO17: 1535.6 | BP17: 1600.1 | BQ17: 1883.7 | BR17: 1741.3 | BS17: 1911.9 | BT17: 1850.4 | BU17: 1936.2 | BV17: 1977.1 | BW17: 1813 | BX17: 1673.6 | BY17: 1669.3 | BZ17: 1456.3 | CA17: 1245.6 | CB17: 1301.4 | CC17: 1250.2 | CD17: 1095.2 | CE17: 1092.2 | CF17: 1051.8 | CG17: 1037 | CH17: 919
A18: =+A14+1 -> 14 | B18: Darzalex | C18: JNJ | D18: Oncology | E18: 1 | H18: =SUM(AO18:GL18) -> 43368 | J18: =SUM(AO18:AR18) -> 383 | K18: =SUM(AS18:AV18) -> 1071 | L18: =SUM(AW18:AZ18) -> 1812 | M18: =SUM(BA18:BD18) -> 2752 | N18: =SUM(BE18:BH18) -> 3767 | O18: =SUM(BI18:BL18) -> 5631 | P18: =SUM(BM18:BP18) -> 7539 | Q18: =SUM(BQ18:BT18) -> 9277 | R18: =SUM(BU18:BX18) -> 11136 | S18: =SUM(BY18:CB18) -> 0 | T18: =SUM(CC18:CF18) -> 0 | U18: =SUM(CG18:CJ18) -> 0 | V18: =SUM(CK18:CN18) -> 0 | W18: =SUM(CO18:CR18) -> 0 | AO18: 20 | AP18: 101 | AQ18: 108 | AR18: =AVERAGE(AQ18,AS18) -> 154 | AS18: 200 | AT18: 255 | AU18: 299 | AV18: 317 | AW18: 371 | AX18: 432 | AY18: 511 | AZ18: 498 | BA18: 584 | BB18: 629 | BC18: 774 | BD18: 765 | BE18: 830 | BF18: 937 | BG18: 901 | BH18: 1099 | BI18: 1253 | BJ18: 1365 | BK18: 1433 | BL18: 1580 | BM18: 1645 | BN18: 1856 | BO18: 1986 | BP18: 2052 | BQ18: 2083 | BR18: 2264 | BS18: 2431 | BT18: 2499 | BU18: 2550 | BV18: 2692 | BW18: 2878 | BX18: 3016
A19: =+A18+1 -> 15 | B19: Gardasil | C19: MRK | D19: Vaccine, Oncology | E19: 1 | H19: =SUM(AO19:GL19) -> 41658 | J19: =SUM(AO19:AR19) -> 600 | K19: =SUM(AS19:AV19) -> 1616 | L19: =SUM(AW19:AZ19) -> 1400 | M19: =SUM(BA19:BD19) -> 1089 | N19: =SUM(BE19:BH19) -> 970 | O19: =SUM(BI19:BL19) -> 1280 | P19: =SUM(BM19:BP19) -> 1737 | Q19: =SUM(BQ19:BT19) -> 1825 | R19: =SUM(BU19:BX19) -> 1714 | S19: =SUM(BY19:CB19) -> 1927 | T19: =SUM(CC19:CF19) -> 2327 | U19: =SUM(CG19:CJ19) -> 2437 | V19: =SUM(CK19:CN19) -> 3329 | W19: =SUM(CO19:CR19) -> 3996 | X19: =SUM(CS19:CV19) -> 3758 | Y19: =SUM(CW19:CZ19) -> 6215 | Z19: =SUM(DA19:DD19) -> 5438 | AA19: =SUM(DE19:DH19) -> 0 | AB19: =SUM(DI19:DL19) -> 0 | AC19: =SUM(DM19:DP19) -> 0 | AO19: 10 | AP19: 70 | AQ19: 155 | AR19: 365 | AS19: 358 | AT19: 418 | AU19: 450 | AV19: 390 | AW19: 326 | AX19: 401 | AY19: 411 | AZ19: 262 | BA19: 268 | BB19: 311 | BC19: 277 | BD19: 233 | BE19: 219 | BF19: 316 | BG19: 221 | BH19: 214 | BI19: 277 | BJ19: 445 | BK19: 274 | BL19: 284 | BM19: 324 | BN19: 581 | BO19: 442 | BP19: 390 | BQ19: 383 | BR19: 665 | BS19: 394 | BT19: 383 | BU19: 409 | BV19: 590 | BW19: 356 | BX19: 359 | BY19: 427 | BZ19: 625 | CA19: 497 | CB19: 378 | CC19: 393 | CD19: 860 | CE19: 542 | CF19: 532 | CG19: 469 | CH19: 675 | CI19: 633 | CJ19: 660 | CK19: 608 | CL19: 1048 | CM19: 835 | CN19: 838 | CO19: 886 | CP19: 1320 | CQ19: 693 | CR19: 1097 | CS19: 656 | CT19: 1187 | CU19: 998 | CV19: 917 | CW19: 1234 | CX19: 1993 | CY19: 1528 | CZ19: 1460 | DA19: 1674 | DB19: 2294 | DC19: 1470
A20: =+A19+1 -> 16 | B20: Ibrance | C20: PFE | D20: Oncology | E20: 1 | H20: =SUM(AO20:GL20) -> 37946 | J20: =SUM(AO20:AR20) -> 723 | K20: =SUM(AS20:AV20) -> 2136 | L20: =SUM(AW20:AZ20) -> 3126 | M20: =SUM(BA20:BD20) -> 4118 | N20: =SUM(BE20:BH20) -> 4960 | O20: =SUM(BI20:BL20) -> 5390 | P20: =SUM(BM20:BP20) -> 5437 | Q20: =SUM(BQ20:BT20) -> 5119 | R20: =SUM(BU20:BX20) -> 4753 | S20: =SUM(BY20:CB20) -> 2184 | T20: =SUM(CC20:CF20) -> 0 | U20: =SUM(CG20:CJ20) -> 0 | V20: =SUM(CK20:CN20) -> 0 | W20: =SUM(CO20:CR20) -> 0 | AO20: 38 | AP20: 140 | AQ20: 230 | AR20: 315 | AS20: 429 | AT20: 514 | AU20: 550 | AV20: 643 | AW20: 679 | AX20: 853 | AY20: 878 | AZ20: 716 | BA20: 933 | BB20: 1027 | BC20: 1025 | BD20: 1133 | BE20: 1133 | BF20: 1261 | BG20: 1283 | BH20: 1283 | BI20: 1248 | BJ20: 1349 | BK20: 1357 | BL20: 1436 | BM20: 1254 | BN20: 1404 | BO20: 1381 | BP20: 1398 | BQ20: 1237 | BR20: 1320 | BS20: 1283 | BT20: 1279 | BU20: 1144 | BV20: 1247 | BW20: 1244 | BX20: 1118 | BY20: 1054 | BZ20: 1130
A21: =+A69+1 -> 59 | B21: Humulin | C21: LLY | D21: Diabetes | G21: Insulin | H21: =SUM(AO21:GL21) -> 33688.7 | J21: =SUM(AO21:AR21) -> 794 | K21: =SUM(AS21:AV21) -> 884 | L21: =SUM(AW21:AZ21) -> 936 | M21: =SUM(BA21:BD21) -> 697 | N21: =SUM(BE21:BH21) -> 1090 | O21: =SUM(BI21:BL21) -> 1110 | P21: =SUM(BM21:BP21) -> 1060 | Q21: =SUM(BQ21:BT21) -> 1000 | R21: =SUM(BU21:BX21) -> 1060 | S21: =SUM(BY21:CB21) -> 997.6 | T21: =SUM(CC21:CF21) -> 1004.8 | U21: =SUM(CG21:CJ21) -> 926 | V21: =SUM(CK21:CN21) -> 985.3 | W21: =SUM(CO21:CR21) -> 1063.1 | X21: =SUM(CS21:CV21) -> 1022.1 | Y21: =SUM(CW21:CZ21) -> 1088.9 | Z21: =SUM(DA21:DD21) -> 1248.7 | AA21: =SUM(DE21:DH21) -> 1239.1 | AB21: =SUM(DI21:DL21) -> 1315.9 | AC21: =SUM(DM21:DP21) -> 1400.1 | AD21: =SUM(DQ21:DT21) -> 1307.4 | AE21: =SUM(DU21:DX21) -> 1366 | AF21: =SUM(DY21:EB21) -> 1335.4 | AG21: =SUM(EC21:EF21) -> 1331.4 | AH21: =SUM(EG21:EJ21) -> 1290.1 | AI21: =SUM(EK21:EN21) -> 1259.6 | AJ21: =SUM(EO21:ER21) -> 1222.5 | AK21: =SUM(ES21:EV21) -> 1019.4 | AL21: =SUM(EW21:EZ21) -> 852.1 | AM21: =SUM(FA21:FD21) -> 917.2 | AO21: 170 | AP21: 190 | AQ21: 210 | AR21: =794-AQ21-AP21-AO21 -> 224 | AS21: 207 | AT21: 212 | AU21: 225.6 | AV21: =884-AU21-AT21-AS21 -> 239.4 | AW21: 209.8 | AX21: 219.1 | AY21: 226.4 | AZ21: =936-AY21-AX21-AW21 -> 280.7 | BA21: 195 | BB21: =291-BB68-30 -> 79 | BC21: =288-BC68-30 -> 258 | BD21: =1150-BC21-BB21-BA21-SUM(BA68:BD68)-120 -> 165 | BE21: 202.9 | BF21: 278.3 | BG21: 292.3 | BH21: =1090-BG21-BF21-BE21 -> 316.5 | BI21: 273.7 | BJ21: 265 | BK21: 282.6 | BL21: =1110-BK21-BJ21-BI21 -> 288.7 | BM21: 273.5 | BN21: 264.7 | BO21: 254.7 | BP21: =1060-BO21-BN21-BM21 -> 267.1 | BQ21: 234.5 | BR21: 257.6 | BS21: 257.4 | BT21: =1000-BS21-BR21-BQ21 -> 250.5 | BU21: 241 | BV21: 255.5 | BW21: 264.5 | BX21: =1060-BW21-BV21-BU21 -> 299 | BY21: 249.4 | BZ21: 259.3 | CA21: 243.7 | CB21: 245.2 | CC21: 256.9 | CD21: 249.8 | CE21: 250.9 | CF21: 247.2 | CG21: 219 | CH21: 220 | CI21: 230 | CJ21: 257 | CK21: 225.8 | CL21: 242.8 | CM21: 243.3 | CN21: 273.4 | CO21: 257.7 | CP21: 271.4 | CQ21: 271.6 | CR21: 262.4 | CS21: 240.6 | CT21: 248.1 | CU21: 260.4 | CV21: 273 | CW21: 257.8 | CX21: 265.2 | CY21: 278 | CZ21: 287.9 | DA21: 289.8 | DB21: 311.8 | DC21: 301.5 | DD21: 345.6 | DE21: 307.7 | DF21: 303 | DG21: 285.4 | DH21: 343 | DI21: 311.9 | DJ21: 327.5 | DK21: 307 | DL21: 369.5 | DM21: 316.2 | DN21: 352.4 | DO21: 335.9 | DP21: 395.6 | DQ21: 315.7 | DR21: 316.4 | DS21: 316.7 | DT21: 358.6 | DU21: 356.4 | DV21: 332.3 | DW21: 322 | DX21: 355.3 | DY21: 314.5 | DZ21: 357.8 | EA21: 300.5 | EB21: 362.6 | EC21: 325.9 | ED21: 346 | EE21: 322.1 | EF21: 337.4 | EG21: 297.7 | EH21: 322.6 | EI21: 321.8 | EJ21: 348 | EK21: 315.7 | EL21: 313.6 | EM21: 305.9 | EN21: 324.4 | EO21: =219+102.7 -> 321.7 | EP21: 315.3 | EQ21: 286.7 | ER21: 298.8 | ES21: =190.4+82.8 -> 273.2 | ET21: 274 | EU21: 238.2 | EV21: 234 | EW21: 252 | EX21: 205.3 | EY21: 206.7 | EZ21: =852.1-EY21-EX21-EW21 -> 188.1 | FA21: 206.2 | FB21: 223.6 | FC21: 207.1 | FD21: 280.3 | FE21: 173.2 | FF21: 175.2 | FG21: 176.6 | FH21: 180 | FI21: 160
A22: =+A23+1 -> 21 | B22: Harvony | C22: GILD | D22: HCV | G22: nucleotide | H22: =SUM(AO22:GL22) -> 31975 | J22: =SUM(AO22:AR22) -> 9314 | K22: =SUM(AS22:AV22) -> 12258 | L22: =SUM(AW22:AZ22) -> 6253 | M22: =SUM(BA22:BD22) -> 2296 | N22: =SUM(BE22:BH22) -> 961 | O22: =SUM(BI22:BL22) -> 404 | P22: =SUM(BM22:BP22) -> 211 | Q22: =SUM(BQ22:BT22) -> 152 | R22: =SUM(BU22:BX22) -> 86 | S22: =SUM(BY22:CB22) -> 40 | T22: =SUM(CC22:CF22) -> 0 | U22: =SUM(CG22:CJ22) -> 0 | V22: =SUM(CK22:CN22) -> 0 | W22: =SUM(CO22:CR22) -> 0 | AO22: 20 | AP22: 2107 | AQ22: 3579 | AR22: 3608 | AS22: 3332 | AT22: 3345 | AU22: 3017 | AV22: 2564 | AW22: 1860 | AX22: 1640 | AY22: 1371 | AZ22: 1382 | BA22: 973 | BB22: 644 | BC22: 348 | BD22: 331 | BE22: 311 | BF22: 232 | BG22: 225 | BH22: 193 | BI22: 124 | BJ22: 101 | BK22: 112 | BL22: 67 | BM22: 84 | BN22: 9 | BO22: 56 | BP22: 62 | BQ22: 45 | BR22: 49 | BS22: 35 | BT22: 23 | BU22: 25 | BV22: 31 | BW22: 15 | BX22: 15 | BY22: 23 | BZ22: 17
A23: =+A26+1 -> 20 | B23: Ozempic | C23: NOVO | D23: Diabetes | G23: GLP-1 | H23: =SUM(AO23:GL23) -> 32529.592 | J23: =SUM(AO23:AR23) -> 769.97085 | K23: =SUM(AS23:AV23) -> 2489.5044 | L23: =SUM(AW23:AZ23) -> 3748.8338 | M23: =SUM(BA23:BD23) -> 6704.3732 | N23: =SUM(BE23:BH23) -> 10948.542 | O23: =SUM(BI23:BL23) -> 7868.3673 | P23: =SUM(BM23:BP23) -> 0 | Q23: =SUM(BQ23:BT23) -> 0 | R23: =SUM(BU23:BX23) -> 0 | S23: =SUM(BY23:CB23) -> 0 | T23: =SUM(CC23:CF23) -> 0 | U23: =SUM(CG23:CJ23) -> 0 | V23: =SUM(CK23:CN23) -> 0 | W23: =SUM(CO23:CR23) -> 0 | AO23: =540/$C$81 -> 78.717201 | AP23: =992/$C$81 -> 144.60641 | AQ23: =1425/$C$81 -> 207.72595 | AR23: =2325/$C$81 -> 338.92128 | AS23: =3122/$C$81 -> 455.10204 | AT23: =4365/$C$81 -> 636.29738 | AU23: =4755/$C$81 -> 693.14869 | AV23: =4836/$C$81 -> 704.95627 | AW23: =5432/$C$81 -> 791.83673 | AX23: =6188/$C$81 -> 902.04082 | AY23: =6662/$C$81 -> 971.13703 | AZ23: =7435/$C$81 -> 1083.8192 | BA23: =8892/$C$81 -> 1296.2099 | BB23: =10716/$C$81 -> 1562.0991 | BC23: =12035/$C$81 -> 1754.3732 | BD23: =14349/$C$81 -> 2091.691 | BE23: =16390/$C$81 -> 2389.2128 | BF23: =16976/$C$81 -> 2474.6356 | BG23: =19640/$C$81 -> 2862.9738 | BH23: =22101/C81 -> 3221.7201 | BI23: =23912/C81 -> 3485.7143 | BJ23: =30065/C81 -> 4382.6531
A24: =+A32+1 -> 30 | B24: Sovaldi | C24: GILD | D24: HCV | H24: =SUM(AO24:GL24) -> 20663.11 | J24: =SUM(AO24:AR24) -> 8690.11 | K24: =SUM(AS24:AV24) -> 5461 | L24: =SUM(AW24:AZ24) -> 5007 | M24: =SUM(BA24:BD24) -> 1388 | N24: =SUM(BE24:BH24) -> 117 | O24: =SUM(BI24:BL24) -> 0 | P24: =SUM(BM24:BP24) -> 0 | Q24: =SUM(BQ24:BT24) -> 0 | R24: =SUM(BU24:BX24) -> 0 | S24: =SUM(BY24:CB24) -> 0 | T24: =SUM(CC24:CF24) -> 0 | U24: =SUM(CG24:CJ24) -> 0 | V24: =SUM(CK24:CN24) -> 0 | W24: =SUM(CO24:CR24) -> 0 | AO24: 139.435 | AP24: 2274.349 | AQ24: 3480.326 | AR24: 2796 | AS24: 1732 | AT24: 972 | AU24: 1291 | AV24: 1466 | AW24: 1547 | AX24: 1277 | AY24: 1358 | AZ24: 825 | BA24: 541 | BB24: 313 | BC24: 315 | BD24: 219 | BE24: 117
A25: =+A30+1 -> 27 | B25: Skyrizi | C25: ABBV | D25: Autoimmune | H25: =SUM(AO25:GL25) -> 37378 | J25: =SUM(AO25:AR25) -> 655 | K25: =SUM(AS25:AV25) -> 1864 | L25: =SUM(AW25:AZ25) -> 3305 | M25: =SUM(BA25:BD25) -> 5585 | N25: =SUM(BE25:BH25) -> 8411 | O25: =SUM(BI25:BL25) -> 13135 | P25: =SUM(BM25:BP25) -> 4423 | Q25: =SUM(BQ25:BT25) -> 0 | R25: =SUM(BU25:BX25) -> 0 | S25: =SUM(BY25:CB25) -> 0 | T25: =SUM(CC25:CF25) -> 0 | U25: =SUM(CG25:CJ25) -> 0 | V25: =SUM(CK25:CN25) -> 0 | W25: =SUM(CO25:CR25) -> 0 | AO25: 48 | AP25: 91 | AQ25: 216 | AR25: 300 | AS25: 330 | AT25: 435 | AU25: 525 | AV25: 574 | AW25: 674 | AX25: 796 | AY25: 895 | AZ25: 940 | BA25: 1252 | BB25: 1397 | BC25: 1576 | BD25: 1360 | BE25: 1883 | BF25: 2126 | BG25: 2394 | BH25: 2008 | BI25: 2727 | BJ25: 3205 | BK25: 3778 | BL25: 3425 | BM25: 4423
A26: =+A35+1 -> 19 | B26: Cymbalta | C26: LLY | D26: Psychiatry | E26: 2 | G26: SNRI | H26: =SUM(AO26:GL26) -> 35447.6 | J26: =SUM(AO26:AR26) -> 362 | K26: =SUM(AS26:AV26) -> 954.6 | L26: =SUM(AW26:AZ26) -> 1734.4 | M26: =SUM(BA26:BD26) -> 2401 | N26: =SUM(BE26:BH26) -> 2891.3 | O26: =SUM(BI26:BL26) -> 3291.9 | P26: =SUM(BM26:BP26) -> 3722.1 | Q26: =SUM(BQ26:BT26) -> 4587.3 | R26: =SUM(BU26:BX26) -> 5481.6 | S26: =SUM(BY26:CB26) -> 3138.5 | T26: =SUM(CC26:CF26) -> 1296.4 | U26: =SUM(CG26:CJ26) -> 901.7 | V26: =SUM(CK26:CN26) -> 876.5 | W26: =SUM(CO26:CR26) -> 727.5 | X26: =SUM(CS26:CV26) -> 707.8 | Y26: =SUM(CW26:CZ26) -> 764.4 | Z26: =SUM(DA26:DD26) -> 729.6 | AA26: =SUM(DE26:DH26) -> 385.9 | AB26: =SUM(DI26:DL26) -> 186.9 | AC26: =SUM(DM26:DP26) -> 104.2 | AD26: =SUM(DQ26:DT26) -> 150.2 | AE26: =SUM(DU26:DX26) -> 51.8 | AF26: =SUM(DY26:EB26) -> 0 | AG26: =SUM(EC26:EF26) -> 0 | AH26: =SUM(EG26:EJ26) -> 0 | AO26: 32.5 | AP26: 61.3 | AQ26: 106.8 | AR26: 161.4 | AS26: 182.8 | AT26: 228.8 | AU26: 233 | AV26: 310 | AW26: 349 | AX26: 424.1 | AY26: 441.8 | AZ26: 519.5 | BA26: 513.2 | BB26: 628.3 | BC26: 605.1 | BD26: 654.4 | BE26: 716.4 | BF26: 721.2 | BG26: 709.3 | BH26: 744.4 | BI26: 790.2 | BJ26: 830.8 | BK26: 803.2 | BL26: 867.7 | BM26: 825.3 | BN26: 984.6 | BO26: 908.8 | BP26: 1003.4 | BQ26: 1068.6 | BR26: 1180.7 | BS26: 1114.9 | BT26: 1223.1 | BU26: 1235.8 | BV26: 1420.4 | BW26: 1328.2 | BX26: 1497.2 | BY26: 1375.8 | BZ26: 883.2 | CA26: 478.2 | CB26: 401.3 | CC26: 368 | CD26: 367.3 | CE26: 287 | CF26: 274.1 | CG26: 242.9 | CH26: 223.6 | CI26: 198.7 | CJ26: 236.5 | CK26: 313.5 | CL26: 181.8 | CM26: 174.6 | CN26: 206.6 | CO26: 183.2 | CP26: 192.8 | CQ26: 169.6 | CR26: 181.9 | CS26: 172 | CT26: 184.5 | CU26: 164.1 | CV26: 187.2 | CW26: 178.6 | CX26: =725.4-CW26-CV26-CU26 -> 195.5 | CY26: 210.4 | CZ26: 179.9 | DA26: 186.6 | DB26: =42.1+725.6-DA26-CZ26-CY26 -> 190.8 | DC26: 176.6 | DD26: 175.6 | DE26: 132 | DF26: =581.5-DE26-DD26-DC26 -> 97.3 | DG26: 81.1 | DH26: 75.5 | DI26: 62.7 | DJ26: =283.3-DI26-DH26-DG26 -> 64 | DK26: 60.2 | DO26: 54.4 | DP26: 49.8 | DQ26: 44.7 | DR26: 50.2 | DS26: 31.2 | DT26: 24.1 | DU26: 4.1 | DV26: 3 | DW26: 44.7
A27: =+A49+1 -> 36 | B27: Vyvgart | C27: ARGX | D27: Autoimmune | E27: 1 | H27: =SUM(AO27:GL27) -> 3777.482 | J27: =SUM(AO27:AR27) -> 400.721 | K27: =SUM(AS27:AV27) -> 1190.761 | L27: =SUM(AW27:AZ27) -> 2186 | M27: =SUM(BA27:BD27) -> 0 | N27: =SUM(BE27:BH27) -> 0 | O27: =SUM(BI27:BL27) -> 0 | P27: =SUM(BM27:BP27) -> 0 | Q27: =SUM(BQ27:BT27) -> 0 | R27: =SUM(BU27:BX27) -> 0 | S27: =SUM(BY27:CB27) -> 0 | T27: =SUM(CC27:CF27) -> 0 | U27: =SUM(CG27:CJ27) -> 0 | V27: =SUM(CK27:CN27) -> 0 | W27: =SUM(CO27:CR27) -> 0 | AO27: 21.163 | AP27: 74.833 | AQ27: 131.329 | AR27: 173.396 | AS27: 218 | AT27: 269.313 | AU27: 329.097 | AV27: 374.351 | AW27: =876-477.635 -> 398.365 | AX27: =876-AW27 -> 477.635 | AY27: 573 | AZ27: 737
A28: =+A17+1 -> 23 | B28: Cosentyx | C28: NVS | D28: Autoimmune | F28: Q115 | H28: =SUM(AO28:GL28) -> 31129 | J28: =SUM(AO28:AR28) -> 209 | K28: =SUM(AS28:AV28) -> 1128 | L28: =SUM(AW28:AZ28) -> 2071 | M28: =SUM(BA28:BD28) -> 2837 | N28: =SUM(BE28:BH28) -> 3551 | O28: =SUM(BI28:BL28) -> 3995 | P28: =SUM(BM28:BP28) -> 4718 | Q28: =SUM(BQ28:BT28) -> 4788 | R28: =SUM(BU28:BX28) -> 4980 | S28: =SUM(BY28:CB28) -> 2852 | T28: =SUM(CC28:CF28) -> 0 | U28: =SUM(CG28:CJ28) -> 0 | V28: =SUM(CK28:CN28) -> 0 | W28: =SUM(CO28:CR28) -> 0 | AO28: 22 | AP28: 30 | AQ28: 88 | AR28: 121 | AS28: 176 | AT28: 260 | AU28: 301 | AV28: 391 | AW28: 410 | AX28: 490 | AY28: 556 | AZ28: 615 | BA28: 580 | BB28: 701 | BC28: 750 | BD28: 806 | BE28: 791 | BF28: 858 | BG28: 937 | BH28: 965 | BI28: 930 | BJ28: 944 | BK28: 1012 | BL28: 1109 | BM28: 1053 | BN28: 1175 | BO28: 1247 | BP28: 1243 | BQ28: 1159 | BR28: 1275 | BS28: 1274 | BT28: 1080 | BU28: 1076 | BV28: 1272 | BW28: 1329 | BX28: 1303 | BY28: 1326 | BZ28: 1526
A29: =+A44+1 -> 33 | B29: Rinvoq | C29: ABBV | D29: Autoimmune | G29: JAK | H29: =SUM(AO29:GL29) -> 11443 | J29: =SUM(AO29:AR29) -> 282 | K29: =SUM(AS29:AV29) -> 1177 | L29: =SUM(AW29:AZ29) -> 2027 | M29: =SUM(BA29:BD29) -> 3069 | N29: =SUM(BE29:BH29) -> 4888 | O29: =SUM(BI29:BL29) -> 0 | P29: =SUM(BM29:BP29) -> 0 | Q29: =SUM(BQ29:BT29) -> 0 | R29: =SUM(BU29:BX29) -> 0 | S29: =SUM(BY29:CB29) -> 0 | T29: =SUM(CC29:CF29) -> 0 | U29: =SUM(CG29:CJ29) -> 0 | V29: =SUM(CK29:CN29) -> 0 | W29: =SUM(CO29:CR29) -> 0 | AO29: 14 | AP29: 33 | AQ29: 86 | AR29: 149 | AS29: 215 | AT29: 281 | AU29: 303 | AV29: 378 | AW29: 453 | AX29: 517 | AY29: 465 | AZ29: 592 | BA29: 695 | BB29: 770 | BC29: 686 | BD29: 918 | BE29: 1110 | BF29: 1255 | BG29: 1093 | BH29: 1430
A30: =+A31+1 -> 26 | B30: Zytiga | C30: JNJ | D30: Oncology | E30: 1 | H30: =SUM(AO30:GL30) -> 25264.5 | J30: =SUM(AO30:AR30) -> 297.5 | K30: =SUM(AS30:AV30) -> 961 | L30: =SUM(AW30:AZ30) -> 1698 | M30: =SUM(BA30:BD30) -> 2237 | N30: =SUM(BE30:BH30) -> 2231 | O30: =SUM(BI30:BL30) -> 2260 | P30: =SUM(BM30:BP30) -> 2505 | Q30: =SUM(BQ30:BT30) -> 3498 | R30: =SUM(BU30:BX30) -> 2795 | S30: =SUM(BY30:CB30) -> 2470 | T30: =SUM(CC30:CF30) -> 2297 | U30: =SUM(CG30:CJ30) -> 1770 | V30: =SUM(CK30:CN30) -> 245 | W30: =SUM(CO30:CR30) -> 0 | AO30: 5 | AP30: =AVERAGE(AO30,AQ30) -> 50 | AQ30: 95 | AR30: =AVERAGE(AQ30,AS30) -> 147.5 | AS30: 200 | AT30: 232 | AU30: 265 | AV30: 264 | AW30: 344 | AX30: 395 | AY30: 464 | AZ30: 495 | BA30: 512 | BB30: 562 | BC30: 568 | BD30: 595 | BE30: 556 | BF30: 546 | BG30: 548 | BH30: 581 | BI30: 558 | BJ30: 601 | BK30: 582 | BL30: 519 | BM30: 523 | BN30: 558 | BO30: 669 | BP30: 755 | BQ30: 845 | BR30: 909 | BS30: 958 | BT30: 786 | BU30: 679 | BV30: 698 | BW30: 741 | BX30: 677 | BY30: 690 | BZ30: 568 | CA30: 590 | CB30: 622 | CC30: 638 | CD30: 563 | CE30: 548 | CF30: 548 | CG30: 539 | CH30: 505 | CI30: 456 | CJ30: 270 | CK30: 245
A31: =+A36+1 -> 25 | B31: Genvoya | C31: GILD | D31: HIV | H31: =SUM(AO31:GL31) -> 25283 | J31: =SUM(AO31:AR31) -> 966 | K31: =SUM(AS31:AV31) -> 3177 | L31: =SUM(AW31:AZ31) -> 4478 | M31: =SUM(BA31:BD31) -> 4179 | N31: =SUM(BE31:BH31) -> 3444 | O31: =SUM(BI31:BL31) -> 2975 | P31: =SUM(BM31:BP31) -> 2520 | Q31: =SUM(BQ31:BT31) -> 2184 | R31: =SUM(BU31:BX31) -> 1360 | S31: =SUM(BY31:CB31) -> 0 | T31: =SUM(CC31:CF31) -> 0 | U31: =SUM(CG31:CJ31) -> 0 | V31: =SUM(CK31:CN31) -> 0 | W31: =SUM(CO31:CR31) -> 0 | AO31: 45 | AP31: 158 | AQ31: 302 | AR31: 461 | AS31: 563 | AT31: 769 | AU31: 857 | AV31: 988 | AW31: 1060 | AX31: 1082 | AY31: 1160 | AZ31: 1176 | BA31: 1206 | BB31: 1015 | BC31: 980 | BD31: 978 | BE31: 958 | BF31: 824 | BG31: 816 | BH31: 846 | BI31: 852 | BJ31: 673 | BK31: 706 | BL31: 744 | BM31: 756 | BN31: 582 | BO31: 582 | BP31: 600 | BQ31: 640 | BR31: 501 | BS31: 540 | BT31: 503 | BU31: 517 | BV31: 403 | BW31: 440
A32: =+A39+1 -> 29 | B32: Imbruvica | C32: JNJ | D32: Oncology | E32: 1 | G32: BTK | H32: =SUM(AO32:GL32) -> 23168 | J32: =SUM(AO32:AR32) -> 200 | K32: =SUM(AS32:AV32) -> 689 | L32: =SUM(AW32:AZ32) -> 1251 | M32: =SUM(BA32:BD32) -> 1893 | N32: =SUM(BE32:BH32) -> 2615 | O32: =SUM(BI32:BL32) -> 3411 | P32: =SUM(BM32:BP32) -> 4128 | Q32: =SUM(BQ32:BT32) -> 4369 | R32: =SUM(BU32:BX32) -> 3785 | S32: =SUM(BY32:CB32) -> 827 | T32: =SUM(CC32:CF32) -> 0 | U32: =SUM(CG32:CJ32) -> 0 | V32: =SUM(CK32:CN32) -> 0 | W32: =SUM(CO32:CR32) -> 0 | AO32: 10 | AP32: 42 | AQ32: 56 | AR32: 92 | AS32: 116 | AT32: 154 | AU32: 184 | AV32: 235 | AW32: 261 | AX32: 295 | AY32: 349 | AZ32: 346 | BA32: 409 | BB32: 450 | BC32: 512 | BD32: 522 | BE32: 587 | BF32: 620 | BG32: 705 | BH32: 703 | BI32: 784 | BJ32: 831 | BK32: 921 | BL32: 875 | BM32: 1031 | BN32: 949 | BO32: 1031 | BP32: 1117 | BQ32: 1125 | BR32: 1116 | BS32: 1066 | BT32: 1062 | BU32: 1038 | BV32: 970 | BW32: 911 | BX32: 866 | BY32: 827
A33: =+A24+1 -> 31 | B33: Isentress | C33: MRK | D33: HIV | H33: =SUM(AO33:GL33) -> 16856 | J33: =SUM(AO33:AR33) -> 348 | K33: =SUM(AS33:AV33) -> 751 | L33: =SUM(AW33:AZ33) -> 1090 | M33: =SUM(BA33:BD33) -> 1359 | N33: =SUM(BE33:BH33) -> 1515 | O33: =SUM(BI33:BL33) -> 1643 | P33: =SUM(BM33:BP33) -> 1673 | Q33: =SUM(BQ33:BT33) -> 1511 | R33: =SUM(BU33:BX33) -> 1387 | S33: =SUM(BY33:CB33) -> 1205 | T33: =SUM(CC33:CF33) -> 1141 | U33: =SUM(CG33:CJ33) -> 975 | V33: =SUM(CK33:CN33) -> 857 | W33: =SUM(CO33:CR33) -> 768 | AO33: 47 | AP33: 77 | AQ33: 107 | AR33: 117 | AS33: 148 | AT33: 172 | AU33: 197 | AV33: 234 | AW33: 232 | AX33: 267 | AY33: 278 | AZ33: 313 | BA33: 292 | BB33: 337 | BC33: 343 | BD33: 387 | BE33: 337 | BF33: 398 | BG33: 399 | BH33: 381 | BI33: 362 | BJ33: 412 | BK33: 427 | BL33: 442 | BM33: 390 | BN33: 453 | BO33: 412 | BP33: 418 | BQ33: 385 | BR33: 375 | BS33: 377 | BT33: 374 | BU33: 340 | BV33: 338 | BW33: 372 | BX33: 337 | BY33: 305 | BZ33: 282 | CA33: 310 | CB33: 308 | CC33: 281 | CD33: 305 | CE33: 275 | CF33: 280 | CG33: 255 | CH33: 247 | CI33: 250 | CJ33: 223 | CK33: 245 | CL33: 196 | CM33: 205 | CN33: 211 | CO33: 209 | CP33: 192 | CQ33: 189 | CR33: 178 | CS33: 158 | CT33: 147 | CU33: 161 | CV33: 167
A34: =+A20+1 -> 17 | B34: Viagra | C34: PFE | D34: Cardiovascular | E34: 1 | G34: PDE5 | H34: =SUM(AO34:GL34) -> 34660 | J34: =SUM(AO34:AR34) -> 963 | K34: =SUM(AS34:AV34) -> 1155 | L34: =SUM(AW34:AZ34) -> 1393 | M34: =SUM(BA34:BD34) -> 1563 | N34: =SUM(BE34:BH34) -> 1788 | O34: =SUM(BI34:BL34) -> 1820 | P34: =SUM(BM34:BP34) -> 1699 | Q34: =SUM(BQ34:BT34) -> 1597 | R34: =SUM(BU34:BX34) -> 1701 | S34: =SUM(BY34:CB34) -> 1790 | T34: =SUM(CC34:CF34) -> 1928 | U34: =SUM(CG34:CJ34) -> 1917 | V34: =SUM(CK34:CN34) -> 1919 | W34: =SUM(CO34:CR34) -> 2007 | X34: =SUM(CS34:CV34) -> 2016 | Y34: =SUM(CW34:CZ34) -> 2130 | Z34: =SUM(DA34:DD34) -> 1714 | AA34: =SUM(DE34:DH34) -> 1708 | AB34: =SUM(DI34:DL34) -> 1506 | AC34: =SUM(DM34:DP34) -> 1170 | AD34: =SUM(DQ34:DT34) -> 602 | AE34: =SUM(DU34:DX34) -> 480 | AF34: =SUM(DY34:EB34) -> 94 | AG34: =SUM(EC34:EF34) -> 0 | AH34: =SUM(EG34:EJ34) -> 0 | AO34: 402 | AP34: 138 | AQ34: 233 | AR34: 190 | AS34: 305 | AT34: 245 | AU34: 277 | AV34: 328 | AW34: 304 | AX34: 332 | AY34: 380 | AZ34: 377 | BA34: 351 | BB34: 375 | BC34: 415 | BD34: 422 | BE34: 385 | BF34: 437 | BG34: 491 | BH34: 475 | BI34: 419 | BJ34: 476 | BK34: 509 | BL34: 416 | BM34: 389 | BN34: 403 | BO34: 469 | BP34: 438 | BQ34: 391 | BR34: 386 | BS34: 430 | BT34: 390 | BU34: 394 | BV34: 423 | BW34: 450 | BX34: 434 | BY34: 382 | BZ34: 450 | CA34: 498 | CB34: 460 | CC34: 463 | CD34: 509 | CE34: 502 | CF34: 454 | CG34: 423 | CH34: 466 | CI34: 549 | CJ34: 479 | CK34: 491 | CL34: 459 | CM34: 499 | CN34: 470 | CO34: 495 | CP34: 493 | CQ34: 523 | CR34: 496 | CS34: 485 | CT34: 517 | CU34: 553 | CV34: 461 | CW34: 484 | CX34: 460 | CY34: 812 | CZ34: 374 | DA34: 427 | DB34: 427 | DC34: 464 | DD34: 396 | DE34: 448 | DF34: 430 | DG34: 434 | DH34: 396 | DI34: 401 | DJ34: 386 | DK34: 381 | DL34: 338 | DM34: 348 | DN34: 308 | DO34: 265 | DP34: 249 | DQ34: 193 | DR34: 137 | DS34: 127 | DT34: 145 | DU34: 114 | DV34: 120 | DW34: 119 | DX34: 127 | DY34: 94
A35: =+A34+1 -> 18 | B35: Alimta | C35: LLY | D35: Oncology | H35: =SUM(AO35:GL35) -> 34654.8 | J35: =SUM(AO35:AR35) -> 142.5 | K35: =SUM(AS35:AV35) -> 463.2 | L35: =SUM(AW35:AZ35) -> 611.4 | M35: =SUM(BA35:BD35) -> 854 | N35: =SUM(BE35:BH35) -> 1154.8 | O35: =SUM(BI35:BL35) -> 1706.1 | P35: =SUM(BM35:BP35) -> 2208.5 | Q35: =SUM(BQ35:BT35) -> 2461.1 | R35: =SUM(BU35:BX35) -> 2594.2 | S35: =SUM(BY35:CB35) -> 2702.9 | T35: =SUM(CC35:CF35) -> 2792 | U35: =SUM(CG35:CJ35) -> 2493 | V35: =SUM(CK35:CN35) -> 2283.3 | W35: =SUM(CO35:CR35) -> 2062.5 | X35: =SUM(CS35:CV35) -> 2132.9 | Y35: =SUM(CW35:CZ35) -> 2115.9 | Z35: =SUM(DA35:DD35) -> 2329.9 | AA35: =SUM(DE35:DH35) -> 2061.5 | AB35: =SUM(DI35:DL35) -> 927.6 | AC35: =SUM(DM35:DP35) -> 217.5 | AD35: =SUM(DQ35:DT35) -> 190.2 | AE35: =SUM(DU35:DX35) -> 114.8 | AF35: =SUM(DY35:EB35) -> 35 | AG35: =SUM(EC35:EF35) -> 0 | AH35: =SUM(EG35:EJ35) -> 0 | AO35: 11.6 | AP35: 17.8 | AQ35: 40 | AR35: 73.1 | AS35: 93.9 | AT35: 111.2 | AU35: 122.3 | AV35: 135.8 | AW35: 130 | AX35: 153 | AY35: 157 | AZ35: 171.4 | BA35: 187.8 | BB35: 207.1 | BC35: 215 | BD35: 244.1 | BE35: 247.2 | BF35: 275 | BG35: 313.9 | BH35: 318.7 | BI35: 335.3 | BJ35: 385.3 | BK35: 461.9 | BL35: 523.6 | BM35: 527.4 | BN35: 551.8 | BO35: 560.3 | BP35: 569 | BQ35: 579.9 | BR35: 613.4 | BS35: 629.7 | BT35: 638.1 | BU35: 606.8 | BV35: 659.5 | BW35: 643.6 | BX35: 684.3 | BY35: 616.8 | BZ35: 669.4 | CA35: 690.5 | CB35: 726.2 | CC35: 632 | CD35: 711.6 | CE35: 723.4 | CF35: 725 | CG35: 573 | CH35: 664.3 | CI35: 628.5 | CJ35: 627.2 | CK35: 564.2 | CL35: 607.1 | CM35: 570.4 | CN35: 541.6 | CO35: 489.9 | CP35: 532.9 | CQ35: 514.5 | CR35: 525.2 | CS35: 499.6 | CT35: 555.9 | CU35: 520.5 | CV35: 556.9 | CW35: 499.2 | CX35: 577.8 | CY35: 508.2 | CZ35: 530.7 | DA35: 560.1 | DB35: 539.1 | DC35: 578 | DD35: 652.7 | DE35: 559 | DF35: 610.6 | DG35: 457 | DH35: 434.9 | DI35: 343.9 | DJ35: 227.7 | DK35: 119.4 | DL35: 236.6 | DM35: 58.2 | DN35: 60.9 | DO35: 53.5 | DP35: 44.9 | DQ35: 69.5 | DR35: 33.9 | DS35: 48 | DT35: 38.8 | DU35: 28.2 | DV35: 28.9 | DW35: 25.7 | DX35: 32 | DY35: 35
A36: =+A28+1 -> 24 | B36: Cialis | C36: LLY | D36: Cardiovascular | E36: 2 | G36: PDE5 | H36: =SUM(AO36:GL36) -> 29639.3 | J36: =SUM(AO36:AR36) -> 203.3 | K36: =SUM(AS36:AV36) -> 540.1 | L36: =SUM(AW36:AZ36) -> 690.4 | M36: =SUM(BA36:BD36) -> 943.3 | N36: =SUM(BE36:BH36) -> 1216.3 | O36: =SUM(BI36:BL36) -> 1444.5 | P36: =SUM(BM36:BP36) -> 1559.1 | Q36: =SUM(BQ36:BT36) -> 1699.4 | R36: =SUM(BU36:BX36) -> 1875.6 | S36: =SUM(BY36:CB36) -> 1926.8 | T36: =SUM(CC36:CF36) -> 2159.4 | U36: =SUM(CG36:CJ36) -> 2291 | V36: =SUM(CK36:CN36) -> 2310.7 | W36: =SUM(CO36:CR36) -> 2471.7 | X36: =SUM(CS36:CV36) -> 2323.2 | Y36: =SUM(CW36:CZ36) -> 1851.9 | Z36: =SUM(DA36:DD36) -> 890.5 | AA36: =SUM(DE36:DH36) -> 607.1 | AB36: =SUM(DI36:DL36) -> 718.4 | AC36: =SUM(DM36:DP36) -> 587.3 | AD36: =SUM(DQ36:DT36) -> 381.5 | AE36: =SUM(DU36:DX36) -> 394.2 | AF36: =SUM(DY36:EB36) -> 462.6 | AG36: =SUM(EC36:EF36) -> 91 | AH36: =SUM(EG36:EJ36) -> 0 | AO36: 21.5 | AP36: 37.5 | AQ36: 50.2 | AR36: 94.1 | AS36: 108.3 | AT36: 125 | AU36: 154.1 | AV36: 152.7 | AW36: 150.1 | AX36: 165.1 | AY36: 180.1 | AZ36: 195.1 | BA36: 210.1 | BB36: 225.1 | BC36: 240.1 | BD36: 268 | BE36: 266 | BF36: 293.1 | BG36: 311 | BH36: 346.2 | BI36: 336.9 | BJ36: 362.2 | BK36: 376.6 | BL36: 368.8 | BM36: 358.8 | BN36: 363.6 | BO36: 397.2 | BP36: 439.5 | BQ36: 408.3 | BR36: 418.7 | BS36: 406.5 | BT36: 465.9 | BU36: 434.4 | BV36: 477.2 | BW36: 469.8 | BX36: 494.2 | BY36: 461.8 | BZ36: 469.5 | CA36: 482.1 | CB36: 513.4 | CC36: 515 | CD36: 529.4 | CE36: 526.7 | CF36: 588.3 | CG36: 532.4 | CH36: 567.8 | CI36: 568.4 | CJ36: 622.4 | CK36: 538.3 | CL36: 567.9 | CM36: 566.1 | CN36: 638.4 | CO36: 576.7 | CP36: 630.5 | CQ36: 588.2 | CR36: 676.3 | CS36: 533.6 | CT36: 627.3 | CU36: 564.9 | CV36: 597.4 | CW36: 495.4 | CX36: 538.7 | CY36: 467.1 | CZ36: 350.7 | DA36: 308.2 | DB36: 200.2 | DC36: 184.3 | DD36: 197.8 | DE36: 193 | DF36: 130.7 | DG36: 162.5 | DH36: 120.9 | DI36: 126.8 | DJ36: 281 | DK36: 130.9 | DL36: 179.7 | DM36: 217.7 | DN36: 147 | DO36: 115.7 | DP36: 106.9 | DQ36: 100.3 | DR36: 115.6 | DS36: 86.8 | DT36: 78.8 | DU36: 139.3 | DV36: 87.7 | DW36: 91.5 | DX36: 75.7 | DY36: 69.9 | DZ36: 66.6 | EA36: 254.1 | EB36: 72 | EC36: 91
A37: =+A30+1 -> 27 | B37: Entresto | C37: NVS | D37: Cardiovascular | E37: 1 | H37: =SUM(AO37:GL37) -> 23953 | J37: =SUM(AO37:AR37) -> 70 | K37: =SUM(AS37:AV37) -> 315 | L37: =SUM(AW37:AZ37) -> 752 | M37: =SUM(BA37:BD37) -> 1367 | N37: =SUM(BE37:BH37) -> 2097 | O37: =SUM(BI37:BL37) -> 3023 | P37: =SUM(BM37:BP37) -> 4091 | Q37: =SUM(BQ37:BT37) -> 5341 | R37: =SUM(BU37:BX37) -> 6897 | S37: =SUM(BY37:CB37) -> 0 | T37: =SUM(CC37:CF37) -> 0 | U37: =SUM(CG37:CJ37) -> 0 | V37: =SUM(CK37:CN37) -> 0 | W37: =SUM(CO37:CR37) -> 0 | X37: =SUM(CS37:CV37) -> 0 | Y37: =SUM(CW37:CZ37) -> 0 | Z37: =SUM(DA37:DD37) -> 0 | AA37: =SUM(DE37:DH37) -> 0 | AB37: =SUM(DI37:DL37) -> 0 | AC37: =SUM(DM37:DP37) -> 0 | AD37: =SUM(DQ37:DT37) -> 0 | AE37: =SUM(DU37:DX37) -> 0 | AF37: =SUM(DY37:EB37) -> 0 | AG37: =SUM(EC37:EF37) -> 0 | AH37: =SUM(EG37:EJ37) -> 0 | AO37: 16 | AP37: 5 | AQ37: 17 | AR37: 32 | AS37: 53 | AT37: 68 | AU37: 84 | AV37: 110 | AW37: 128 | AX37: 185 | AY37: 200 | AZ37: 239 | BA37: 271 | BB37: 318 | BC37: 357 | BD37: 421 | BE37: 430 | BF37: 518 | BG37: 569 | BH37: 580 | BI37: 632 | BJ37: 716 | BK37: 789 | BL37: 886 | BM37: 924 | BN37: 949 | BO37: 1093 | BP37: 1125 | BQ37: 1135 | BR37: 1291 | BS37: 1399 | BT37: 1516 | BU37: 1485 | BV37: 1635 | BW37: 1879 | BX37: 1898
A38: =+A60+1 -> 49 | B38: Zepbound | C38: LLY | D38: Diabetes | E38: 4 | G38: GLP-1 | H38: =SUM(AO38:GL38) -> 22803.4 | J38: =SUM(AO38:AR38) -> 3193.8 | K38: =SUM(AS38:AV38) -> 11188.6 | L38: =SUM(AW38:AZ38) -> 8421 | M38: =SUM(BA38:BD38) -> 0 | N38: =SUM(BE38:BH38) -> 0 | O38: =SUM(BI38:BL38) -> 0 | P38: =SUM(BM38:BP38) -> 0 | Q38: =SUM(BQ38:BT38) -> 0 | X38: =SUM(CS38:CV38) -> 0 | Y38: =SUM(CW38:CZ38) -> 0 | Z38: =SUM(DA38:DD38) -> 0 | AA38: =SUM(DE38:DH38) -> 0 | AB38: =SUM(DI38:DL38) -> 0 | AC38: =SUM(DM38:DP38) -> 0 | AD38: =SUM(DQ38:DT38) -> 0 | AE38: =SUM(DU38:DX38) -> 0 | AF38: =SUM(DY38:EB38) -> 0 | AG38: =SUM(EC38:EF38) -> 0 | AH38: =SUM(EG38:EJ38) -> 0 | AO38: 176 | AP38: 517 | AQ38: 1243 | AR38: 1257.8 | AS38: 1907.2 | AT38: 2311.9 | AU38: 3381.4 | AV38: 3588.1 | AW38: 4261 | AX38: 4160
A39: =+A37+1 -> 28 | B39: Paxlovid | C39: PFE | D39: COVID-19 | E39: 1 | H39: =SUM(AO39:GL39) -> 22574 | J39: =SUM(AO39:AR39) -> 17175 | K39: =SUM(AS39:AV39) -> 6248 | L39: =SUM(AW39:AZ39) -> -849 | M39: =SUM(BA39:BD39) -> 0 | N39: =SUM(BE39:BH39) -> 0 | O39: =SUM(BI39:BL39) -> 0 | P39: =SUM(BM39:BP39) -> 0 | Q39: =SUM(BQ39:BT39) -> 0 | R39: =SUM(BU39:BX39) -> 0 | S39: =SUM(BY39:CB39) -> 0 | T39: =SUM(CC39:CF39) -> 0 | U39: =SUM(CG39:CJ39) -> 0 | V39: =SUM(CK39:CN39) -> 0 | W39: =SUM(CO39:CR39) -> 0 | X39: =SUM(CS39:CV39) -> 0 | Y39: =SUM(CW39:CZ39) -> 0 | Z39: =SUM(DA39:DD39) -> 0 | AA39: =SUM(DE39:DH39) -> 0 | AB39: =SUM(DI39:DL39) -> 0 | AC39: =SUM(DM39:DP39) -> 0 | AD39: =SUM(DQ39:DT39) -> 0 | AE39: =SUM(DU39:DX39) -> 0 | AF39: =SUM(DY39:EB39) -> 0 | AG39: =SUM(EC39:EF39) -> 0 | AH39: =SUM(EG39:EJ39) -> 0 | AO39: 76 | AP39: 1470 | AQ39: 8115 | AR39: 7514 | AS39: 1834 | AT39: 4069 | AU39: 143 | AV39: 202 | AW39: -3135 | AX39: 2035 | AY39: 251
A40: =+A48+1 -> 42 | B40: Verzenio | C40: LLY | D40: Oncology | H40: =SUM(AO40:GL40) -> 21796.1 | J40: =SUM(AO40:AR40) -> 192.9 | K40: =SUM(AS40:AV40) -> 483.6 | L40: =SUM(AW40:AZ40) -> 810.1 | M40: =SUM(BA40:BD40) -> 1227.4 | N40: =SUM(BE40:BH40) -> 2079.7 | O40: =SUM(BI40:BL40) -> 3525.9 | P40: =SUM(BM40:BP40) -> 4896.9 | Q40: =SUM(BQ40:BT40) -> 5673.6 | X40: =SUM(CS40:CV40) -> 0 | Y40: =SUM(CW40:CZ40) -> 0 | Z40: =SUM(DA40:DD40) -> 0 | AA40: =SUM(DE40:DH40) -> 0 | AB40: =SUM(DI40:DL40) -> 0 | AC40: =SUM(DM40:DP40) -> 0 | AD40: =SUM(DQ40:DT40) -> 0 | AE40: =SUM(DU40:DX40) -> 0 | AF40: =SUM(DY40:EB40) -> 0 | AG40: =SUM(EC40:EF40) -> 0 | AH40: =SUM(EG40:EJ40) -> 0 | AO40: 21 | AP40: 29.7 | AQ40: 57.7 | AR40: 84.5 | AS40: 83.1 | AT40: 109.4 | AU40: 133.9 | AV40: 157.2 | AW40: 179.1 | AX40: 188 | AY40: 208.6 | AZ40: 234.4 | BA40: 281.6 | BB40: 269 | BC40: 341.3 | BD40: 335.5 | BE40: 404.1 | BF40: 469.4 | BG40: 588.5 | BH40: 617.7 | BI40: 808 | BJ40: 750.9 | BK40: 926.8 | BL40: 1040.2 | BM40: 1145.4 | BN40: 1050.3 | BO40: 1331.9 | BP40: 1369.3 | BQ40: 1555.2 | BR40: 1158.9 | BS40: 1489.3 | BT40: 1470.2 | BU40: 1604 | BV40: 1302
A41: =+A75+1 -> 63 | B41: Forteo | C41: LLY | D41: Endocrinology | H41: =SUM(AO41:GL41) -> 20335.6 | J41: =SUM(AO41:AR41) -> 65.3 | K41: =SUM(AS41:AV41) -> 238.5 | L41: =SUM(AW41:AZ41) -> 389.5 | M41: =SUM(BA41:BD41) -> 594.1 | N41: =SUM(BE41:BH41) -> 709.3 | O41: =SUM(BI41:BL41) -> 778.8 | P41: =SUM(BM41:BP41) -> 816.7 | Q41: =SUM(BQ41:BT41) -> 830.1 | R41: =SUM(BU41:BX41) -> 949.9 | S41: =SUM(BY41:CB41) -> 1151 | T41: =SUM(CC41:CF41) -> 1244.9 | U41: =SUM(CG41:CJ41) -> 1322 | V41: =SUM(CK41:CN41) -> 1348.2 | W41: =SUM(CO41:CR41) -> 1499.9 | X41: =SUM(CS41:CV41) -> 1749.1 | Y41: =SUM(CW41:CZ41) -> 1575.6 | Z41: =SUM(DA41:DD41) -> 1404.6 | AA41: =SUM(DE41:DH41) -> 1046.4 | AB41: =SUM(DI41:DL41) -> 801.8 | AC41: =SUM(DM41:DP41) -> 613 | AD41: =SUM(DQ41:DT41) -> 533.2 | AE41: =SUM(DU41:DX41) -> 310.9 | AF41: =SUM(DY41:EB41) -> 289.8 | AG41: =SUM(EC41:EF41) -> 73 | AH41: =SUM(EG41:EJ41) -> 0 | AO41: 4.1 | AP41: 13.7 | AQ41: 21.6 | AR41: 25.9 | AS41: 40.8 | AT41: 65.3 | AU41: 58.1 | AV41: 74.3 | AW41: 67 | AX41: 101.9 | AY41: 102.6 | AZ41: 118 | BA41: 127 | BB41: 146 | BC41: 149 | BD41: 172.1 | BE41: 153.4 | BF41: 177.2 | BG41: 180.5 | BH41: 198.2 | BI41: 185 | BJ41: 206.6 | BK41: 192.7 | BL41: 194.5 | BM41: 187.5 | BN41: 203.3 | BO41: 213.1 | BP41: 212.8 | BQ41: 194.5 | BR41: 209.6 | BS41: 199.7 | BT41: 226.3 | BU41: 216.1 | BV41: 231 | BW41: 240.3 | BX41: 262.5 | BY41: 271.3 | BZ41: 276.4 | CA41: 288.7 | CB41: 314.6 | CC41: 281.5 | CD41: 296.9 | CE41: 306.7 | CF41: 359.8 | CG41: 300.4 | CH41: 308.6 | CI41: 332.2 | CJ41: 380.8 | CK41: 293 | CL41: 328.4 | CM41: 348.9 | CN41: 377.9 | CO41: 318.6 | CP41: 367.6 | CQ41: 391.2 | CR41: 422.5 | CS41: 347.5 | CT41: 446.7 | CU41: 441.7 | CV41: 513.2 | CW41: 313.2 | CX41: 434.5 | CY41: 390.8 | CZ41: 437.1 | DA41: 312.9 | DB41: 360.8 | DC41: 370.7 | DD41: 360.2 | DE41: 272.4 | DF41: 252.7 | DG41: 266.9 | DH41: 254.4 | DI41: 198.5 | DJ41: 218.4 | DK41: 200.9 | DL41: 184 | DM41: 137.4 | DN41: 138.5 | DO41: 177.1 | DP41: 160 | DQ41: 122.3 | DR41: 148 | DS41: 146.4 | DT41: 116.5 | DU41: 61.3 | DV41: 69.9 | DW41: 118.1 | DX41: 61.6 | DY41: 66.6 | DZ41: 92.5 | EA41: 55.7 | EB41: 75 | EC41: 73
A42: =+A47+1 -> 34 | B42: Taltz | C42: LLY | D42: Autoimmune | H42: =SUM(AO42:GL42) -> 19774.5 | J42: =SUM(AO42:AR42) -> 209.7 | K42: =SUM(AS42:AV42) -> 609 | L42: =SUM(AW42:AZ42) -> 1043.5 | M42: =SUM(BA42:BD42) -> 1557.4 | N42: =SUM(BE42:BH42) -> 1748.2 | O42: =SUM(BI42:BL42) -> 2297.7 | P42: =SUM(BM42:BP42) -> 2520.9 | Q42: =SUM(BQ42:BT42) -> 2836.8 | R42: =SUM(BU42:BX42) -> 3418.2 | S42: =SUM(BY42:CB42) -> 3533.1 | T42: =SUM(CC42:CF42) -> 0 | U42: =SUM(CG42:CJ42) -> 0 | X42: =SUM(CS42:CV42) -> 0 | Y42: =SUM(CW42:CZ42) -> 0 | Z42: =SUM(DA42:DD42) -> 0 | AA42: =SUM(DE42:DH42) -> 0 | AB42: =SUM(DI42:DL42) -> 0 | AC42: =SUM(DM42:DP42) -> 0 | AD42: =SUM(DQ42:DT42) -> 0 | AE42: =SUM(DU42:DX42) -> 0 | AF42: =SUM(DY42:EB42) -> 0 | AG42: =SUM(EC42:EF42) -> 0 | AH42: =SUM(EG42:EJ42) -> 0 | AO42: 19.3 | AP42: 32.5 | AQ42: 61.3 | AR42: 96.6 | AS42: 138.7 | AT42: 151.3 | AU42: 172.5 | AV42: 146.5 | AW42: 220.1 | AX42: 263.9 | AY42: 307 | AZ42: 252.5 | BA42: 353.8 | BB42: 340 | BC42: 420.1 | BD42: 443.5 | BE42: 395.2 | BF42: 454.5 | BG42: 495.3 | BH42: 403.2 | BI42: 569.1 | BJ42: 593.1 | BK42: 647.4 | BL42: 488.1 | BM42: 606.2 | BN42: 679.9 | BO42: 707.8 | BP42: 527 | BQ42: 703.9 | BR42: 744.2 | BS42: 784.6 | BT42: 604.1 | BU42: 824.7 | BV42: 879.6 | BW42: 952 | BX42: 761.9 | BY42: 847.6 | BZ42: 901.5 | CA42: 1051 | CB42: 733
A43: =+A50+1 -> 38 | B43: Jardiance | C43: LLY | D43: Diabetes | H43: =SUM(AO43:GL43) -> 17654.1 | J43: =SUM(AO43:AR43) -> 60.4 | K43: =SUM(AS43:AV43) -> 201.9 | L43: =SUM(AW43:AZ43) -> 447.6 | M43: =SUM(BA43:BD43) -> 658.3 | N43: =SUM(BE43:BH43) -> 944.2 | O43: =SUM(BI43:BL43) -> 1153.9 | P43: =SUM(BM43:BP43) -> 1490.8 | Q43: =SUM(BQ43:BT43) -> 2066 | R43: =SUM(BU43:BX43) -> 2744.7 | S43: =SUM(BY43:CB43) -> 3340.9 | T43: =SUM(CC43:CF43) -> 3431.4 | U43: =SUM(CG43:CJ43) -> 1114 | V43: =SUM(CK43:CN43) -> 0 | W43: =SUM(CO43:CR43) -> 0 | X43: =SUM(CS43:CV43) -> 0 | Y43: =SUM(CW43:CZ43) -> 0 | Z43: =SUM(DA43:DD43) -> 0 | AA43: =SUM(DE43:DH43) -> 0 | AB43: =SUM(DI43:DL43) -> 0 | AC43: =SUM(DM43:DP43) -> 0 | AD43: =SUM(DQ43:DT43) -> 0 | AE43: =SUM(DU43:DX43) -> 0 | AF43: =SUM(DY43:EB43) -> 0 | AG43: =SUM(EC43:EF43) -> 0 | AH43: =SUM(EG43:EJ43) -> 0 | AO43: 19.3 | AP43: 11.1 | AQ43: 15.4 | AR43: 14.6 | AS43: 38.2 | AT43: 40.1 | AU43: 47.5 | AV43: 76.1 | AW43: 74 | AX43: 103.2 | AY43: 127.2 | AZ43: 143.2 | BA43: 151 | BB43: 147.2 | BC43: 166.9 | BD43: 193.2 | BE43: 203.6 | BF43: 231.9 | BG43: 240.7 | BH43: 268 | BI43: 267.5 | BJ43: 262 | BK43: 310.8 | BL43: 313.6 | BM43: 312 | BN43: 356.5 | BO43: 390.4 | BP43: 431.9 | BQ43: 419.4 | BR43: 461 | BS43: 573.3 | BT43: 612.3 | BU43: 577.5 | BV43: 668.3 | BW43: 700.8 | BX43: 798.1 | BY43: 686.5 | BZ43: 769.6 | CA43: 686.4 | CB43: 1198.4 | CC43: 1014.4 | CD43: 690 | CE43: 959 | CF43: 768 | CG43: 1114
A44: =+A33+1 -> 32 | B44: Xeljanz | C44: PFE | D44: Autoimmune | G44: JAK | H44: =SUM(AO44:GL44) -> 16115 | J44: =SUM(AO44:AR44) -> 63 | K44: =SUM(AS44:AV44) -> 251 | L44: =SUM(AW44:AZ44) -> 455 | M44: =SUM(BA44:BD44) -> 821 | N44: =SUM(BE44:BH44) -> 1212 | O44: =SUM(BI44:BL44) -> 1631 | P44: =SUM(BM44:BP44) -> 2188 | Q44: =SUM(BQ44:BT44) -> 2347 | R44: =SUM(BU44:BX44) -> 2430 | S44: =SUM(BY44:CB44) -> 2025 | T44: =SUM(CC44:CF44) -> 1702 | U44: =SUM(CG44:CJ44) -> 990 | V44: =SUM(CK44:CN44) -> 0 | W44: =SUM(CO44:CR44) -> 0 | X44: =SUM(CS44:CV44) -> 0 | Y44: =SUM(CW44:CZ44) -> 0 | Z44: =SUM(DA44:DD44) -> 0 | AA44: =SUM(DE44:DH44) -> 0 | AB44: =SUM(DI44:DL44) -> 0 | AC44: =SUM(DM44:DP44) -> 0 | AD44: =SUM(DQ44:DT44) -> 0 | AE44: =SUM(DU44:DX44) -> 0 | AF44: =SUM(DY44:EB44) -> 0 | AG44: =SUM(EC44:EF44) -> 0 | AH44: =SUM(EG44:EJ44) -> 0 | AO44: 6 | AP44: 0 | AQ44: 22 | AR44: 35 | AS44: 46 | AT44: 52 | AU44: 68 | AV44: 85 | AW44: 104 | AX44: 96 | AY44: 128 | AZ44: 127 | BA44: 172 | BB44: 197 | BC44: 217 | BD44: 235 | BE44: 278 | BF44: 250 | BG44: 336 | BH44: 348 | BI44: 410 | BJ44: 326 | BK44: 463 | BL44: 432 | BM44: 553 | BN44: 423 | BO44: 613 | BP44: 599 | BQ44: 607 | BR44: 451 | BS44: 635 | BT44: 654 | BU44: 696 | BV44: 538 | BW44: 586 | BX44: 610 | BY44: 721 | BZ44: 372 | CA44: 430 | CB44: 502 | CC44: 493 | CD44: 237 | CE44: 469 | CF44: 503 | CG44: 493 | CH44: 194 | CI44: 303
A45: =+A64+1 -> 54 | B45: Gemzar | C45: LLY | D45: Oncology | H45: =SUM(AO45:GL45) -> 14413.2 | J45: =SUM(AO45:AR45) -> 95.1 | K45: =SUM(AS45:AV45) -> 198.7 | L45: =SUM(AW45:AZ45) -> 364.2 | M45: =SUM(BA45:BD45) -> 477.4 | N45: =SUM(BE45:BH45) -> 597.3 | O45: =SUM(BI45:BL45) -> 746.4 | P45: =SUM(BM45:BP45) -> 911 | Q45: =SUM(BQ45:BT45) -> 1066.8 | R45: =SUM(BU45:BX45) -> 1240.1 | S45: =SUM(BY45:CB45) -> 1368.9 | T45: =SUM(CC45:CF45) -> 1447.2 | U45: =SUM(CG45:CJ45) -> 1641.7 | V45: =SUM(CK45:CN45) -> 1661.4 | W45: =SUM(CO45:CR45) -> 1283.3 | X45: =SUM(CS45:CV45) -> 1017.7 | Y45: =SUM(CW45:CZ45) -> 296 | Z45: =SUM(DA45:DD45) -> 0 | AA45: =SUM(DE45:DH45) -> 0 | AB45: =SUM(DI45:DL45) -> 0 | AC45: =SUM(DM45:DP45) -> 0 | AD45: =SUM(DQ45:DT45) -> 0 | AE45: =SUM(DU45:DX45) -> 0 | AF45: =SUM(DY45:EB45) -> 0 | AG45: =SUM(EC45:EF45) -> 0 | AH45: =SUM(EG45:EJ45) -> 0 | AO45: 12 | AP45: 22 | AQ45: =62-AP45-AO45 -> 28 | AR45: 33.1 | AS45: 41 | AT45: 47.3 | AU45: =174.8-AT45-AS45-AR45 -> 53.4 | AV45: 57 | AW45: 85 | AX45: 69 | AY45: =306.8-AX45-AW45-AV45 -> 95.8 | AZ45: 114.4 | BA45: 86.5 | BB45: 119.2 | BC45: =455.8-BB45-BA45-AZ45 -> 135.7 | BD45: 136 | BE45: 107.9 | BF45: 155.1 | BG45: =559.3-BF45-BE45-BD45 -> 160.3 | BH45: 174 | BI45: 160.9 | BJ45: 187 | BK45: =722.9-BJ45-BI45-BH45 -> 201 | BL45: 197.5 | BM45: 219 | BN45: 197.2 | BO45: =874.6-BN45-BM45-BL45 -> 260.9 | BP45: 233.9 | BQ45: 254.6 | BR45: 250.6 | BS45: 282.6 | BT45: 279 | BU45: 293.3 | BV45: 312.7 | BW45: 329.5 | BX45: 304.6 | BY45: 343 | BZ45: 334.3 | CA45: 352.6 | CB45: 339 | CC45: 344 | CD45: 355 | CE45: 371.3 | CF45: 376.9 | CG45: 395.6 | CH45: 394.4 | CI45: 425.5 | CJ45: 426.2 | CK45: 440.1 | CL45: 440.2 | CM45: 413.3 | CN45: 367.8 | CO45: 353.2 | CP45: 331.8 | CQ45: 310.5 | CR45: 287.8 | CS45: 293.4 | CT45: 324.6 | CU45: 243.6 | CV45: 156.1 | CW45: 112.4 | CX45: 91 | CY45: 92.6 | CZ45: 0 | DA45: 0 | DB45: 0
A46: =+A33+1 -> 32 | B46: Descovy | C46: GILD | D46: HIV | H46: =SUM(AO46:GL46) -> 12925 | J46: =SUM(AO46:AR46) -> 549 | K46: =SUM(AS46:AV46) -> 1328 | L46: =SUM(AW46:AZ46) -> 1562 | M46: =SUM(BA46:BD46) -> 1616 | N46: =SUM(BE46:BH46) -> 1762 | O46: =SUM(BI46:BL46) -> 1715 | P46: =SUM(BM46:BP46) -> 1946 | Q46: =SUM(BQ46:BT46) -> 1962 | R46: =SUM(BU46:BX46) -> 485 | S46: =SUM(BY46:CB46) -> 0 | T46: =SUM(CC46:CF46) -> 0 | U46: =SUM(CG46:CJ46) -> 0 | V46: =SUM(CK46:CN46) -> 0 | W46: =SUM(CO46:CR46) -> 0 | X46: =SUM(CS46:CV46) -> 0 | Y46: =SUM(CW46:CZ46) -> 0 | Z46: =SUM(DA46:DD46) -> 0 | AA46: =SUM(DE46:DH46) -> 0 | AB46: =SUM(DI46:DL46) -> 0 | AC46: =SUM(DM46:DP46) -> 0 | AD46: =SUM(DQ46:DT46) -> 0 | AE46: =SUM(DU46:DX46) -> 0 | AF46: =SUM(DY46:EB46) -> 0 | AG46: =SUM(EC46:EF46) -> 0 | AH46: =SUM(EG46:EJ46) -> 0 | AO46: 61 | AP46: 88 | AQ46: 149 | AR46: 251 | AS46: 286 | AT46: 316 | AU46: 365 | AV46: 361 | AW46: 403 | AX46: 406 | AY46: 411 | AZ46: 342 | BA46: 358 | BB46: 363 | BC46: 437 | BD46: 458 | BE46: 417 | BF46: 508 | BG46: 478 | BH46: 359 | BI46: 435 | BJ46: 433 | BK46: 473 | BL46: 374 | BM46: 460 | BN46: 500 | BO46: 537 | BP46: 449 | BQ46: 516 | BR46: 511 | BS46: 509 | BT46: 426 | BU46: 485
A47: =+A46+1 -> 33 | B47: Vyndaqel | C47: PFE | D47: Rare | E47: 1 | H47: =SUM(AO47:GL47) -> 12080 | J47: =SUM(AO47:AR47) -> 180 | K47: =SUM(AS47:AV47) -> 877 | L47: =SUM(AW47:AZ47) -> 1734 | M47: =SUM(BA47:BD47) -> 2226 | N47: =SUM(BE47:BH47) -> 2750 | O47: =SUM(BI47:BL47) -> 4313 | P47: =SUM(BM47:BP47) -> 0 | Q47: =SUM(BQ47:BT47) -> 0 | R47: =SUM(BU47:BX47) -> 0 | S47: =SUM(BY47:CB47) -> 0 | T47: =SUM(CC47:CF47) -> 0 | U47: =SUM(CG47:CJ47) -> 0 | V47: =SUM(CK47:CN47) -> 0 | W47: =SUM(CO47:CR47) -> 0 | X47: =SUM(CS47:CV47) -> 0 | Y47: =SUM(CW47:CZ47) -> 0 | Z47: =SUM(DA47:DD47) -> 0 | AA47: =SUM(DE47:DH47) -> 0 | AB47: =SUM(DI47:DL47) -> 0 | AC47: =SUM(DM47:DP47) -> 0 | AD47: =SUM(DQ47:DT47) -> 0 | AE47: =SUM(DU47:DX47) -> 0 | AF47: =SUM(DY47:EB47) -> 0 | AG47: =SUM(EC47:EF47) -> 0 | AH47: =SUM(EG47:EJ47) -> 0 | AO47: 37 | AP47: 39 | AQ47: 41 | AR47: 63 | AS47: 156 | AT47: 213 | AU47: 231 | AV47: 277 | AW47: 351 | AX47: 429 | AY47: 453 | AZ47: 501 | BA47: 501 | BB47: 561 | BC47: 612 | BD47: 552 | BE47: 602 | BF47: 680 | BG47: 686 | BH47: 782 | BI47: 892 | BJ47: 961 | BK47: 1137 | BL47: 1323
A48: =+A53+1 -> 41 | B48: Cyramza | C48: LLY | D48: Oncology | H48: =SUM(AO48:GL48) -> 9781 | J48: =SUM(AO48:AR48) -> 143.2 | K48: =SUM(AS48:AV48) -> 447.4 | L48: =SUM(AW48:AZ48) -> 654.3 | M48: =SUM(BA48:BD48) -> 770.7 | N48: =SUM(BE48:BH48) -> 836.1 | O48: =SUM(BI48:BL48) -> 965.9 | P48: =SUM(BM48:BP48) -> 1034.1 | Q48: =SUM(BQ48:BT48) -> 1022.8 | R48: =SUM(BU48:BX48) -> 978 | S48: =SUM(BY48:CB48) -> 967.9 | T48: =SUM(CC48:CF48) -> 968.4 | U48: =SUM(CG48:CJ48) -> 992.2 | V48: =SUM(CK48:CN48) -> 0 | W48: =SUM(CO48:CR48) -> 0 | X48: =SUM(CS48:CV48) -> 0 | Y48: =SUM(CW48:CZ48) -> 0 | Z48: =SUM(DA48:DD48) -> 0 | AA48: =SUM(DE48:DH48) -> 0 | AB48: =SUM(DI48:DL48) -> 0 | AC48: =SUM(DM48:DP48) -> 0 | AD48: =SUM(DQ48:DT48) -> 0 | AE48: =SUM(DU48:DX48) -> 0 | AF48: =SUM(DY48:EB48) -> 0 | AG48: =SUM(EC48:EF48) -> 0 | AH48: =SUM(EG48:EJ48) -> 0 | AO48: 13.7 | AP48: 28.4 | AQ48: 33.6 | AR48: 67.5 | AS48: 87.7 | AT48: 111.2 | AU48: 117.5 | AV48: 131 | AW48: 147 | AX48: 159 | AY48: 177.1 | AZ48: 171.2 | BA48: 186.3 | BB48: 196 | BC48: 204.8 | BD48: 183.6 | BE48: 218.8 | BF48: 198.4 | BG48: 220.6 | BH48: 198.3 | BI48: 241.8 | BJ48: 240 | BK48: 245.1 | BL48: 239 | BM48: 256.7 | BN48: 252.7 | BO48: 284.2 | BP48: 240.5 | BQ48: 268.7 | BR48: 253.4 | BS48: 270.4 | BT48: 230.3 | BU48: 231.3 | BV48: 232.1 | BW48: 277.8 | BX48: 236.8 | BY48: 260.3 | BZ48: 224.1 | CA48: 253.6 | CB48: 229.9 | CC48: 248.9 | CD48: 236 | CE48: 258.6 | CF48: 224.9 | CG48: 253.7 | CH48: 245.5 | CI48: 262 | CJ48: 231
A49: =+A42+1 -> 35 | B49: Bridion | C49: MRK/SGP | D49: Hospital | H49: =SUM(AO49:GL49) -> 9091 | J49: =SUM(AO49:AR49) -> 200 | K49: =SUM(AS49:AV49) -> 261 | L49: =SUM(AW49:AZ49) -> 289 | M49: =SUM(BA49:BD49) -> 340 | N49: =SUM(BE49:BH49) -> 353 | O49: =SUM(BI49:BL49) -> 481 | P49: =SUM(BM49:BP49) -> 705 | Q49: =SUM(BQ49:BT49) -> 917 | R49: =SUM(BU49:BX49) -> 1130 | S49: =SUM(BY49:CB49) -> 1198 | T49: =SUM(CC49:CF49) -> 1532 | U49: =SUM(CG49:CJ49) -> 1685 | V49: =SUM(CK49:CN49) -> 0 | W49: =SUM(CO49:CR49) -> 0 | X49: =SUM(CS49:CV49) -> 0 | Y49: =SUM(CW49:CZ49) -> 0 | Z49: =SUM(DA49:DD49) -> 0 | AA49: =SUM(DE49:DH49) -> 0 | AB49: =SUM(DI49:DL49) -> 0 | AC49: =SUM(DM49:DP49) -> 0 | AD49: =SUM(DQ49:DT49) -> 0 | AE49: =SUM(DU49:DX49) -> 0 | AF49: =SUM(DY49:EB49) -> 0 | AG49: =SUM(EC49:EF49) -> 0 | AH49: =SUM(EG49:EJ49) -> 0 | AO49: 41 | AP49: 47 | AQ49: 52 | AR49: 60 | AS49: 58 | AT49: 60 | AU49: 68 | AV49: 75 | AW49: 63 | AX49: 69 | AY49: 75 | AZ49: 82 | BA49: 73 | BB49: 82 | BC49: 90 | BD49: 95 | BE49: 85 | BF49: 87 | BG49: 89 | BH49: 92 | BI49: 90 | BJ49: 113 | BK49: 139 | BL49: 139 | BM49: 148 | BN49: 163 | BO49: 185 | BP49: 209 | BQ49: 204 | BR49: 240 | BS49: 217 | BT49: 256 | BU49: 255 | BV49: 278 | BW49: 284 | BX49: 313 | BY49: 299 | BZ49: 224 | CA49: 320 | CB49: 355 | CC49: 340 | CD49: 387 | CE49: 369 | CF49: 436 | CG49: 395 | CH49: 426 | CI49: 423 | CJ49: 441
A50: =+A27+1 -> 37 | B50: Tremfya | C50: JNJ | D50: Autoimmune | H50: =SUM(AO50:GL50) -> 8385 | J50: =SUM(AO50:AR50) -> 416 | K50: =SUM(AS50:AV50) -> 917 | L50: =SUM(AW50:AZ50) -> 1235 | M50: =SUM(BA50:BD50) -> 1816 | N50: =SUM(BE50:BH50) -> 2609 | O50: =SUM(BI50:BL50) -> 1392 | P50: =SUM(BM50:BP50) -> 0 | Q50: =SUM(BQ50:BT50) -> 0 | R50: =SUM(BU50:BX50) -> 0 | S50: =SUM(BY50:CB50) -> 0 | T50: =SUM(CC50:CF50) -> 0 | U50: =SUM(CG50:CJ50) -> 0 | V50: =SUM(CK50:CN50) -> 0 | W50: =SUM(CO50:CR50) -> 0 | X50: =SUM(CS50:CV50) -> 0 | Y50: =SUM(CW50:CZ50) -> 0 | Z50: =SUM(DA50:DD50) -> 0 | AA50: =SUM(DE50:DH50) -> 0 | AB50: =SUM(DI50:DL50) -> 0 | AC50: =SUM(DM50:DP50) -> 0 | AD50: =SUM(DQ50:DT50) -> 0 | AE50: =SUM(DU50:DX50) -> 0 | AF50: =SUM(DY50:EB50) -> 0 | AG50: =SUM(EC50:EF50) -> 0 | AH50: =SUM(EG50:EJ50) -> 0 | AO50: 47 | AP50: 72 | AQ50: 126 | AR50: 171 | AS50: 175 | AT50: 217 | AU50: 235 | AV50: 290 | AW50: 270 | AX50: 296 | AY50: 342 | AZ50: 327 | BA50: 382 | BB50: 418 | BC50: 479 | BD50: 537 | BE50: 693 | BF50: 590 | BG50: 597 | BH50: 729 | BI50: 752 | BJ50: 640
A51: =+A75+1 -> 63 | B51: Erbitux | C51: LLY | D51: Oncology | G51: EGFR | H51: =SUM(AO51:GL51) -> 8274.7 | J51: =SUM(AO51:AR51) -> 389 | K51: =SUM(AS51:AV51) -> 397.7 | L51: =SUM(AW51:AZ51) -> 418.5 | M51: =SUM(BA51:BD51) -> 196.6 | N51: =SUM(BE51:BH51) -> 0 | O51: =SUM(BI51:BL51) -> 184.2 | P51: =SUM(BM51:BP51) -> 564.8 | Q51: =SUM(BQ51:BT51) -> 673.3 | R51: =SUM(BU51:BX51) -> 641.1 | S51: =SUM(BY51:CB51) -> 604.1 | T51: =SUM(CC51:CF51) -> 555.8 | U51: =SUM(CG51:CJ51) -> 528 | V51: =SUM(CK51:CN51) -> 548.6 | W51: =SUM(CO51:CR51) -> 573.7 | X51: =SUM(CS51:CV51) -> 611.2 | Y51: =SUM(CW51:CZ51) -> 631.8 | Z51: =SUM(DA51:DD51) -> 756.3 | AA51: =SUM(DE51:DH51) -> 0 | AB51: =SUM(DI51:DL51) -> 0 | AC51: =SUM(DM51:DP51) -> 0 | AD51: =SUM(DQ51:DT51) -> 0 | AE51: =SUM(DU51:DX51) -> 0 | AF51: =SUM(DY51:EB51) -> 0 | AG51: =SUM(EC51:EF51) -> 0 | AH51: =SUM(EG51:EJ51) -> 0 | AO51: 99.7 | AP51: 101.9 | AQ51: 95 | AR51: 92.4 | AS51: 103.8 | AT51: 95.4 | AU51: 94.5 | AV51: 104 | AW51: 100.1 | AX51: 97.2 | AY51: 107.9 | AZ51: 113.3 | BA51: 110 | BB51: 86.6 | BK51: 96 | BL51: 88.2 | BM51: 134.6 | BN51: 85.9 | BO51: 176.2 | BP51: 168.1 | BQ51: 180.6 | BR51: 184.6 | BS51: 153.7 | BT51: 154.4 | BU51: 159.1 | BV51: 163.5 | BW51: 168.9 | BX51: 149.6 | BY51: 166.4 | BZ51: 159.5 | CA51: 159.8 | CB51: 118.4 | CC51: 159.3 | CD51: 128.6 | CE51: =543.4-CD51-CC51-CB51 -> 137.1 | CF51: 130.8 | CG51: 129.5 | CH51: 136.4 | CI51: =480.1+56.3-CH51-CG51-CF51 -> 139.7 | CJ51: 122.4 | CK51: 147 | CL51: 134.3 | CM51: =548.3-CL51-CK51-CJ51 -> 144.6 | CN51: 122.7 | CO51: 140.8 | CP51: 144.9 | CQ51: =566.5-CP51-CO51-CN51 -> 158.1 | CR51: 129.9 | CS51: 162.5 | CT51: 153.9 | CU51: =596.5-CT51-CS51-CR51 -> 150.2 | CV51: 144.6 | CW51: 155.8 | CX51: 152 | CY51: 175 | CZ51: 149 | DA51: 183.7 | DB51: 198.6 | DC51: 196 | DD51: 178
A52: =+A55+1 -> 44 | B52: Basaglar | C52: LLY | D52: Diabetes | H52: =SUM(AO52:GL52) -> 7457.3 | J52: =SUM(AO52:AR52) -> 38.3 | K52: =SUM(AS52:AV52) -> 191.5 | L52: =SUM(AW52:AZ52) -> 667.3 | M52: =SUM(BA52:BD52) -> 975.5 | N52: =SUM(BE52:BH52) -> 1164.5 | O52: =SUM(BI52:BL52) -> 987.6 | P52: =SUM(BM52:BP52) -> 800.9 | Q52: =SUM(BQ52:BT52) -> 758.2 | R52: =SUM(BU52:BX52) -> 703.2 | S52: =SUM(BY52:CB52) -> 657.1 | T52: =SUM(CC52:CF52) -> 513.2 | U52: =SUM(CG52:CJ52) -> 0 | V52: =SUM(CK52:CN52) -> 0 | W52: =SUM(CO52:CR52) -> 0 | X52: =SUM(CS52:CV52) -> 0 | Y52: =SUM(CW52:CZ52) -> 0 | Z52: =SUM(DA52:DD52) -> 0 | AA52: =SUM(DE52:DH52) -> 0 | AB52: =SUM(DI52:DL52) -> 0 | AC52: =SUM(DM52:DP52) -> 0 | AD52: =SUM(DQ52:DT52) -> 0 | AE52: =SUM(DU52:DX52) -> 0 | AF52: =SUM(DY52:EB52) -> 0 | AG52: =SUM(EC52:EF52) -> 0 | AH52: =SUM(EG52:EJ52) -> 0 | AO52: 3.8 | AP52: 7.3 | AQ52: 10.9 | AR52: 16.3 | AS52: 19.4 | AT52: 39.5 | AU52: 46 | AV52: 86.6 | AW52: 145.7 | AX52: 153.8 | AY52: 166 | AZ52: 201.8 | BA52: 201.2 | BB52: 232.2 | BC52: 251.4 | BD52: 290.7 | BE52: 263.2 | BF52: 307.2 | BG52: 303.7 | BH52: 290.4 | BI52: 248.2 | BJ52: 282.1 | BK52: 246.6 | BL52: 210.7 | BM52: 192.8 | BN52: 242.4 | BO52: 191.5 | BP52: 174.2 | BQ52: 193 | BR52: 201.7 | BS52: 209.3 | BT52: 154.2 | BU52: 179.6 | BV52: =728.3-BU52-BT52-BS52 -> 185.2 | BW52: 157.6 | BX52: 180.8 | BY52: 161.6 | BZ52: 176.9 | CA52: 173.6 | CB52: 145 | CC52: 162.2 | CD52: 145 | CE52: 206
A53: =+A16+1 -> 40 | B53: Kisqali | C53: NVS | D53: Oncology | H53: =SUM(AO53:GL53) -> 7070 | J53: =SUM(AO53:AR53) -> 76 | K53: =SUM(AS53:AV53) -> 235 | L53: =SUM(AW53:AZ53) -> 480 | M53: =SUM(BA53:BD53) -> 687 | N53: =SUM(BE53:BH53) -> 937 | O53: =SUM(BI53:BL53) -> 1231 | P53: =SUM(BM53:BP53) -> 2080 | Q53: =SUM(BQ53:BT53) -> 1344 | R53: =SUM(BU53:BX53) -> 0 | S53: =SUM(BY53:CB53) -> 0 | T53: =SUM(CC53:CF53) -> 0 | U53: =SUM(CG53:CJ53) -> 0 | V53: =SUM(CK53:CN53) -> 0 | W53: =SUM(CO53:CR53) -> 0 | X53: =SUM(CS53:CV53) -> 0 | Y53: =SUM(CW53:CZ53) -> 0 | Z53: =SUM(DA53:DD53) -> 0 | AA53: =SUM(DE53:DH53) -> 0 | AB53: =SUM(DI53:DL53) -> 0 | AC53: =SUM(DM53:DP53) -> 0 | AD53: =SUM(DQ53:DT53) -> 0 | AE53: =SUM(DU53:DX53) -> 0 | AF53: =SUM(DY53:EB53) -> 0 | AG53: =SUM(EC53:EF53) -> 0 | AH53: =SUM(EG53:EJ53) -> 0 | AO53: 7 | AP53: 8 | AQ53: 26 | AR53: 35 | AS53: 44 | AT53: 59 | AU53: 72 | AV53: 60 | AW53: 91 | AX53: 111 | AY53: 123 | AZ53: 155 | BA53: 161 | BB53: 159 | BC53: 183 | BD53: 184 | BE53: 195 | BF53: 225 | BG53: 232 | BH53: 285 | BI53: 239 | BJ53: 308 | BK53: 327 | BL53: 357 | BM53: 415 | BN53: 493 | BO53: 562 | BP53: 610 | BQ53: 627 | BR53: 717
A54: =+A56+1 -> 46 | B54: Olumiant | C54: LLY | D54: Autoimmune | H54: =SUM(AO54:GL54) -> 6397.1 | J54: =SUM(AO54:AR54) -> 45.9 | K54: =SUM(AS54:AV54) -> 202.6 | L54: =SUM(AW54:AZ54) -> 426.9 | M54: =SUM(BA54:BD54) -> 638.9 | N54: =SUM(BE54:BH54) -> 1115.1 | O54: =SUM(BI54:BL54) -> 830.5 | P54: =SUM(BM54:BP54) -> 922.7 | Q54: =SUM(BQ54:BT54) -> 957.5 | R54: =SUM(BU54:BX54) -> 1011 | S54: =SUM(BY54:CB54) -> 246 | T54: =SUM(CC54:CF54) -> 0 | U54: =SUM(CG54:CJ54) -> 0 | V54: =SUM(CK54:CN54) -> 0 | W54: =SUM(CO54:CR54) -> 0 | X54: =SUM(CS54:CV54) -> 0 | Y54: =SUM(CW54:CZ54) -> 0 | Z54: =SUM(DA54:DD54) -> 0 | AA54: =SUM(DE54:DH54) -> 0 | AB54: =SUM(DI54:DL54) -> 0 | AC54: =SUM(DM54:DP54) -> 0 | AD54: =SUM(DQ54:DT54) -> 0 | AE54: =SUM(DU54:DX54) -> 0 | AF54: =SUM(DY54:EB54) -> 0 | AG54: =SUM(EC54:EF54) -> 0 | AH54: =SUM(EG54:EJ54) -> 0 | AO54: 1.9 | AP54: 4.8 | AQ54: 16.2 | AR54: 23 | AS54: 32.2 | AT54: 44.7 | AU54: 55.6 | AV54: 70.1 | AW54: 82.1 | AX54: 102.4 | AY54: 114.6 | AZ54: 127.8 | BA54: 139.7 | BB54: 145 | BC54: 162 | BD54: 192.2 | BE54: 193.8 | BF54: 208.4 | BG54: 406.9 | BH54: 306 | BI54: 255.6 | BJ54: 186.2 | BK54: 182.9 | BL54: 205.8 | BM54: 228.9 | BN54: 218.9 | BO54: 231.4 | BP54: 243.5 | BQ54: 217.4 | BR54: 227.7 | BS54: 250.8 | BT54: 261.6 | BU54: 228.7 | BV54: 246.4 | BW54: 268.9 | BX54: 267 | BY54: 246
A55: =+A40+1 -> 43 | B55: Zolgensma | C55: NVS | D55: Rare | G55: Gene Therapy | H55: =SUM(AO55:GL55) -> 5845 | J55: =SUM(AO55:AR55) -> 721 | K55: =SUM(AS55:AV55) -> 1179 | L55: =SUM(AW55:AZ55) -> 1459 | M55: =SUM(BA55:BD55) -> 1248 | N55: =SUM(BE55:BH55) -> 1238 | O55: =SUM(BI55:BL55) -> 0 | P55: =SUM(BM55:BP55) -> 0 | Q55: =SUM(BQ55:BT55) -> 0 | R55: =SUM(BU55:BX55) -> 0 | S55: =SUM(BY55:CB55) -> 0 | T55: =SUM(CC55:CF55) -> 0 | U55: =SUM(CG55:CJ55) -> 0 | V55: =SUM(CK55:CN55) -> 0 | W55: =SUM(CO55:CR55) -> 0 | X55: =SUM(CS55:CV55) -> 0 | Y55: =SUM(CW55:CZ55) -> 0 | Z55: =SUM(DA55:DD55) -> 0 | AA55: =SUM(DE55:DH55) -> 0 | AB55: =SUM(DI55:DL55) -> 0 | AC55: =SUM(DM55:DP55) -> 0 | AD55: =SUM(DQ55:DT55) -> 0 | AE55: =SUM(DU55:DX55) -> 0 | AF55: =SUM(DY55:EB55) -> 0 | AG55: =SUM(EC55:EF55) -> 0 | AH55: =SUM(EG55:EJ55) -> 0 | AO55: 160 | AP55: 186 | AQ55: 170 | AR55: 205 | AS55: 291 | AT55: 254 | AU55: 319 | AV55: 315 | AW55: 375 | AX55: 342 | AY55: 363 | AZ55: 379 | BA55: 319 | BB55: 309 | BC55: 309 | BD55: 311 | BE55: 308 | BF55: 286 | BG55: 295 | BH55: 349
A56: =+A52+1 -> 45 | B56: Kesmipta | C56: NVS | H56: =SUM(AO56:GL56) -> 5086 | J56: =SUM(AO56:AR56) -> 131 | K56: =SUM(AS56:AV56) -> 690 | L56: =SUM(AW56:AZ56) -> 1531 | M56: =SUM(BA56:BD56) -> 2734 | N56: =SUM(BE56:BH56) -> 0 | O56: =SUM(BI56:BL56) -> 0 | P56: =SUM(BM56:BP56) -> 0 | Q56: =SUM(BQ56:BT56) -> 0 | R56: =SUM(BU56:BX56) -> 0 | S56: =SUM(BY56:CB56) -> 0 | T56: =SUM(CC56:CF56) -> 0 | U56: =SUM(CG56:CJ56) -> 0 | V56: =SUM(CK56:CN56) -> 0 | W56: =SUM(CO56:CR56) -> 0 | X56: =SUM(CS56:CV56) -> 0 | Y56: =SUM(CW56:CZ56) -> 0 | Z56: =SUM(DA56:DD56) -> 0 | AA56: =SUM(DE56:DH56) -> 0 | AB56: =SUM(DI56:DL56) -> 0 | AC56: =SUM(DM56:DP56) -> 0 | AD56: =SUM(DQ56:DT56) -> 0 | AE56: =SUM(DU56:DX56) -> 0 | AF56: =SUM(DY56:EB56) -> 0 | AG56: =SUM(EC56:EF56) -> 0 | AH56: =SUM(EG56:EJ56) -> 0 | AO56: 1 | AP56: 14 | AQ56: 50 | AR56: 66 | AS56: 109 | AT56: 147 | AU56: 195 | AV56: 239 | AW56: 289 | AX56: 369 | AY56: 384 | AZ56: 489 | BA56: 657 | BB56: 641 | BC56: 637 | BD56: 799
